Workbook

Sheet Rapport d'analyse
A6: Analyse NBA 2024-2025 – Mission Les Pionniers
C8: Projet 2 – Parcours Business Intelligence Analyst – OpenClassrooms
A10: 24 octobre 2025
A14: Henrique DA COSTA

Sheet Contexte_Objectif
A1: Contexte et objectifs
A3: Le club de basket Les Pionniers, structure semi-professionnelle, ambitionne de monter en division supérieure.
A5: Pour atteindre cet objectif, l’équipe souhaite s’appuyer sur une approche plus analytique de la performance
A6: sportive, inspirée des pratiques des grands clubs de la NBA dans les cinq prochaines saisons.
A8: Dans ce cadre, le club a mandaté notre Entreprise de Services Numériques (ESN) pour réaliser une analyse
A9: exploratoire des statistiques de la saison régulière NBA 2024/2025.
A11: L’objectif est double :
A13: 1️⃣ Identifier les facteurs clés de performance qui expliquent la réussite individuelle et collective des joueurs
A14: NBA ;
A15: 2️⃣ Déterminer les leviers d’amélioration que Les Pionniers pourraient adapter localement, tant sur le plan de
A16: l’entraînement, du recrutement, que du style de jeu.
A18: Cette première mission s’inscrit dans une démarche de data-driven performance, visant à utiliser les données
... A21: rebonds, efficacité, etc.), enrichies d’indicateurs complémentaires construits pour affiner l’analyse :
B23: Efficacité au tir (EFG%, TS%),
B24: Création et maîtrise du ballon (AST/TOV, AST/Min),
B25: Impact défensif (REB/Min, BLK/Min, STL/Min).
A27: À travers cette étude, le but est de produire une analyse lisible, visuelle et exploitable, permettant au staff
A28: technique des Pionniers d’orienter ses choix stratégiques et de définir des profils de joueurs cohérents avec ses
A29: ambitions sportives.

Sheet Méthodologie
A1: Méthodologie
A4: L’analyse a été conduite selon une démarche structurée en plusieurs étapes, inspirée des bonnes pratiques de la
A5: data analysis appliquée au sport de haut niveau.
A7: L’objectif était de garantir la fiabilité des données, la pertinence des indicateurs produits, et la lisibilité
A8: des résultats pour un public non technique.
A11: Préparation et nettoyage du jeu de données
A13: Le jeu de données utilisé correspond aux statistiques complètes de la saison régulière NBA 2024/2025.
A14: Une première étape a consisté à :
B16: Supprimer les lignes incomplètes ou comportant des valeurs manquantes ;
B17: Uniformiser les formats (décimales, pourcentages, noms d’équipes) ;
B18: Appliquer des filtres de cohérence pour ne conserver que les joueurs significatifs :
C19: => GP (Games Played) ≥ 30,
C20: => Min (Minutes jouées) ≥ 300.
A22: Ces traitements visent à éliminer les biais statistiques liés aux joueurs peu utilisés ou aux échantillons trop faibles.
A25: Enrichissement et création d’indicateurs
A27: Afin d’aller au-delà des données brutes, plusieurs indicateurs calculés ont été ajoutés pour analyser les
A28: dimensions clés de la performance (Cf. Dictionnaire de donnée enrichi ) :
A30: => Productivité offensive : PTS/Min, PTS_tot, FGA_tot ;
A31: => Efficacité au tir : EFG% = (FG + 0,5×3P)/FGA, TS% = PTS/(2×(FGA+0,44×FTA)) ;
A32: => Création et maîtrise : AST/TOV, AST/Min ;
A33: => Impact défensif : OREB/Min, DREB/Min, STL/Min, BLK/Min ;
A34: => Indices normalisés (FGA_norm, PTS_norm) pour faciliter la comparaison inter-joueurs.
A37: Des mises en forme conditionnelles ont ensuite été intégrées dans le tableau de données enrichi afin de
A38: visualiser instantanément les valeurs extrêmes et les tendances fortes (du rouge au vert pour les indicateurs de
A39: performance).
... A67: recrutement stratégique.

Sheet Données NBA enrichies
A1: Player | B1: Team | C1: Age | D1: GP | E1: W | F1: L | G1: Min | H1: PTS | I1: FGM | J1: FGA | K1: FG% | L1: 0.625 | M1: 3PA | N1: 3P% | O1: FTM | P1: FTA | Q1: FT% | R1: OREB | S1: DREB | T1: REB | U1: AST | V1: TOV | W1: STL | X1: BLK | Y1: PF | Z1: FP | AA1: DD2 | AB1: TD3 | AC1: ="+/-" -> +/- | AD1: OFFRTG | AE1: DEFRTG | AF1: NETRTG | AG1: AST% | AH1: AST/TO | AI1: AST RATIO | AJ1: OREB% | AK1: DREB% | AL1: REB% | AM1: TO RATIO | AN1: EFG% | AO1: TS% | AP1: USG% | AQ1: PACE | AR1: PIE | AS1: POSS | AT1: PTS_pg | AU1: AST_pg | AV1: REB_pg | AW1: OREB_pg | AX1: DREB_pg | AY1: STL_pg | AZ1: BLK_pg | BA1: TOV_pg | BB1: PTS_pg/Min | BC1: AST_pg/TOV_pg | BD1: STL_pg/Min | BE1: BLK_pg/Min | BF1: OREB_pg/Min | BG1: DREB_pg/Min | BH1: Classe_Min | BI1: Classe_Age | BJ1: EFG%_corr | BK1: TS%_corr | BL1: FGA_norm | BM1: Filtre joueur | BN1: PTS_pg_Norm | BO1: Min_tot | BP1: AST/Min | BQ1: AST/TOV | BR1: REB_pg/Min
A2: Shai Gilgeous-Alexander | B2: OKC | C2: 26 | D2: 76 | E2: 63 | F2: 13 | G2: 34.2 | H2: 2485 | I2: 859 | J2: 1657 | K2: 51.9 | L2: 160 | M2: 433 | N2: 37.5 | O2: 600 | P2: 669 | Q2: 89.8 | R2: 68 | S2: 312 | T2: 380 | U2: 486 | V2: 182 | W2: 129 | X2: 76 | Y2: 167 | Z2: 4112 | AA2: 6 | AB2: 0 | AC2: 12.1 | AD2: 122.4 | AE2: 105.7 | AF2: 16.7 | AG2: 29.9 | AH2: 2.66 | AI2: 18.7 | AJ2: 2.5 | AK2: 11.2 | AL2: 6.9 | AM2: 7 | AN2: 56.9 | AO2: 63.7 | AP2: 33.6 | AQ2: 101.91 | AR2: 19.9 | AS2: 5514 | AT2: =H2/D2 -> 32.697368 | AU2: =U2/D2 -> 6.3947368 | AV2: =T2/D2 -> 5 | AW2: =R2/D2 -> 0.89473684 | AX2: =S2/D2 -> 4.1052632 | AY2: =W2/D2 -> 1.6973684 | AZ2: =X2/D2 -> 1 | BA2: =V2/D2 -> 2.3947368 | BB2: =IF(G2>0,AT2/G2,"") -> 0.9560634 | BC2: =IF(BA2>0,AU2/BA2,"") -> 2.6703297 | BD2: =IF(G2>0,AY2/G2,"") -> 0.049630656 | BE2: =IF(G2>0,AZ2/G2,"") -> 0.029239766 | BF2: =IF(G2>0,AW2/G2,"") -> 0.026161896 | BG2: =IF(G2>0,AX2/G2,"") -> 0.12003693 | BH2: =IF(G2<10,"<10 min",IF(G2<20,"10–19 min",IF(G2<30,"20–29 min",IF(G2<40,"30–39 min","40+ min")))) -> 30–39 min | BI2: =IF(C2<23,"18–22",IF(C2<28,"23–27",IF(C2<33,"28–32","33+"))) -> 23–27 | BJ2: =AN2/100 -> 0.569 | BK2: =AO2/100 -> 0.637 | BL2: =J2/(MAX($J$2:$J$570)) -> 1 | BM2: =IF(AND(G2>=30,J2>=500),"Conserver","Écarter") -> Conserver | BN2: =AT2/(MAX($AT$2:$AT$570)) -> 1 | BO2: =G2*D2 -> 2599.2 | BP2: =IF(BO2>0,U2/BO2,"") -> 0.18698061 | BQ2: =IF(V2>0,U2/V2,0) -> 2.6703297 | BR2: =IF(G2>0,AV2/G2,"") -> 0.14619883
A3: Giannis Antetokounmpo | B3: MIL | C3: 30 | D3: 67 | E3: 40 | F3: 27 | G3: 34.2 | H3: 2037 | I3: 791 | J3: 1320 | K3: 60.1 | L3: 13 | M3: 60 | N3: 22.2 | O3: 436 | P3: 710 | Q3: 61.7 | R3: 147 | S3: 650 | T3: 797 | U3: 436 | V3: 208 | W3: 60 | X3: 80 | Y3: 154 | Z3: 3846 | AA3: 55 | AB3: 11 | AC3: 5 | AD3: 118.9 | AE3: 111.7 | AF3: 7.2 | AG3: 33.9 | AH3: 2.1 | AI3: 19.2 | AJ3: 6.7 | AK3: 26.6 | AL3: 17.2 | AM3: 9.1 | AN3: 60.7 | AO3: 62.5 | AP3: 34.6 | AQ3: 100.18 | AR3: 21 | AS3: 4772 | AT3: =H3/D3 -> 30.402985 | AU3: =U3/D3 -> 6.5074627 | AV3: =T3/D3 -> 11.895522 | AW3: =R3/D3 -> 2.1940299 | AX3: =S3/D3 -> 9.7014925 | AY3: =W3/D3 -> 0.89552239 | AZ3: =X3/D3 -> 1.1940299 | BA3: =V3/D3 -> 3.1044776 | BB3: =IF(G3>0,AT3/G3,"") -> 0.88897617 | BC3: =IF(BA3>0,AU3/BA3,"") -> 2.0961538 | BD3: =IF(G3>0,AY3/G3,"") -> 0.026184865 | BE3: =IF(G3>0,AZ3/G3,"") -> 0.034913154 | BF3: =IF(G3>0,AW3/G3,"") -> 0.06415292 | BG3: =IF(G3>0,AX3/G3,"") -> 0.28366937 | BH3: =IF(G3<10,"<10 min",IF(G3<20,"10–19 min",IF(G3<30,"20–29 min",IF(G3<40,"30–39 min","40+ min")))) -> 30–39 min | BI3: =IF(C3<23,"18–22",IF(C3<28,"23–27",IF(C3<33,"28–32","33+"))) -> 28–32 | BJ3: =AN3/100 -> 0.607 | BK3: =AO3/100 -> 0.625 | BL3: =J3/(MAX($J$2:$J$570)) -> 0.7966204 | BM3: =IF(AND(G3>=30,J3>=500),"Conserver","Écarter") -> Conserver | BN3: =AT3/(MAX($AT$2:$AT$570)) -> 0.92982972 | BO3: =G3*D3 -> 2291.4 | BP3: =IF(BO3>0,U3/BO3,"") -> 0.19027669 | BQ3: =IF(V3>0,U3/V3,0) -> 2.0961538 | BR3: =IF(G3>0,AV3/G3,"") -> 0.34782229
A4: Nikola Jokić | B4: DEN | C4: 30 | D4: 70 | E4: 46 | F4: 24 | G4: 36.7 | H4: 2072 | I4: 784 | J4: 1365 | K4: 57.6 | L4: 140 | M4: 329 | N4: 41.7 | O4: 364 | P4: 448 | Q4: 80 | R4: 203 | S4: 693 | T4: 889 | U4: 714 | V4: 231 | W4: 126 | X4: 42 | Y4: 161 | Z4: 4501 | AA4: 59 | AB4: 34 | AC4: 8.5 | AD4: 125.6 | AE4: 115.1 | AF4: 10.5 | AG4: 39.8 | AH4: 3.11 | AI4: 28.7 | AJ4: 8.3 | AK4: 25.2 | AL4: 17.3 | AM4: 9.2 | AN4: 62.7 | AO4: 66.3 | AP4: 28.5 | AQ4: 101.99 | AR4: 20.6 | AS4: 5471 | AT4: =H4/D4 -> 29.6 | AU4: =U4/D4 -> 10.2 | AV4: =T4/D4 -> 12.7 | AW4: =R4/D4 -> 2.9 | AX4: =S4/D4 -> 9.9 | AY4: =W4/D4 -> 1.8 | AZ4: =X4/D4 -> 0.6 | BA4: =V4/D4 -> 3.3 | BB4: =IF(G4>0,AT4/G4,"") -> 0.80653951 | BC4: =IF(BA4>0,AU4/BA4,"") -> 3.0909091 | BD4: =IF(G4>0,AY4/G4,"") -> 0.049046322 | BE4: =IF(G4>0,AZ4/G4,"") -> 0.016348774 | BF4: =IF(G4>0,AW4/G4,"") -> 0.079019074 | BG4: =IF(G4>0,AX4/G4,"") -> 0.26975477 | BH4: =IF(G4<10,"<10 min",IF(G4<20,"10–19 min",IF(G4<30,"20–29 min",IF(G4<40,"30–39 min","40+ min")))) -> 30–39 min | BI4: =IF(C4<23,"18–22",IF(C4<28,"23–27",IF(C4<33,"28–32","33+"))) -> 28–32 | BJ4: =AN4/100 -> 0.627 | BK4: =AO4/100 -> 0.663 | BL4: =J4/(MAX($J$2:$J$570)) -> 0.82377791 | BM4: =IF(AND(G4>=30,J4>=500),"Conserver","Écarter") -> Conserver | BN4: =AT4/(MAX($AT$2:$AT$570)) -> 0.90527163 | BO4: =G4*D4 -> 2569 | BP4: =IF(BO4>0,U4/BO4,"") -> 0.27792916 | BQ4: =IF(V4>0,U4/V4,0) -> 3.0909091 | BR4: =IF(G4>0,AV4/G4,"") -> 0.34604905
A5: Luka Dončić | B5: LAL | C5: 26 | D5: 50 | E5: 31 | F5: 19 | G5: 35.4 | H5: 1410 | I5: 460 | J5: 1025 | K5: 45 | L5: 175 | M5: 480 | N5: 36.8 | O5: 310 | P5: 395 | Q5: 78.2 | R5: 40 | S5: 370 | T5: 410 | U5: 385 | V5: 180 | W5: 90 | X5: 20 | Y5: 125 | Z5: 2625 | AA5: 21 | AB5: 5 | AC5: 6.9 | AD5: 119.6 | AE5: 110.5 | AF5: 9.1 | AG5: 34.2 | AH5: 2.14 | AI5: 21.8 | AJ5: 2.3 | AK5: 19.8 | AL5: 11.2 | AM5: 10.2 | AN5: 53.6 | AO5: 58.7 | AP5: 32.8 | AQ5: 100.22 | AR5: 17 | AS5: 3696 | AT5: =H5/D5 -> 28.2 | AU5: =U5/D5 -> 7.7 | AV5: =T5/D5 -> 8.2 | AW5: =R5/D5 -> 0.8 | AX5: =S5/D5 -> 7.4 | AY5: =W5/D5 -> 1.8 | AZ5: =X5/D5 -> 0.4 | BA5: =V5/D5 -> 3.6 | BB5: =IF(G5>0,AT5/G5,"") -> 0.79661017 | BC5: =IF(BA5>0,AU5/BA5,"") -> 2.1388889 | BD5: =IF(G5>0,AY5/G5,"") -> 0.050847458 | BE5: =IF(G5>0,AZ5/G5,"") -> 0.011299435 | BF5: =IF(G5>0,AW5/G5,"") -> 0.02259887 | BG5: =IF(G5>0,AX5/G5,"") -> 0.20903955 | BH5: =IF(G5<10,"<10 min",IF(G5<20,"10–19 min",IF(G5<30,"20–29 min",IF(G5<40,"30–39 min","40+ min")))) -> 30–39 min | BI5: =IF(C5<23,"18–22",IF(C5<28,"23–27",IF(C5<33,"28–32","33+"))) -> 23–27 | BJ5: =AN5/100 -> 0.536 | BK5: =AO5/100 -> 0.587 | BL5: =J5/(MAX($J$2:$J$570)) -> 0.61858781 | BM5: =IF(AND(G5>=30,J5>=500),"Conserver","Écarter") -> Conserver | BN5: =AT5/(MAX($AT$2:$AT$570)) -> 0.86245473 | BO5: =G5*D5 -> 1770 | BP5: =IF(BO5>0,U5/BO5,"") -> 0.21751412 | BQ5: =IF(V5>0,U5/V5,0) -> 2.1388889 | BR5: =IF(G5>0,AV5/G5,"") -> 0.23163842
A6: Anthony Edwards | B6: MIN | C6: 23 | D6: 79 | E6: 48 | F6: 31 | G6: 36.3 | H6: 2180 | I6: 719 | J6: 1612 | K6: 44.7 | L6: 324 | M6: 814 | N6: 39.5 | O6: 419 | P6: 498 | Q6: 83.7 | R6: 63 | S6: 387 | T6: 450 | U6: 356 | V6: 253 | W6: 95 | X6: 47 | Y6: 150 | Z6: 3429 | AA6: 7 | AB6: 0 | AC6: 3.7 | AD6: 116.2 | AE6: 111.4 | AF6: 4.8 | AG6: 20.9 | AH6: 1.44 | AI6: 14.8 | AJ6: 2.1 | AK6: 13.1 | AL6: 7.7 | AM6: 10.3 | AN6: 54.7 | AO6: 59.5 | AP6: 30.7 | AQ6: 98.27 | AR6: 14 | AS6: 5883 | AT6: =H6/D6 -> 27.594937 | AU6: =U6/D6 -> 4.5063291 | AV6: =T6/D6 -> 5.6962025 | AW6: =R6/D6 -> 0.79746835 | AX6: =S6/D6 -> 4.8987342 | AY6: =W6/D6 -> 1.2025316 | AZ6: =X6/D6 -> 0.59493671 | BA6: =V6/D6 -> 3.2025316 | BB6: =IF(G6>0,AT6/G6,"") -> 0.76019109 | BC6: =IF(BA6>0,AU6/BA6,"") -> 1.4071146 | BD6: =IF(G6>0,AY6/G6,"") -> 0.033127594 | BE6: =IF(G6>0,AZ6/G6,"") -> 0.016389441 | BF6: =IF(G6>0,AW6/G6,"") -> 0.021968825 | BG6: =IF(G6>0,AX6/G6,"") -> 0.13495135 | BH6: =IF(G6<10,"<10 min",IF(G6<20,"10–19 min",IF(G6<30,"20–29 min",IF(G6<40,"30–39 min","40+ min")))) -> 30–39 min | BI6: =IF(C6<23,"18–22",IF(C6<28,"23–27",IF(C6<33,"28–32","33+"))) -> 23–27 | BJ6: =AN6/100 -> 0.547 | BK6: =AO6/100 -> 0.595 | BL6: =J6/(MAX($J$2:$J$570)) -> 0.97284249 | BM6: =IF(AND(G6>=30,J6>=500),"Conserver","Écarter") -> Conserver | BN6: =AT6/(MAX($AT$2:$AT$570)) -> 0.84394977 | BO6: =G6*D6 -> 2867.7 | BP6: =IF(BO6>0,U6/BO6,"") -> 0.1241413 | BQ6: =IF(V6>0,U6/V6,0) -> 1.4071146 | BR6: =IF(G6>0,AV6/G6,"") -> 0.15692018
A7: Jayson Tatum | B7: BOS | C7: 27 | D7: 72 | E7: 53 | F7: 19 | G7: 36.4 | H7: 1930 | I7: 662 | J7: 1462 | K7: 45.2 | L7: 252 | M7: 727 | N7: 34.3 | O7: 360 | P7: 439 | Q7: 81.4 | R7: 50 | S7: 576 | T7: 626 | U7: 432 | V7: 209 | W7: 79 | X7: 36 | Y7: 158 | Z7: 3456 | AA7: 31 | AB7: 2 | AC7: 7.4 | AD7: 119.6 | AE7: 109.8 | AF7: 9.8 | AG7: 26.6 | AH7: 2.6 | AI7: 18.9 | AJ7: 1.7 | AK7: 20.6 | AL7: 11.2 | AM7: 9.2 | AN7: 53.7 | AO7: 58.2 | AP7: 30.1 | AQ7: 98.14 | AR7: 15.8 | AS7: 5368 | AT7: =H7/D7 -> 26.805556 | AU7: =U7/D7 -> 6 | AV7: =T7/D7 -> 8.6944444 | AW7: =R7/D7 -> 0.69444444 | AX7: =S7/D7 -> 8 | AY7: =W7/D7 -> 1.0972222 | AZ7: =X7/D7 -> 0.5 | BA7: =V7/D7 -> 2.9027778 | BB7: =IF(G7>0,AT7/G7,"") -> 0.73641636 | BC7: =IF(BA7>0,AU7/BA7,"") -> 2.0669856 | BD7: =IF(G7>0,AY7/G7,"") -> 0.030143468 | BE7: =IF(G7>0,AZ7/G7,"") -> 0.013736264 | BF7: =IF(G7>0,AW7/G7,"") -> 0.019078144 | BG7: =IF(G7>0,AX7/G7,"") -> 0.21978022 | BH7: =IF(G7<10,"<10 min",IF(G7<20,"10–19 min",IF(G7<30,"20–29 min",IF(G7<40,"30–39 min","40+ min")))) -> 30–39 min | BI7: =IF(C7<23,"18–22",IF(C7<28,"23–27",IF(C7<33,"28–32","33+"))) -> 23–27 | BJ7: =AN7/100 -> 0.537 | BK7: =AO7/100 -> 0.582 | BL7: =J7/(MAX($J$2:$J$570)) -> 0.88231744 | BM7: =IF(AND(G7>=30,J7>=500),"Conserver","Écarter") -> Conserver | BN7: =AT7/(MAX($AT$2:$AT$570)) -> 0.81980774 | BO7: =G7*D7 -> 2620.8 | BP7: =IF(BO7>0,U7/BO7,"") -> 0.16483516 | BQ7: =IF(V7>0,U7/V7,0) -> 2.0669856 | BR7: =IF(G7>0,AV7/G7,"") -> 0.23885836
A8: Kevin Durant | B8: PHX | C8: 36 | D8: 62 | E8: 33 | F8: 29 | G8: 36.5 | H8: 1649 | I8: 589 | J8: 1122 | K8: 52.7 | L8: 161 | M8: 372 | N8: 43 | O8: 304 | P8: 360 | Q8: 83.9 | R8: 25 | S8: 353 | T8: 372 | U8: 260 | V8: 192 | W8: 50 | X8: 74 | Y8: 105 | Z8: 2678 | AA8: 5 | AB8: 0 | AC8: -0.6 | AD8: 116.5 | AE8: 117.4 | AF8: -1 | AG8: 18.8 | AH8: 1.38 | AI8: 15.2 | AJ8: 1.1 | AK8: 14.7 | AL8: 8.4 | AM8: 11 | AN8: 59.8 | AO8: 64.2 | AP8: 28.3 | AQ8: 99.49 | AR8: 14.2 | AS8: 4697 | AT8: =H8/D8 -> 26.596774 | AU8: =U8/D8 -> 4.1935484 | AV8: =T8/D8 -> 6 | AW8: =R8/D8 -> 0.40322581 | AX8: =S8/D8 -> 5.6935484 | AY8: =W8/D8 -> 0.80645161 | AZ8: =X8/D8 -> 1.1935484 | BA8: =V8/D8 -> 3.0967742 | BB8: =IF(G8>0,AT8/G8,"") -> 0.72867875 | BC8: =IF(BA8>0,AU8/BA8,"") -> 1.3541667 | BD8: =IF(G8>0,AY8/G8,"") -> 0.022094565 | BE8: =IF(G8>0,AZ8/G8,"") -> 0.032699956 | BF8: =IF(G8>0,AW8/G8,"") -> 0.011047282 | BG8: =IF(G8>0,AX8/G8,"") -> 0.15598763 | BH8: =IF(G8<10,"<10 min",IF(G8<20,"10–19 min",IF(G8<30,"20–29 min",IF(G8<40,"30–39 min","40+ min")))) -> 30–39 min | BI8: =IF(C8<23,"18–22",IF(C8<28,"23–27",IF(C8<33,"28–32","33+"))) -> 33+ | BJ8: =AN8/100 -> 0.598 | BK8: =AO8/100 -> 0.642 | BL8: =J8/(MAX($J$2:$J$570)) -> 0.67712734 | BM8: =IF(AND(G8>=30,J8>=500),"Conserver","Écarter") -> Conserver | BN8: =AT8/(MAX($AT$2:$AT$570)) -> 0.81342247 | BO8: =G8*D8 -> 2263 | BP8: =IF(BO8>0,U8/BO8,"") -> 0.11489174 | BQ8: =IF(V8>0,U8/V8,0) -> 1.3541667 | BR8: =IF(G8>0,AV8/G8,"") -> 0.16438356
A9: Tyrese Maxey | B9: PHI | C9: 24 | D9: 52 | E9: 20 | F9: 32 | G9: 37.7 | H9: 1368 | I9: 478 | J9: 1092 | K9: 43.7 | L9: 161 | M9: 478 | N9: 33.7 | O9: 255 | P9: 291 | Q9: 87.9 | R9: 16 | S9: 161 | T9: 172 | U9: 317 | V9: 125 | W9: 94 | X9: 21 | Y9: 114 | Z9: 2267 | AA9: 8 | AB9: 1 | AC9: -2.4 | AD9: 113.8 | AE9: 117.4 | AF9: -3.5 | AG9: 27.6 | AH9: 2.56 | AI9: 19.2 | AJ9: 0.7 | AK9: 8.7 | AL9: 4.5 | AM9: 7.5 | AN9: 51.1 | AO9: 56.2 | AP9: 29.3 | AQ9: 98.34 | AR9: 12.7 | AS9: 4024 | AT9: =H9/D9 -> 26.307692 | AU9: =U9/D9 -> 6.0961538 | AV9: =T9/D9 -> 3.3076923 | AW9: =R9/D9 -> 0.30769231 | AX9: =S9/D9 -> 3.0961538 | AY9: =W9/D9 -> 1.8076923 | AZ9: =X9/D9 -> 0.40384615 | BA9: =V9/D9 -> 2.4038462 | BB9: =IF(G9>0,AT9/G9,"") -> 0.69781677 | BC9: =IF(BA9>0,AU9/BA9,"") -> 2.536 | BD9: =IF(G9>0,AY9/G9,"") -> 0.047949398 | BE9: =IF(G9>0,AZ9/G9,"") -> 0.0107121 | BF9: =IF(G9>0,AW9/G9,"") -> 0.0081615997 | BG9: =IF(G9>0,AX9/G9,"") -> 0.082126097 | BH9: =IF(G9<10,"<10 min",IF(G9<20,"10–19 min",IF(G9<30,"20–29 min",IF(G9<40,"30–39 min","40+ min")))) -> 30–39 min | BI9: =IF(C9<23,"18–22",IF(C9<28,"23–27",IF(C9<33,"28–32","33+"))) -> 23–27 | BJ9: =AN9/100 -> 0.511 | BK9: =AO9/100 -> 0.562 | BL9: =J9/(MAX($J$2:$J$570)) -> 0.65902233 | BM9: =IF(AND(G9>=30,J9>=500),"Conserver","Écarter") -> Conserver | BN9: =AT9/(MAX($AT$2:$AT$570)) -> 0.80458133 | BO9: =G9*D9 -> 1960.4 | BP9: =IF(BO9>0,U9/BO9,"") -> 0.16170169 | BQ9: =IF(V9>0,U9/V9,0) -> 2.536 | BR9: =IF(G9>0,AV9/G9,"") -> 0.087737196
A10: Cade Cunningham | B10: DET | C10: 23 | D10: 70 | E10: 38 | F10: 32 | G10: 35 | H10: 1827 | I10: 686 | J10: 1456 | K10: 46.9 | L10: 147 | M10: 420 | N10: 35.6 | O10: 315 | P10: 371 | Q10: 84.6 | R10: 56 | S10: 371 | T10: 427 | U10: 637 | V10: 308 | W10: 70 | X10: 56 | Y10: 196 | Z10: 3360 | AA10: 31 | AB10: 9 | AC10: 2.5 | AD10: 115 | AE10: 112.2 | AF10: 2.8 | AG10: 40.9 | AH10: 2.06 | AI10: 25 | AJ10: 2.3 | AK10: 14.7 | AL10: 8.6 | AM10: 12.1 | AN10: 52.1 | AO10: 56.5 | AP10: 32.3 | AQ10: 101.57 | AR10: 15.2 | AS10: 5201 | AT10: =H10/D10 -> 26.1 | AU10: =U10/D10 -> 9.1 | AV10: =T10/D10 -> 6.1 | AW10: =R10/D10 -> 0.8 | AX10: =S10/D10 -> 5.3 | AY10: =W10/D10 -> 1 | AZ10: =X10/D10 -> 0.8 | BA10: =V10/D10 -> 4.4 | BB10: =IF(G10>0,AT10/G10,"") -> 0.74571429 | BC10: =IF(BA10>0,AU10/BA10,"") -> 2.0681818 | BD10: =IF(G10>0,AY10/G10,"") -> 0.028571429 | BE10: =IF(G10>0,AZ10/G10,"") -> 0.022857143 | BF10: =IF(G10>0,AW10/G10,"") -> 0.022857143 | BG10: =IF(G10>0,AX10/G10,"") -> 0.15142857 | BH10: =IF(G10<10,"<10 min",IF(G10<20,"10–19 min",IF(G10<30,"20–29 min",IF(G10<40,"30–39 min","40+ min")))) -> 30–39 min | BI10: =IF(C10<23,"18–22",IF(C10<28,"23–27",IF(C10<33,"28–32","33+"))) -> 23–27 | BJ10: =AN10/100 -> 0.521 | BK10: =AO10/100 -> 0.565 | BL10: =J10/(MAX($J$2:$J$570)) -> 0.87869644 | BM10: =IF(AND(G10>=30,J10>=500),"Conserver","Écarter") -> Conserver | BN10: =AT10/(MAX($AT$2:$AT$570)) -> 0.79822938 | BO10: =G10*D10 -> 2450 | BP10: =IF(BO10>0,U10/BO10,"") -> 0.26 | BQ10: =IF(V10>0,U10/V10,0) -> 2.0681818 | BR10: =IF(G10>0,AV10/G10,"") -> 0.17428571
A11: Jalen Brunson | B11: NYK | C11: 28 | D11: 65 | E11: 40 | F11: 25 | G11: 35.4 | H11: 1690 | I11: 585 | J11: 1203 | K11: 48.8 | L11: 150 | M11: 397 | N11: 38.3 | O11: 371 | P11: 449 | Q11: 82.1 | R11: 26 | S11: 163 | T11: 189 | U11: 475 | V11: 163 | W11: 59 | X11: 7 | Y11: 137 | Z11: 2665 | AA11: 14 | AB11: 0 | AC11: 2.2 | AD11: 118.3 | AE11: 115.7 | AF11: 2.6 | AG11: 31.8 | AH11: 2.9 | AI11: 23.5 | AJ11: 1.2 | AK11: 7.2 | AL11: 4.2 | AM11: 8.1 | AN11: 55.1 | AO11: 60.5 | AP11: 28.9 | AQ11: 97.79 | AR11: 13.8 | AS11: 4697 | AT11: =H11/D11 -> 26 | AU11: =U11/D11 -> 7.3076923 | AV11: =T11/D11 -> 2.9076923 | AW11: =R11/D11 -> 0.4 | AX11: =S11/D11 -> 2.5076923 | AY11: =W11/D11 -> 0.90769231 | AZ11: =X11/D11 -> 0.10769231 | BA11: =V11/D11 -> 2.5076923 | BB11: =IF(G11>0,AT11/G11,"") -> 0.73446328 | BC11: =IF(BA11>0,AU11/BA11,"") -> 2.9141104 | BD11: =IF(G11>0,AY11/G11,"") -> 0.025641026 | BE11: =IF(G11>0,AZ11/G11,"") -> 0.0030421556 | BF11: =IF(G11>0,AW11/G11,"") -> 0.011299435 | BG11: =IF(G11>0,AX11/G11,"") -> 0.070838766 | BH11: =IF(G11<10,"<10 min",IF(G11<20,"10–19 min",IF(G11<30,"20–29 min",IF(G11<40,"30–39 min","40+ min")))) -> 30–39 min | BI11: =IF(C11<23,"18–22",IF(C11<28,"23–27",IF(C11<33,"28–32","33+"))) -> 28–32 | BJ11: =AN11/100 -> 0.551 | BK11: =AO11/100 -> 0.605 | BL11: =J11/(MAX($J$2:$J$570)) -> 0.72601086 | BM11: =IF(AND(G11>=30,J11>=500),"Conserver","Écarter") -> Conserver | BN11: =AT11/(MAX($AT$2:$AT$570)) -> 0.79517103 | BO11: =G11*D11 -> 2301 | BP11: =IF(BO11>0,U11/BO11,"") -> 0.20643199 | BQ11: =IF(V11>0,U11/V11,0) -> 2.9141104 | BR11: =IF(G11>0,AV11/G11,"") -> 0.082138201
A12: Paolo Banchero | B12: ORL | C12: 22 | D12: 46 | E12: 21 | F12: 25 | G12: 34.4 | H12: 1191 | I12: 414 | J12: 911 | K12: 45.2 | L12: 87 | M12: 271 | N12: 32 | O12: 281 | P12: 386 | Q12: 72.7 | R12: 51 | S12: 294 | T12: 345 | U12: 221 | V12: 138 | W12: 37 | X12: 28 | Y12: 97 | Z12: 1992 | AA12: 11 | AB12: 0 | AC12: -0.5 | AD12: 109.1 | AE12: 109.6 | AF12: -0.6 | AG12: 26.2 | AH12: 1.61 | AI12: 15.3 | AJ12: 3.1 | AK12: 19.2 | AL12: 10.8 | AM12: 9.5 | AN12: 50 | AO12: 55.1 | AP12: 33 | AQ12: 97.29 | AR12: 15.7 | AS12: 3204 | AT12: =H12/D12 -> 25.891304 | AU12: =U12/D12 -> 4.8043478 | AV12: =T12/D12 -> 7.5 | AW12: =R12/D12 -> 1.1086957 | AX12: =S12/D12 -> 6.3913043 | AY12: =W12/D12 -> 0.80434783 | AZ12: =X12/D12 -> 0.60869565 | BA12: =V12/D12 -> 3 | BB12: =IF(G12>0,AT12/G12,"") -> 0.7526542 | BC12: =IF(BA12>0,AU12/BA12,"") -> 1.6014493 | BD12: =IF(G12>0,AY12/G12,"") -> 0.023382204 | BE12: =IF(G12>0,AZ12/G12,"") -> 0.017694641 | BF12: =IF(G12>0,AW12/G12,"") -> 0.032229525 | BG12: =IF(G12>0,AX12/G12,"") -> 0.18579373 | BH12: =IF(G12<10,"<10 min",IF(G12<20,"10–19 min",IF(G12<30,"20–29 min",IF(G12<40,"30–39 min","40+ min")))) -> 30–39 min | BI12: =IF(C12<23,"18–22",IF(C12<28,"23–27",IF(C12<33,"28–32","33+"))) -> 18–22 | BJ12: =AN12/100 -> 0.5 | BK12: =AO12/100 -> 0.551 | BL12: =J12/(MAX($J$2:$J$570)) -> 0.54978877 | BM12: =IF(AND(G12>=30,J12>=500),"Conserver","Écarter") -> Conserver | BN12: =AT12/(MAX($AT$2:$AT$570)) -> 0.79184673 | BO12: =G12*D12 -> 1582.4 | BP12: =IF(BO12>0,U12/BO12,"") -> 0.13966127 | BQ12: =IF(V12>0,U12/V12,0) -> 1.6014493 | BR12: =IF(G12>0,AV12/G12,"") -> 0.21802326
A13: Devin Booker | B13: PHX | C13: 28 | D13: 75 | E13: 35 | F13: 40 | G13: 37.3 | H13: 1920 | I13: 653 | J13: 1418 | K13: 46.1 | L13: 180 | M13: 548 | N13: 33.2 | O13: 435 | P13: 480 | Q13: 89.4 | R13: 75 | S13: 233 | T13: 308 | U13: 533 | V13: 218 | W13: 68 | X13: 15 | Y13: 195 | Z13: 3113 | AA13: 16 | AB13: 0 | AC13: -2.4 | AD13: 115.3 | AE13: 118.5 | AF13: -3.2 | AG13: 30.1 | AH13: 2.4 | AI13: 22.4 | AJ13: 2.8 | AK13: 8 | AL13: 5.5 | AM13: 9.3 | AN13: 52.5 | AO13: 58.9 | AP13: 28.5 | AQ13: 98.72 | AR13: 12.2 | AS13: 5752 | AT13: =H13/D13 -> 25.6 | AU13: =U13/D13 -> 7.1066667 | AV13: =T13/D13 -> 4.1066667 | AW13: =R13/D13 -> 1 | AX13: =S13/D13 -> 3.1066667 | AY13: =W13/D13 -> 0.90666667 | AZ13: =X13/D13 -> 0.2 | BA13: =V13/D13 -> 2.9066667 | BB13: =IF(G13>0,AT13/G13,"") -> 0.68632708 | BC13: =IF(BA13>0,AU13/BA13,"") -> 2.4449541 | BD13: =IF(G13>0,AY13/G13,"") -> 0.024307417 | BE13: =IF(G13>0,AZ13/G13,"") -> 0.0053619303 | BF13: =IF(G13>0,AW13/G13,"") -> 0.026809651 | BG13: =IF(G13>0,AX13/G13,"") -> 0.083288651 | BH13: =IF(G13<10,"<10 min",IF(G13<20,"10–19 min",IF(G13<30,"20–29 min",IF(G13<40,"30–39 min","40+ min")))) -> 30–39 min | BI13: =IF(C13<23,"18–22",IF(C13<28,"23–27",IF(C13<33,"28–32","33+"))) -> 28–32 | BJ13: =AN13/100 -> 0.525 | BK13: =AO13/100 -> 0.589 | BL13: =J13/(MAX($J$2:$J$570)) -> 0.85576343 | BM13: =IF(AND(G13>=30,J13>=500),"Conserver","Écarter") -> Conserver | BN13: =AT13/(MAX($AT$2:$AT$570)) -> 0.78293763 | BO13: =G13*D13 -> 2797.5 | BP13: =IF(BO13>0,U13/BO13,"") -> 0.19052726 | BQ13: =IF(V13>0,U13/V13,0) -> 2.4449541 | BR13: =IF(G13>0,AV13/G13,"") -> 0.1100983
... A570: Jalen McDaniels | B570: WAS | C570: 27 | D570: 4 | E570: 2 | F570: 2 | G570: 1.8 | H570: 0 | I570: 0 | J570: 0 | K570: 0 | L570: 0 | M570: 0 | N570: 0 | O570: 0 | P570: 0 | Q570: 0 | R570: 0 | S570: 0 | T570: 0 | U570: 1 | V570: 0 | W570: 1 | X570: 0 | Y570: 0 | Z570: 4 | AA570: 0 | AB570: 0 | AC570: -0.3 | AD570: 81.3 | AE570: 77.8 | AF570: 3.5 | AG570: 25 | AH570: 0 | AI570: 100 | AJ570: 0 | AK570: 0 | AL570: 0 | AM570: 0 | AN570: 0 | AO570: 0 | AP570: 0 | AQ570: 111.25 | AR570: 11.4 | AS570: 16 | AT570: =H570/D570 -> 0 | AU570: =U570/D570 -> 0.25 | AV570: =T570/D570 -> 0 | AW570: =R570/D570 -> 0 | AX570: =S570/D570 -> 0 | AY570: =W570/D570 -> 0.25 | AZ570: =X570/D570 -> 0 | BA570: =V570/D570 -> 0 | BB570: =IF(G570>0,AT570/G570,"") -> 0 | BC570: =IF(BA570>0,AU570/BA570,"") | BD570: =IF(G570>0,AY570/G570,"") -> 0.13888889 | BE570: =IF(G570>0,AZ570/G570,"") -> 0 | BF570: =IF(G570>0,AW570/G570,"") -> 0 | BG570: =IF(G570>0,AX570/G570,"") -> 0 | BH570: =IF(G570<10,"<10 min",IF(G570<20,"10–19 min",IF(G570<30,"20–29 min",IF(G570<40,"30–39 min","40+ min")))) -> <10 min | BI570: =IF(C570<23,"18–22",IF(C570<28,"23–27",IF(C570<33,"28–32","33+"))) -> 23–27 | BJ570: =AN570/100 -> 0 | BK570: =AO570/100 -> 0 | BL570: =J570/(MAX($J$2:$J$570)) -> 0 | BM570: =IF(AND(G570>=30,J570>=500),"Conserver","Écarter") -> Écarter | BN570: =AT570/(MAX($AT$2:$AT$570)) -> 0 | BO570: =G570*D570 -> 7.2 | BP570: =IF(BO570>0,U570/BO570,"") -> 0.13888889 | BQ570: =IF(V570>0,U570/V570,0) -> 0 | BR570: =IF(G570>0,AV570/G570,"") -> 0

Sheet Filtres_Zones_Critères
BT1: Zones de critères
A2: Sélections selon filtres élaborés divers
BT3: Tot_Min >1000 | BX3: Top Players PTS_pg
BT5: Min_tot | BX5: Players | BZ5: PTS_pg
BT6: >1000 | BX6: Shai Gilgeous-Alexander | BZ6: 32.697368
BX7: Giannis Antetokounmpo | BZ7: 30.402985
A8: Tableau de données complet | BX8: Nikola Jokić | BZ8: 29.6
BX9: Luka Dončić | BZ9: 28.2
A10: Player | B10: Team | C10: Age | D10: GP | E10: W | F10: L | G10: Min | H10: PTS | I10: FGM | J10: FGA | K10: FG% | L10: 15:00 | M10: 3PA | N10: 3P% | O10: FTM | P10: FTA | Q10: FT% | R10: OREB | S10: DREB | T10: REB | U10: AST | V10: TOV | W10: STL | X10: BLK | Y10: PF | Z10: FP | AA10: DD2 | AB10: TD3 | AC10: +/- | AD10: OFFRTG | AE10: DEFRTG | AF10: NETRTG | AG10: AST% | AH10: AST/TO | AI10: AST RATIO | AJ10: OREB% | AK10: DREB% | AL10: REB% | AM10: TO RATIO | AN10: EFG% | AO10: TS% | AP10: USG% | AQ10: PACE | AR10: PIE | AS10: POSS | AT10: PTS_pg | AU10: AST_pg | AV10: REB_pg | AW10: OREB_pg | AX10: DREB_pg | AY10: STL_pg | AZ10: BLK_pg | BA10: TOV_pg | BB10: PTS_pg/Min | BC10: AST_pg/TOV_pg | BD10: STL_pg/Min | BE10: BLK_pg/Min | BF10: OREB_pg/Min | BG10: DREB_pg/Min | BH10: Classe_Min | BI10: Classe_Age | BJ10: EFG%_corr | BK10: TS%_corr | BL10: FGA_norm | BM10: Filtre joueur | BN10: PTG_pg_Norm | BO10: Min_tot | BP10: AST/Min | BQ10: AST/TOV | BR10: REB_pg/Min | BS10: Def Impact Score | BT10: Moy. Gén. Réussite Tirs | BU10: Moy. Gén. Réussite 3 Points | BV10: Moy. Gén. Réussite Lancers Francs | BX10: Anthony Edwards | BZ10: 27.594937
A11: Shai Gilgeous-Alexander | B11: OKC | C11: 26 | D11: 76 | E11: 63 | F11: 13 | G11: 34.2 | H11: 2485 | I11: 859 | J11: 1657 | K11: 51.9 | L11: 160 | M11: 433 | N11: 37.5 | O11: 600 | P11: 669 | Q11: 89.8 | R11: 68 | S11: 312 | T11: 380 | U11: 486 | V11: 182 | W11: 129 | X11: 76 | Y11: 167 | Z11: 4112 | AA11: 6 | AB11: 0 | AC11: 12.1 | AD11: 122.4 | AE11: 105.7 | AF11: 16.7 | AG11: 29.9 | AH11: 2.66 | AI11: 18.7 | AJ11: 2.5 | AK11: 11.2 | AL11: 6.9 | AM11: 7 | AN11: 56.9 | AO11: 63.7 | AP11: 33.6 | AQ11: 101.91 | AR11: 19.9 | AS11: 5514 | AT11: =H11/D11 -> 32.697368 | AU11: =U11/D11 -> 6.3947368 | AV11: =T11/D11 -> 5 | AW11: =R11/D11 -> 0.89473684 | AX11: =S11/D11 -> 4.1052632 | AY11: =W11/D11 -> 1.6973684 | AZ11: =X11/D11 -> 1 | BA11: =V11/D11 -> 2.3947368 | BB11: =IF(G11>0,AT11/G11,"") -> 0.9560634 | BC11: =IF(BA11>0,AU11/BA11,"") -> 2.6703297 | BD11: =IF(G11>0,AY11/G11,"") -> 0.049630656 | BE11: =IF(G11>0,AZ11/G11,"") -> 0.029239766 | BF11: =IF(G11>0,AW11/G11,"") -> 0.026161896 | BG11: =IF(G11>0,AX11/G11,"") -> 0.12003693 | BH11: =IF(G11<10,"<10 min",IF(G11<20,"10–19 min",IF(G11<30,"20–29 min",IF(G11<40,"30–39 min","40+ min")))) -> 30–39 min | BI11: =IF(C11<23,"18–22",IF(C11<28,"23–27",IF(C11<33,"28–32","33+"))) -> 23–27 | BJ11: =AN11/100 -> 0.569 | BK11: =AO11/100 -> 0.637 | BL11: =J11/(MAX($J$11:$J$579)) -> 1 | BM11: =IF(AND(G11>=30,J11>=500),"Conserver","Écarter") -> Conserver | BN11: =AT11/(MAX($AT$11:$AT$579)) -> 1 | BO11: =G11*D11 -> 2599.2 | BP11: =IF(BO11>0,U11/BO11,"") -> 0.18698061 | BQ11: =IF(V11>0,U11/V11,0) -> 2.6703297 | BR11: =IF(G11>0,AV11/G11,"") -> 0.14619883 | BS11: =AVERAGE(Tableau1[[#This Row],[STL_pg/Min]],Tableau1[[#This Row],[BLK_pg/Min]],Tableau1[[#This Row],[REB_pg/Min]]) -> 0.075023084 | BT11: =AVERAGE(Tableau1[FG%]) -> 44.610896 | BU11: =AVERAGE(Tableau1[3P%]) -> 29.90246 | BV11: =AVERAGE(Tableau1[FT%]) -> 72.024077 | BX11: Jayson Tatum | BZ11: 26.805556
A12: Giannis Antetokounmpo | B12: MIL | C12: 30 | D12: 67 | E12: 40 | F12: 27 | G12: 34.2 | H12: 2037 | I12: 791 | J12: 1320 | K12: 60.1 | L12: 13 | M12: 60 | N12: 22.2 | O12: 436 | P12: 710 | Q12: 61.7 | R12: 147 | S12: 650 | T12: 797 | U12: 436 | V12: 208 | W12: 60 | X12: 80 | Y12: 154 | Z12: 3846 | AA12: 55 | AB12: 11 | AC12: 5 | AD12: 118.9 | AE12: 111.7 | AF12: 7.2 | AG12: 33.9 | AH12: 2.1 | AI12: 19.2 | AJ12: 6.7 | AK12: 26.6 | AL12: 17.2 | AM12: 9.1 | AN12: 60.7 | AO12: 62.5 | AP12: 34.6 | AQ12: 100.18 | AR12: 21 | AS12: 4772 | AT12: =H12/D12 -> 30.402985 | AU12: =U12/D12 -> 6.5074627 | AV12: =T12/D12 -> 11.895522 | AW12: =R12/D12 -> 2.1940299 | AX12: =S12/D12 -> 9.7014925 | AY12: =W12/D12 -> 0.89552239 | AZ12: =X12/D12 -> 1.1940299 | BA12: =V12/D12 -> 3.1044776 | BB12: =IF(G12>0,AT12/G12,"") -> 0.88897617 | BC12: =IF(BA12>0,AU12/BA12,"") -> 2.0961538 | BD12: =IF(G12>0,AY12/G12,"") -> 0.026184865 | BE12: =IF(G12>0,AZ12/G12,"") -> 0.034913154 | BF12: =IF(G12>0,AW12/G12,"") -> 0.06415292 | BG12: =IF(G12>0,AX12/G12,"") -> 0.28366937 | BH12: =IF(G12<10,"<10 min",IF(G12<20,"10–19 min",IF(G12<30,"20–29 min",IF(G12<40,"30–39 min","40+ min")))) -> 30–39 min | BI12: =IF(C12<23,"18–22",IF(C12<28,"23–27",IF(C12<33,"28–32","33+"))) -> 28–32 | BJ12: =AN12/100 -> 0.607 | BK12: =AO12/100 -> 0.625 | BL12: =J12/(MAX($J$11:$J$579)) -> 0.7966204 | BM12: =IF(AND(G12>=30,J12>=500),"Conserver","Écarter") -> Conserver | BN12: =AT12/(MAX($AT$11:$AT$579)) -> 0.92982972 | BO12: =G12*D12 -> 2291.4 | BP12: =IF(BO12>0,U12/BO12,"") -> 0.19027669 | BQ12: =IF(V12>0,U12/V12,0) -> 2.0961538 | BR12: =IF(G12>0,AV12/G12,"") -> 0.34782229 | BS12: =AVERAGE(Tableau1[[#This Row],[STL_pg/Min]],Tableau1[[#This Row],[BLK_pg/Min]],Tableau1[[#This Row],[REB_pg/Min]]) -> 0.13630677 | BT12: =AVERAGE(Tableau1[FG%]) -> 44.610896 | BU12: =AVERAGE(Tableau1[3P%]) -> 29.90246 | BV12: =AVERAGE(Tableau1[FT%]) -> 72.024077 | BX12: Kevin Durant | BZ12: 26.596774
A13: Nikola Jokić | B13: DEN | C13: 30 | D13: 70 | E13: 46 | F13: 24 | G13: 36.7 | H13: 2072 | I13: 784 | J13: 1365 | K13: 57.6 | L13: 140 | M13: 329 | N13: 41.7 | O13: 364 | P13: 448 | Q13: 80 | R13: 203 | S13: 693 | T13: 889 | U13: 714 | V13: 231 | W13: 126 | X13: 42 | Y13: 161 | Z13: 4501 | AA13: 59 | AB13: 34 | AC13: 8.5 | AD13: 125.6 | AE13: 115.1 | AF13: 10.5 | AG13: 39.8 | AH13: 3.11 | AI13: 28.7 | AJ13: 8.3 | AK13: 25.2 | AL13: 17.3 | AM13: 9.2 | AN13: 62.7 | AO13: 66.3 | AP13: 28.5 | AQ13: 101.99 | AR13: 20.6 | AS13: 5471 | AT13: =H13/D13 -> 29.6 | AU13: =U13/D13 -> 10.2 | AV13: =T13/D13 -> 12.7 | AW13: =R13/D13 -> 2.9 | AX13: =S13/D13 -> 9.9 | AY13: =W13/D13 -> 1.8 | AZ13: =X13/D13 -> 0.6 | BA13: =V13/D13 -> 3.3 | BB13: =IF(G13>0,AT13/G13,"") -> 0.80653951 | BC13: =IF(BA13>0,AU13/BA13,"") -> 3.0909091 | BD13: =IF(G13>0,AY13/G13,"") -> 0.049046322 | BE13: =IF(G13>0,AZ13/G13,"") -> 0.016348774 | BF13: =IF(G13>0,AW13/G13,"") -> 0.079019074 | BG13: =IF(G13>0,AX13/G13,"") -> 0.26975477 | BH13: =IF(G13<10,"<10 min",IF(G13<20,"10–19 min",IF(G13<30,"20–29 min",IF(G13<40,"30–39 min","40+ min")))) -> 30–39 min | BI13: =IF(C13<23,"18–22",IF(C13<28,"23–27",IF(C13<33,"28–32","33+"))) -> 28–32 | BJ13: =AN13/100 -> 0.627 | BK13: =AO13/100 -> 0.663 | BL13: =J13/(MAX($J$11:$J$579)) -> 0.82377791 | BM13: =IF(AND(G13>=30,J13>=500),"Conserver","Écarter") -> Conserver | BN13: =AT13/(MAX($AT$11:$AT$579)) -> 0.90527163 | BO13: =G13*D13 -> 2569 | BP13: =IF(BO13>0,U13/BO13,"") -> 0.27792916 | BQ13: =IF(V13>0,U13/V13,0) -> 3.0909091 | BR13: =IF(G13>0,AV13/G13,"") -> 0.34604905 | BS13: =AVERAGE(Tableau1[[#This Row],[STL_pg/Min]],Tableau1[[#This Row],[BLK_pg/Min]],Tableau1[[#This Row],[REB_pg/Min]]) -> 0.13714805 | BT13: =AVERAGE(Tableau1[FG%]) -> 44.610896 | BU13: =AVERAGE(Tableau1[3P%]) -> 29.90246 | BV13: =AVERAGE(Tableau1[FT%]) -> 72.024077 | BX13: Tyrese Maxey | BZ13: 26.307692
A14: Luka Dončić | B14: LAL | C14: 26 | D14: 50 | E14: 31 | F14: 19 | G14: 35.4 | H14: 1410 | I14: 460 | J14: 1025 | K14: 45 | L14: 175 | M14: 480 | N14: 36.8 | O14: 310 | P14: 395 | Q14: 78.2 | R14: 40 | S14: 370 | T14: 410 | U14: 385 | V14: 180 | W14: 90 | X14: 20 | Y14: 125 | Z14: 2625 | AA14: 21 | AB14: 5 | AC14: 6.9 | AD14: 119.6 | AE14: 110.5 | AF14: 9.1 | AG14: 34.2 | AH14: 2.14 | AI14: 21.8 | AJ14: 2.3 | AK14: 19.8 | AL14: 11.2 | AM14: 10.2 | AN14: 53.6 | AO14: 58.7 | AP14: 32.8 | AQ14: 100.22 | AR14: 17 | AS14: 3696 | AT14: =H14/D14 -> 28.2 | AU14: =U14/D14 -> 7.7 | AV14: =T14/D14 -> 8.2 | AW14: =R14/D14 -> 0.8 | AX14: =S14/D14 -> 7.4 | AY14: =W14/D14 -> 1.8 | AZ14: =X14/D14 -> 0.4 | BA14: =V14/D14 -> 3.6 | BB14: =IF(G14>0,AT14/G14,"") -> 0.79661017 | BC14: =IF(BA14>0,AU14/BA14,"") -> 2.1388889 | BD14: =IF(G14>0,AY14/G14,"") -> 0.050847458 | BE14: =IF(G14>0,AZ14/G14,"") -> 0.011299435 | BF14: =IF(G14>0,AW14/G14,"") -> 0.02259887 | BG14: =IF(G14>0,AX14/G14,"") -> 0.20903955 | BH14: =IF(G14<10,"<10 min",IF(G14<20,"10–19 min",IF(G14<30,"20–29 min",IF(G14<40,"30–39 min","40+ min")))) -> 30–39 min | BI14: =IF(C14<23,"18–22",IF(C14<28,"23–27",IF(C14<33,"28–32","33+"))) -> 23–27 | BJ14: =AN14/100 -> 0.536 | BK14: =AO14/100 -> 0.587 | BL14: =J14/(MAX($J$11:$J$579)) -> 0.61858781 | BM14: =IF(AND(G14>=30,J14>=500),"Conserver","Écarter") -> Conserver | BN14: =AT14/(MAX($AT$11:$AT$579)) -> 0.86245473 | BO14: =G14*D14 -> 1770 | BP14: =IF(BO14>0,U14/BO14,"") -> 0.21751412 | BQ14: =IF(V14>0,U14/V14,0) -> 2.1388889 | BR14: =IF(G14>0,AV14/G14,"") -> 0.23163842 | BS14: =AVERAGE(Tableau1[[#This Row],[STL_pg/Min]],Tableau1[[#This Row],[BLK_pg/Min]],Tableau1[[#This Row],[REB_pg/Min]]) -> 0.097928437 | BT14: =AVERAGE(Tableau1[FG%]) -> 44.610896 | BU14: =AVERAGE(Tableau1[3P%]) -> 29.90246 | BV14: =AVERAGE(Tableau1[FT%]) -> 72.024077 | BX14: Cade Cunningham | BZ14: 26.1
A15: Anthony Edwards | B15: MIN | C15: 23 | D15: 79 | E15: 48 | F15: 31 | G15: 36.3 | H15: 2180 | I15: 719 | J15: 1612 | K15: 44.7 | L15: 324 | M15: 814 | N15: 39.5 | O15: 419 | P15: 498 | Q15: 83.7 | R15: 63 | S15: 387 | T15: 450 | U15: 356 | V15: 253 | W15: 95 | X15: 47 | Y15: 150 | Z15: 3429 | AA15: 7 | AB15: 0 | AC15: 3.7 | AD15: 116.2 | AE15: 111.4 | AF15: 4.8 | AG15: 20.9 | AH15: 1.44 | AI15: 14.8 | AJ15: 2.1 | AK15: 13.1 | AL15: 7.7 | AM15: 10.3 | AN15: 54.7 | AO15: 59.5 | AP15: 30.7 | AQ15: 98.27 | AR15: 14 | AS15: 5883 | AT15: =H15/D15 -> 27.594937 | AU15: =U15/D15 -> 4.5063291 | AV15: =T15/D15 -> 5.6962025 | AW15: =R15/D15 -> 0.79746835 | AX15: =S15/D15 -> 4.8987342 | AY15: =W15/D15 -> 1.2025316 | AZ15: =X15/D15 -> 0.59493671 | BA15: =V15/D15 -> 3.2025316 | BB15: =IF(G15>0,AT15/G15,"") -> 0.76019109 | BC15: =IF(BA15>0,AU15/BA15,"") -> 1.4071146 | BD15: =IF(G15>0,AY15/G15,"") -> 0.033127594 | BE15: =IF(G15>0,AZ15/G15,"") -> 0.016389441 | BF15: =IF(G15>0,AW15/G15,"") -> 0.021968825 | BG15: =IF(G15>0,AX15/G15,"") -> 0.13495135 | BH15: =IF(G15<10,"<10 min",IF(G15<20,"10–19 min",IF(G15<30,"20–29 min",IF(G15<40,"30–39 min","40+ min")))) -> 30–39 min | BI15: =IF(C15<23,"18–22",IF(C15<28,"23–27",IF(C15<33,"28–32","33+"))) -> 23–27 | BJ15: =AN15/100 -> 0.547 | BK15: =AO15/100 -> 0.595 | BL15: =J15/(MAX($J$11:$J$579)) -> 0.97284249 | BM15: =IF(AND(G15>=30,J15>=500),"Conserver","Écarter") -> Conserver | BN15: =AT15/(MAX($AT$11:$AT$579)) -> 0.84394977 | BO15: =G15*D15 -> 2867.7 | BP15: =IF(BO15>0,U15/BO15,"") -> 0.1241413 | BQ15: =IF(V15>0,U15/V15,0) -> 1.4071146 | BR15: =IF(G15>0,AV15/G15,"") -> 0.15692018 | BS15: =AVERAGE(Tableau1[[#This Row],[STL_pg/Min]],Tableau1[[#This Row],[BLK_pg/Min]],Tableau1[[#This Row],[REB_pg/Min]]) -> 0.068812405 | BT15: =AVERAGE(Tableau1[FG%]) -> 44.610896 | BU15: =AVERAGE(Tableau1[3P%]) -> 29.90246 | BV15: =AVERAGE(Tableau1[FT%]) -> 72.024077 | BX15: Jalen Brunson | BZ15: 26
A16: Jayson Tatum | B16: BOS | C16: 27 | D16: 72 | E16: 53 | F16: 19 | G16: 36.4 | H16: 1930 | I16: 662 | J16: 1462 | K16: 45.2 | L16: 252 | M16: 727 | N16: 34.3 | O16: 360 | P16: 439 | Q16: 81.4 | R16: 50 | S16: 576 | T16: 626 | U16: 432 | V16: 209 | W16: 79 | X16: 36 | Y16: 158 | Z16: 3456 | AA16: 31 | AB16: 2 | AC16: 7.4 | AD16: 119.6 | AE16: 109.8 | AF16: 9.8 | AG16: 26.6 | AH16: 2.6 | AI16: 18.9 | AJ16: 1.7 | AK16: 20.6 | AL16: 11.2 | AM16: 9.2 | AN16: 53.7 | AO16: 58.2 | AP16: 30.1 | AQ16: 98.14 | AR16: 15.8 | AS16: 5368 | AT16: =H16/D16 -> 26.805556 | AU16: =U16/D16 -> 6 | AV16: =T16/D16 -> 8.6944444 | AW16: =R16/D16 -> 0.69444444 | AX16: =S16/D16 -> 8 | AY16: =W16/D16 -> 1.0972222 | AZ16: =X16/D16 -> 0.5 | BA16: =V16/D16 -> 2.9027778 | BB16: =IF(G16>0,AT16/G16,"") -> 0.73641636 | BC16: =IF(BA16>0,AU16/BA16,"") -> 2.0669856 | BD16: =IF(G16>0,AY16/G16,"") -> 0.030143468 | BE16: =IF(G16>0,AZ16/G16,"") -> 0.013736264 | BF16: =IF(G16>0,AW16/G16,"") -> 0.019078144 | BG16: =IF(G16>0,AX16/G16,"") -> 0.21978022 | BH16: =IF(G16<10,"<10 min",IF(G16<20,"10–19 min",IF(G16<30,"20–29 min",IF(G16<40,"30–39 min","40+ min")))) -> 30–39 min | BI16: =IF(C16<23,"18–22",IF(C16<28,"23–27",IF(C16<33,"28–32","33+"))) -> 23–27 | BJ16: =AN16/100 -> 0.537 | BK16: =AO16/100 -> 0.582 | BL16: =J16/(MAX($J$11:$J$579)) -> 0.88231744 | BM16: =IF(AND(G16>=30,J16>=500),"Conserver","Écarter") -> Conserver | BN16: =AT16/(MAX($AT$11:$AT$579)) -> 0.81980774 | BO16: =G16*D16 -> 2620.8 | BP16: =IF(BO16>0,U16/BO16,"") -> 0.16483516 | BQ16: =IF(V16>0,U16/V16,0) -> 2.0669856 | BR16: =IF(G16>0,AV16/G16,"") -> 0.23885836 | BS16: =AVERAGE(Tableau1[[#This Row],[STL_pg/Min]],Tableau1[[#This Row],[BLK_pg/Min]],Tableau1[[#This Row],[REB_pg/Min]]) -> 0.094246032 | BT16: =AVERAGE(Tableau1[FG%]) -> 44.610896 | BU16: =AVERAGE(Tableau1[3P%]) -> 29.90246 | BV16: =AVERAGE(Tableau1[FT%]) -> 72.024077 | BX16: Paolo Banchero | BZ16: 25.891304
A17: Kevin Durant | B17: PHX | C17: 36 | D17: 62 | E17: 33 | F17: 29 | G17: 36.5 | H17: 1649 | I17: 589 | J17: 1122 | K17: 52.7 | L17: 161 | M17: 372 | N17: 43 | O17: 304 | P17: 360 | Q17: 83.9 | R17: 25 | S17: 353 | T17: 372 | U17: 260 | V17: 192 | W17: 50 | X17: 74 | Y17: 105 | Z17: 2678 | AA17: 5 | AB17: 0 | AC17: -0.6 | AD17: 116.5 | AE17: 117.4 | AF17: -1 | AG17: 18.8 | AH17: 1.38 | AI17: 15.2 | AJ17: 1.1 | AK17: 14.7 | AL17: 8.4 | AM17: 11 | AN17: 59.8 | AO17: 64.2 | AP17: 28.3 | AQ17: 99.49 | AR17: 14.2 | AS17: 4697 | AT17: =H17/D17 -> 26.596774 | AU17: =U17/D17 -> 4.1935484 | AV17: =T17/D17 -> 6 | AW17: =R17/D17 -> 0.40322581 | AX17: =S17/D17 -> 5.6935484 | AY17: =W17/D17 -> 0.80645161 | AZ17: =X17/D17 -> 1.1935484 | BA17: =V17/D17 -> 3.0967742 | BB17: =IF(G17>0,AT17/G17,"") -> 0.72867875 | BC17: =IF(BA17>0,AU17/BA17,"") -> 1.3541667 | BD17: =IF(G17>0,AY17/G17,"") -> 0.022094565 | BE17: =IF(G17>0,AZ17/G17,"") -> 0.032699956 | BF17: =IF(G17>0,AW17/G17,"") -> 0.011047282 | BG17: =IF(G17>0,AX17/G17,"") -> 0.15598763 | BH17: =IF(G17<10,"<10 min",IF(G17<20,"10–19 min",IF(G17<30,"20–29 min",IF(G17<40,"30–39 min","40+ min")))) -> 30–39 min | BI17: =IF(C17<23,"18–22",IF(C17<28,"23–27",IF(C17<33,"28–32","33+"))) -> 33+ | BJ17: =AN17/100 -> 0.598 | BK17: =AO17/100 -> 0.642 | BL17: =J17/(MAX($J$11:$J$579)) -> 0.67712734 | BM17: =IF(AND(G17>=30,J17>=500),"Conserver","Écarter") -> Conserver | BN17: =AT17/(MAX($AT$11:$AT$579)) -> 0.81342247 | BO17: =G17*D17 -> 2263 | BP17: =IF(BO17>0,U17/BO17,"") -> 0.11489174 | BQ17: =IF(V17>0,U17/V17,0) -> 1.3541667 | BR17: =IF(G17>0,AV17/G17,"") -> 0.16438356 | BS17: =AVERAGE(Tableau1[[#This Row],[STL_pg/Min]],Tableau1[[#This Row],[BLK_pg/Min]],Tableau1[[#This Row],[REB_pg/Min]]) -> 0.073059361 | BT17: =AVERAGE(Tableau1[FG%]) -> 44.610896 | BU17: =AVERAGE(Tableau1[3P%]) -> 29.90246 | BV17: =AVERAGE(Tableau1[FT%]) -> 72.024077 | BX17: Devin Booker | BZ17: 25.6
A18: Tyrese Maxey | B18: PHI | C18: 24 | D18: 52 | E18: 20 | F18: 32 | G18: 37.7 | H18: 1368 | I18: 478 | J18: 1092 | K18: 43.7 | L18: 161 | M18: 478 | N18: 33.7 | O18: 255 | P18: 291 | Q18: 87.9 | R18: 16 | S18: 161 | T18: 172 | U18: 317 | V18: 125 | W18: 94 | X18: 21 | Y18: 114 | Z18: 2267 | AA18: 8 | AB18: 1 | AC18: -2.4 | AD18: 113.8 | AE18: 117.4 | AF18: -3.5 | AG18: 27.6 | AH18: 2.56 | AI18: 19.2 | AJ18: 0.7 | AK18: 8.7 | AL18: 4.5 | AM18: 7.5 | AN18: 51.1 | AO18: 56.2 | AP18: 29.3 | AQ18: 98.34 | AR18: 12.7 | AS18: 4024 | AT18: =H18/D18 -> 26.307692 | AU18: =U18/D18 -> 6.0961538 | AV18: =T18/D18 -> 3.3076923 | AW18: =R18/D18 -> 0.30769231 | AX18: =S18/D18 -> 3.0961538 | AY18: =W18/D18 -> 1.8076923 | AZ18: =X18/D18 -> 0.40384615 | BA18: =V18/D18 -> 2.4038462 | BB18: =IF(G18>0,AT18/G18,"") -> 0.69781677 | BC18: =IF(BA18>0,AU18/BA18,"") -> 2.536 | BD18: =IF(G18>0,AY18/G18,"") -> 0.047949398 | BE18: =IF(G18>0,AZ18/G18,"") -> 0.0107121 | BF18: =IF(G18>0,AW18/G18,"") -> 0.0081615997 | BG18: =IF(G18>0,AX18/G18,"") -> 0.082126097 | BH18: =IF(G18<10,"<10 min",IF(G18<20,"10–19 min",IF(G18<30,"20–29 min",IF(G18<40,"30–39 min","40+ min")))) -> 30–39 min | BI18: =IF(C18<23,"18–22",IF(C18<28,"23–27",IF(C18<33,"28–32","33+"))) -> 23–27 | BJ18: =AN18/100 -> 0.511 | BK18: =AO18/100 -> 0.562 | BL18: =J18/(MAX($J$11:$J$579)) -> 0.65902233 | BM18: =IF(AND(G18>=30,J18>=500),"Conserver","Écarter") -> Conserver | BN18: =AT18/(MAX($AT$11:$AT$579)) -> 0.80458133 | BO18: =G18*D18 -> 1960.4 | BP18: =IF(BO18>0,U18/BO18,"") -> 0.16170169 | BQ18: =IF(V18>0,U18/V18,0) -> 2.536 | BR18: =IF(G18>0,AV18/G18,"") -> 0.087737196 | BS18: =AVERAGE(Tableau1[[#This Row],[STL_pg/Min]],Tableau1[[#This Row],[BLK_pg/Min]],Tableau1[[#This Row],[REB_pg/Min]]) -> 0.048799565 | BT18: =AVERAGE(Tableau1[FG%]) -> 44.610896 | BU18: =AVERAGE(Tableau1[3P%]) -> 29.90246 | BV18: =AVERAGE(Tableau1[FT%]) -> 72.024077 | BX18: LaMelo Ball | BZ18: 25.191489
A19: Cade Cunningham | B19: DET | C19: 23 | D19: 70 | E19: 38 | F19: 32 | G19: 35 | H19: 1827 | I19: 686 | J19: 1456 | K19: 46.9 | L19: 147 | M19: 420 | N19: 35.6 | O19: 315 | P19: 371 | Q19: 84.6 | R19: 56 | S19: 371 | T19: 427 | U19: 637 | V19: 308 | W19: 70 | X19: 56 | Y19: 196 | Z19: 3360 | AA19: 31 | AB19: 9 | AC19: 2.5 | AD19: 115 | AE19: 112.2 | AF19: 2.8 | AG19: 40.9 | AH19: 2.06 | AI19: 25 | AJ19: 2.3 | AK19: 14.7 | AL19: 8.6 | AM19: 12.1 | AN19: 52.1 | AO19: 56.5 | AP19: 32.3 | AQ19: 101.57 | AR19: 15.2 | AS19: 5201 | AT19: =H19/D19 -> 26.1 | AU19: =U19/D19 -> 9.1 | AV19: =T19/D19 -> 6.1 | AW19: =R19/D19 -> 0.8 | AX19: =S19/D19 -> 5.3 | AY19: =W19/D19 -> 1 | AZ19: =X19/D19 -> 0.8 | BA19: =V19/D19 -> 4.4 | BB19: =IF(G19>0,AT19/G19,"") -> 0.74571429 | BC19: =IF(BA19>0,AU19/BA19,"") -> 2.0681818 | BD19: =IF(G19>0,AY19/G19,"") -> 0.028571429 | BE19: =IF(G19>0,AZ19/G19,"") -> 0.022857143 | BF19: =IF(G19>0,AW19/G19,"") -> 0.022857143 | BG19: =IF(G19>0,AX19/G19,"") -> 0.15142857 | BH19: =IF(G19<10,"<10 min",IF(G19<20,"10–19 min",IF(G19<30,"20–29 min",IF(G19<40,"30–39 min","40+ min")))) -> 30–39 min | BI19: =IF(C19<23,"18–22",IF(C19<28,"23–27",IF(C19<33,"28–32","33+"))) -> 23–27 | BJ19: =AN19/100 -> 0.521 | BK19: =AO19/100 -> 0.565 | BL19: =J19/(MAX($J$11:$J$579)) -> 0.87869644 | BM19: =IF(AND(G19>=30,J19>=500),"Conserver","Écarter") -> Conserver | BN19: =AT19/(MAX($AT$11:$AT$579)) -> 0.79822938 | BO19: =G19*D19 -> 2450 | BP19: =IF(BO19>0,U19/BO19,"") -> 0.26 | BQ19: =IF(V19>0,U19/V19,0) -> 2.0681818 | BR19: =IF(G19>0,AV19/G19,"") -> 0.17428571 | BS19: =AVERAGE(Tableau1[[#This Row],[STL_pg/Min]],Tableau1[[#This Row],[BLK_pg/Min]],Tableau1[[#This Row],[REB_pg/Min]]) -> 0.075238095 | BT19: =AVERAGE(Tableau1[FG%]) -> 44.610896 | BU19: =AVERAGE(Tableau1[3P%]) -> 29.90246 | BV19: =AVERAGE(Tableau1[FT%]) -> 72.024077 | BX19: Damian Lillard | BZ19: 24.896552
A20: Jalen Brunson | B20: NYK | C20: 28 | D20: 65 | E20: 40 | F20: 25 | G20: 35.4 | H20: 1690 | I20: 585 | J20: 1203 | K20: 48.8 | L20: 150 | M20: 397 | N20: 38.3 | O20: 371 | P20: 449 | Q20: 82.1 | R20: 26 | S20: 163 | T20: 189 | U20: 475 | V20: 163 | W20: 59 | X20: 7 | Y20: 137 | Z20: 2665 | AA20: 14 | AB20: 0 | AC20: 2.2 | AD20: 118.3 | AE20: 115.7 | AF20: 2.6 | AG20: 31.8 | AH20: 2.9 | AI20: 23.5 | AJ20: 1.2 | AK20: 7.2 | AL20: 4.2 | AM20: 8.1 | AN20: 55.1 | AO20: 60.5 | AP20: 28.9 | AQ20: 97.79 | AR20: 13.8 | AS20: 4697 | AT20: =H20/D20 -> 26 | AU20: =U20/D20 -> 7.3076923 | AV20: =T20/D20 -> 2.9076923 | AW20: =R20/D20 -> 0.4 | AX20: =S20/D20 -> 2.5076923 | AY20: =W20/D20 -> 0.90769231 | AZ20: =X20/D20 -> 0.10769231 | BA20: =V20/D20 -> 2.5076923 | BB20: =IF(G20>0,AT20/G20,"") -> 0.73446328 | BC20: =IF(BA20>0,AU20/BA20,"") -> 2.9141104 | BD20: =IF(G20>0,AY20/G20,"") -> 0.025641026 | BE20: =IF(G20>0,AZ20/G20,"") -> 0.0030421556 | BF20: =IF(G20>0,AW20/G20,"") -> 0.011299435 | BG20: =IF(G20>0,AX20/G20,"") -> 0.070838766 | BH20: =IF(G20<10,"<10 min",IF(G20<20,"10–19 min",IF(G20<30,"20–29 min",IF(G20<40,"30–39 min","40+ min")))) -> 30–39 min | BI20: =IF(C20<23,"18–22",IF(C20<28,"23–27",IF(C20<33,"28–32","33+"))) -> 28–32 | BJ20: =AN20/100 -> 0.551 | BK20: =AO20/100 -> 0.605 | BL20: =J20/(MAX($J$11:$J$579)) -> 0.72601086 | BM20: =IF(AND(G20>=30,J20>=500),"Conserver","Écarter") -> Conserver | BN20: =AT20/(MAX($AT$11:$AT$579)) -> 0.79517103 | BO20: =G20*D20 -> 2301 | BP20: =IF(BO20>0,U20/BO20,"") -> 0.20643199 | BQ20: =IF(V20>0,U20/V20,0) -> 2.9141104 | BR20: =IF(G20>0,AV20/G20,"") -> 0.082138201 | BS20: =AVERAGE(Tableau1[[#This Row],[STL_pg/Min]],Tableau1[[#This Row],[BLK_pg/Min]],Tableau1[[#This Row],[REB_pg/Min]]) -> 0.036940461 | BT20: =AVERAGE(Tableau1[FG%]) -> 44.610896 | BU20: =AVERAGE(Tableau1[3P%]) -> 29.90246 | BV20: =AVERAGE(Tableau1[FT%]) -> 72.024077 | BX20: Anthony Davis | BZ20: 24.705882
A21: Paolo Banchero | B21: ORL | C21: 22 | D21: 46 | E21: 21 | F21: 25 | G21: 34.4 | H21: 1191 | I21: 414 | J21: 911 | K21: 45.2 | L21: 87 | M21: 271 | N21: 32 | O21: 281 | P21: 386 | Q21: 72.7 | R21: 51 | S21: 294 | T21: 345 | U21: 221 | V21: 138 | W21: 37 | X21: 28 | Y21: 97 | Z21: 1992 | AA21: 11 | AB21: 0 | AC21: -0.5 | AD21: 109.1 | AE21: 109.6 | AF21: -0.6 | AG21: 26.2 | AH21: 1.61 | AI21: 15.3 | AJ21: 3.1 | AK21: 19.2 | AL21: 10.8 | AM21: 9.5 | AN21: 50 | AO21: 55.1 | AP21: 33 | AQ21: 97.29 | AR21: 15.7 | AS21: 3204 | AT21: =H21/D21 -> 25.891304 | AU21: =U21/D21 -> 4.8043478 | AV21: =T21/D21 -> 7.5 | AW21: =R21/D21 -> 1.1086957 | AX21: =S21/D21 -> 6.3913043 | AY21: =W21/D21 -> 0.80434783 | AZ21: =X21/D21 -> 0.60869565 | BA21: =V21/D21 -> 3 | BB21: =IF(G21>0,AT21/G21,"") -> 0.7526542 | BC21: =IF(BA21>0,AU21/BA21,"") -> 1.6014493 | BD21: =IF(G21>0,AY21/G21,"") -> 0.023382204 | BE21: =IF(G21>0,AZ21/G21,"") -> 0.017694641 | BF21: =IF(G21>0,AW21/G21,"") -> 0.032229525 | BG21: =IF(G21>0,AX21/G21,"") -> 0.18579373 | BH21: =IF(G21<10,"<10 min",IF(G21<20,"10–19 min",IF(G21<30,"20–29 min",IF(G21<40,"30–39 min","40+ min")))) -> 30–39 min | BI21: =IF(C21<23,"18–22",IF(C21<28,"23–27",IF(C21<33,"28–32","33+"))) -> 18–22 | BJ21: =AN21/100 -> 0.5 | BK21: =AO21/100 -> 0.551 | BL21: =J21/(MAX($J$11:$J$579)) -> 0.54978877 | BM21: =IF(AND(G21>=30,J21>=500),"Conserver","Écarter") -> Conserver | BN21: =AT21/(MAX($AT$11:$AT$579)) -> 0.79184673 | BO21: =G21*D21 -> 1582.4 | BP21: =IF(BO21>0,U21/BO21,"") -> 0.13966127 | BQ21: =IF(V21>0,U21/V21,0) -> 1.6014493 | BR21: =IF(G21>0,AV21/G21,"") -> 0.21802326 | BS21: =AVERAGE(Tableau1[[#This Row],[STL_pg/Min]],Tableau1[[#This Row],[BLK_pg/Min]],Tableau1[[#This Row],[REB_pg/Min]]) -> 0.0863667 | BT21: =AVERAGE(Tableau1[FG%]) -> 44.610896 | BU21: =AVERAGE(Tableau1[3P%]) -> 29.90246 | BV21: =AVERAGE(Tableau1[FT%]) -> 72.024077
A22: Devin Booker | B22: PHX | C22: 28 | D22: 75 | E22: 35 | F22: 40 | G22: 37.3 | H22: 1920 | I22: 653 | J22: 1418 | K22: 46.1 | L22: 180 | M22: 548 | N22: 33.2 | O22: 435 | P22: 480 | Q22: 89.4 | R22: 75 | S22: 233 | T22: 308 | U22: 533 | V22: 218 | W22: 68 | X22: 15 | Y22: 195 | Z22: 3113 | AA22: 16 | AB22: 0 | AC22: -2.4 | AD22: 115.3 | AE22: 118.5 | AF22: -3.2 | AG22: 30.1 | AH22: 2.4 | AI22: 22.4 | AJ22: 2.8 | AK22: 8 | AL22: 5.5 | AM22: 9.3 | AN22: 52.5 | AO22: 58.9 | AP22: 28.5 | AQ22: 98.72 | AR22: 12.2 | AS22: 5752 | AT22: =H22/D22 -> 25.6 | AU22: =U22/D22 -> 7.1066667 | AV22: =T22/D22 -> 4.1066667 | AW22: =R22/D22 -> 1 | AX22: =S22/D22 -> 3.1066667 | AY22: =W22/D22 -> 0.90666667 | AZ22: =X22/D22 -> 0.2 | BA22: =V22/D22 -> 2.9066667 | BB22: =IF(G22>0,AT22/G22,"") -> 0.68632708 | BC22: =IF(BA22>0,AU22/BA22,"") -> 2.4449541 | BD22: =IF(G22>0,AY22/G22,"") -> 0.024307417 | BE22: =IF(G22>0,AZ22/G22,"") -> 0.0053619303 | BF22: =IF(G22>0,AW22/G22,"") -> 0.026809651 | BG22: =IF(G22>0,AX22/G22,"") -> 0.083288651 | BH22: =IF(G22<10,"<10 min",IF(G22<20,"10–19 min",IF(G22<30,"20–29 min",IF(G22<40,"30–39 min","40+ min")))) -> 30–39 min | BI22: =IF(C22<23,"18–22",IF(C22<28,"23–27",IF(C22<33,"28–32","33+"))) -> 28–32 | BJ22: =AN22/100 -> 0.525 | BK22: =AO22/100 -> 0.589 | BL22: =J22/(MAX($J$11:$J$579)) -> 0.85576343 | BM22: =IF(AND(G22>=30,J22>=500),"Conserver","Écarter") -> Conserver | BN22: =AT22/(MAX($AT$11:$AT$579)) -> 0.78293763 | BO22: =G22*D22 -> 2797.5 | BP22: =IF(BO22>0,U22/BO22,"") -> 0.19052726 | BQ22: =IF(V22>0,U22/V22,0) -> 2.4449541 | BR22: =IF(G22>0,AV22/G22,"") -> 0.1100983 | BS22: =AVERAGE(Tableau1[[#This Row],[STL_pg/Min]],Tableau1[[#This Row],[BLK_pg/Min]],Tableau1[[#This Row],[REB_pg/Min]]) -> 0.046589217 | BT22: =AVERAGE(Tableau1[FG%]) -> 44.610896 | BU22: =AVERAGE(Tableau1[3P%]) -> 29.90246 | BV22: =AVERAGE(Tableau1[FT%]) -> 72.024077
A23: LaMelo Ball | B23: CHA | C23: 23 | D23: 47 | E23: 16 | F23: 31 | G23: 32 | H23: 1184 | I23: 404 | J23: 1001 | K23: 40.5 | L23: 179 | M23: 526 | N23: 33.9 | O23: 193 | P23: 230 | Q23: 84.3 | R23: 47 | S23: 183 | T23: 230 | U23: 348 | V23: 169 | W23: 52 | X23: 14 | Y23: 155 | Z23: 2016 | AA23: 13 | AB23: 0 | AC23: -2.8 | AD23: 112.7 | AE23: 116.5 | AF23: -3.9 | AG23: 39 | AH23: 2.07 | AI23: 21.5 | AJ23: 2.8 | AK23: 12.1 | AL23: 7.2 | AM23: 10.4 | AN23: 49.4 | AO23: 53.6 | AP23: 34.2 | AQ23: 101.33 | AR23: 12.7 | AS23: 3173 | AT23: =H23/D23 -> 25.191489 | AU23: =U23/D23 -> 7.4042553 | AV23: =T23/D23 -> 4.893617 | AW23: =R23/D23 -> 1 | AX23: =S23/D23 -> 3.893617 | AY23: =W23/D23 -> 1.106383 | AZ23: =X23/D23 -> 0.29787234 | BA23: =V23/D23 -> 3.5957447 | BB23: =IF(G23>0,AT23/G23,"") -> 0.78723404 | BC23: =IF(BA23>0,AU23/BA23,"") -> 2.0591716 | BD23: =IF(G23>0,AY23/G23,"") -> 0.034574468 | BE23: =IF(G23>0,AZ23/G23,"") -> 0.0093085106 | BF23: =IF(G23>0,AW23/G23,"") -> 0.03125 | BG23: =IF(G23>0,AX23/G23,"") -> 0.12167553 | BH23: =IF(G23<10,"<10 min",IF(G23<20,"10–19 min",IF(G23<30,"20–29 min",IF(G23<40,"30–39 min","40+ min")))) -> 30–39 min | BI23: =IF(C23<23,"18–22",IF(C23<28,"23–27",IF(C23<33,"28–32","33+"))) -> 23–27 | BJ23: =AN23/100 -> 0.494 | BK23: =AO23/100 -> 0.536 | BL23: =J23/(MAX($J$11:$J$579)) -> 0.6041038 | BM23: =IF(AND(G23>=30,J23>=500),"Conserver","Écarter") -> Conserver | BN23: =AT23/(MAX($AT$11:$AT$579)) -> 0.77044394 | BO23: =G23*D23 -> 1504 | BP23: =IF(BO23>0,U23/BO23,"") -> 0.23138298 | BQ23: =IF(V23>0,U23/V23,0) -> 2.0591716 | BR23: =IF(G23>0,AV23/G23,"") -> 0.15292553 | BS23: =AVERAGE(Tableau1[[#This Row],[STL_pg/Min]],Tableau1[[#This Row],[BLK_pg/Min]],Tableau1[[#This Row],[REB_pg/Min]]) -> 0.065602837 | BT23: =AVERAGE(Tableau1[FG%]) -> 44.610896 | BU23: =AVERAGE(Tableau1[3P%]) -> 29.90246 | BV23: =AVERAGE(Tableau1[FT%]) -> 72.024077
A24: Damian Lillard | B24: MIL | C24: 34 | D24: 58 | E24: 32 | F24: 26 | G24: 36.1 | H24: 1444 | I24: 447 | J24: 992 | K24: 44.8 | L24: 197 | M24: 522 | N24: 37.6 | O24: 360 | P24: 394 | Q24: 92.1 | R24: 29 | S24: 244 | T24: 273 | U24: 412 | V24: 162 | W24: 70 | X24: 12 | Y24: 99 | Z24: 2465 | AA24: 14 | AB24: 2 | AC24: 0.9 | AD24: 115.3 | AE24: 114.6 | AF24: 0.7 | AG24: 29.9 | AH24: 2.53 | AI24: 23.8 | AJ24: 1.4 | AK24: 10.8 | AL24: 6.3 | AM24: 9.4 | AN24: 54.7 | AO24: 62.1 | AP24: 26.9 | AQ24: 100.86 | AR24: 14.4 | AS24: 4407 | AT24: =H24/D24 -> 24.896552 | AU24: =U24/D24 -> 7.1034483 | AV24: =T24/D24 -> 4.7068966 | AW24: =R24/D24 -> 0.5 | AX24: =S24/D24 -> 4.2068966 | AY24: =W24/D24 -> 1.2068966 | AZ24: =X24/D24 -> 0.20689655 | BA24: =V24/D24 -> 2.7931034 | BB24: =IF(G24>0,AT24/G24,"") -> 0.68965517 | BC24: =IF(BA24>0,AU24/BA24,"") -> 2.5432099 | BD24: =IF(G24>0,AY24/G24,"") -> 0.033432037 | BE24: =IF(G24>0,AZ24/G24,"") -> 0.0057312064 | BF24: =IF(G24>0,AW24/G24,"") -> 0.013850416 | BG24: =IF(G24>0,AX24/G24,"") -> 0.11653453 | BH24: =IF(G24<10,"<10 min",IF(G24<20,"10–19 min",IF(G24<30,"20–29 min",IF(G24<40,"30–39 min","40+ min")))) -> 30–39 min | BI24: =IF(C24<23,"18–22",IF(C24<28,"23–27",IF(C24<33,"28–32","33+"))) -> 33+ | BJ24: =AN24/100 -> 0.547 | BK24: =AO24/100 -> 0.621 | BL24: =J24/(MAX($J$11:$J$579)) -> 0.5986723 | BM24: =IF(AND(G24>=30,J24>=500),"Conserver","Écarter") -> Conserver | BN24: =AT24/(MAX($AT$11:$AT$579)) -> 0.76142371 | BO24: =G24*D24 -> 2093.8 | BP24: =IF(BO24>0,U24/BO24,"") -> 0.19677142 | BQ24: =IF(V24>0,U24/V24,0) -> 2.5432099 | BR24: =IF(G24>0,AV24/G24,"") -> 0.13038495 | BS24: =AVERAGE(Tableau1[[#This Row],[STL_pg/Min]],Tableau1[[#This Row],[BLK_pg/Min]],Tableau1[[#This Row],[REB_pg/Min]]) -> 0.056516063 | BT24: =AVERAGE(Tableau1[FG%]) -> 44.610896 | BU24: =AVERAGE(Tableau1[3P%]) -> 29.90246 | BV24: =AVERAGE(Tableau1[FT%]) -> 72.024077
A25: Anthony Davis | B25: DAL | C25: 32 | D25: 51 | E25: 30 | F25: 21 | G25: 33.4 | H25: 1260 | I25: 469 | J25: 908 | K25: 51.6 | L25: 36 | M25: 122 | N25: 28.2 | O25: 286 | P25: 367 | Q25: 77.5 | R25: 133 | S25: 454 | T25: 592 | U25: 179 | V25: 112 | W25: 61 | X25: 112 | Y25: 97 | Z25: 2637 | AA25: 36 | AB25: 1 | AC25: 0.5 | AD25: 113.3 | AE25: 112.9 | AF25: 0.5 | AG25: 18.2 | AH25: 1.6 | AI25: 13.3 | AJ25: 8.3 | AK25: 25.4 | AL25: 17.3 | AM25: 8.3 | AN25: 53.6 | AO25: 58.8 | AP25: 30.1 | AQ25: 98.83 | AR25: 17.9 | AS25: 3515 | AT25: =H25/D25 -> 24.705882 | AU25: =U25/D25 -> 3.5098039 | AV25: =T25/D25 -> 11.607843 | AW25: =R25/D25 -> 2.6078431 | AX25: =S25/D25 -> 8.9019608 | AY25: =W25/D25 -> 1.1960784 | AZ25: =X25/D25 -> 2.1960784 | BA25: =V25/D25 -> 2.1960784 | BB25: =IF(G25>0,AT25/G25,"") -> 0.73969708 | BC25: =IF(BA25>0,AU25/BA25,"") -> 1.5982143 | BD25: =IF(G25>0,AY25/G25,"") -> 0.035810731 | BE25: =IF(G25>0,AZ25/G25,"") -> 0.065750851 | BF25: =IF(G25>0,AW25/G25,"") -> 0.078079136 | BG25: =IF(G25>0,AX25/G25,"") -> 0.26652577 | BH25: =IF(G25<10,"<10 min",IF(G25<20,"10–19 min",IF(G25<30,"20–29 min",IF(G25<40,"30–39 min","40+ min")))) -> 30–39 min | BI25: =IF(C25<23,"18–22",IF(C25<28,"23–27",IF(C25<33,"28–32","33+"))) -> 28–32 | BJ25: =AN25/100 -> 0.536 | BK25: =AO25/100 -> 0.588 | BL25: =J25/(MAX($J$11:$J$579)) -> 0.54797827 | BM25: =IF(AND(G25>=30,J25>=500),"Conserver","Écarter") -> Conserver | BN25: =AT25/(MAX($AT$11:$AT$579)) -> 0.75559238 | BO25: =G25*D25 -> 1703.4 | BP25: =IF(BO25>0,U25/BO25,"") -> 0.10508395 | BQ25: =IF(V25>0,U25/V25,0) -> 1.5982143 | BR25: =IF(G25>0,AV25/G25,"") -> 0.34754021 | BS25: =AVERAGE(Tableau1[[#This Row],[STL_pg/Min]],Tableau1[[#This Row],[BLK_pg/Min]],Tableau1[[#This Row],[REB_pg/Min]]) -> 0.1497006 | BT25: =AVERAGE(Tableau1[FG%]) -> 44.610896 | BU25: =AVERAGE(Tableau1[3P%]) -> 29.90246 | BV25: =AVERAGE(Tableau1[FT%]) -> 72.024077
A26: Kyrie Irving | B26: DAL | C26: 33 | D26: 50 | E26: 28 | F26: 22 | G26: 36.1 | H26: 1235 | I26: 445 | J26: 945 | K26: 47.3 | L26: 145 | M26: 360 | N26: 40.1 | O26: 195 | P26: 215 | Q26: 91.6 | R26: 60 | S26: 180 | T26: 240 | U26: 230 | V26: 110 | W26: 65 | X26: 25 | Y26: 100 | Z26: 2025 | AA26: 0 | AB26: 0 | AC26: 2.5 | AD26: 116.5 | AE26: 113.9 | AF26: 2.6 | AG26: 19.8 | AH26: 2.08 | AI26: 16.9 | AJ26: 3.3 | AK26: 9.3 | AL26: 6.4 | AM26: 8.1 | AN26: 54.9 | AO26: 59.4 | AP26: 26.4 | AQ26: 99.98 | AR26: 12.9 | AS26: 3768 | AT26: =H26/D26 -> 24.7 | AU26: =U26/D26 -> 4.6 | AV26: =T26/D26 -> 4.8 | AW26: =R26/D26 -> 1.2 | AX26: =S26/D26 -> 3.6 | AY26: =W26/D26 -> 1.3 | AZ26: =X26/D26 -> 0.5 | BA26: =V26/D26 -> 2.2 | BB26: =IF(G26>0,AT26/G26,"") -> 0.68421053 | BC26: =IF(BA26>0,AU26/BA26,"") -> 2.0909091 | BD26: =IF(G26>0,AY26/G26,"") -> 0.03601108 | BE26: =IF(G26>0,AZ26/G26,"") -> 0.013850416 | BF26: =IF(G26>0,AW26/G26,"") -> 0.033240997 | BG26: =IF(G26>0,AX26/G26,"") -> 0.099722992 | BH26: =IF(G26<10,"<10 min",IF(G26<20,"10–19 min",IF(G26<30,"20–29 min",IF(G26<40,"30–39 min","40+ min")))) -> 30–39 min | BI26: =IF(C26<23,"18–22",IF(C26<28,"23–27",IF(C26<33,"28–32","33+"))) -> 33+ | BJ26: =AN26/100 -> 0.549 | BK26: =AO26/100 -> 0.594 | BL26: =J26/(MAX($J$11:$J$579)) -> 0.57030779 | BM26: =IF(AND(G26>=30,J26>=500),"Conserver","Écarter") -> Conserver | BN26: =AT26/(MAX($AT$11:$AT$579)) -> 0.75541247 | BO26: =G26*D26 -> 1805 | BP26: =IF(BO26>0,U26/BO26,"") -> 0.12742382 | BQ26: =IF(V26>0,U26/V26,0) -> 2.0909091 | BR26: =IF(G26>0,AV26/G26,"") -> 0.13296399 | BS26: =AVERAGE(Tableau1[[#This Row],[STL_pg/Min]],Tableau1[[#This Row],[BLK_pg/Min]],Tableau1[[#This Row],[REB_pg/Min]]) -> 0.060941828 | BT26: =AVERAGE(Tableau1[FG%]) -> 44.610896 | BU26: =AVERAGE(Tableau1[3P%]) -> 29.90246 | BV26: =AVERAGE(Tableau1[FT%]) -> 72.024077
A27: Zion Williamson | B27: NOP | C27: 24 | D27: 30 | E27: 10 | F27: 20 | G27: 28.6 | H27: 738 | I27: 288 | J27: 507 | K27: 56.7 | L27: 3 | M27: 12 | N27: 23.1 | O27: 159 | P27: 240 | Q27: 65.6 | R27: 75 | S27: 141 | T27: 216 | U27: 159 | V27: 90 | W27: 36 | X27: 27 | Y27: 81 | Z27: 1338 | AA27: 8 | AB27: 2 | AC27: -1.4 | AD27: 113.7 | AE27: 115.5 | AF27: -1.8 | AG27: 32.5 | AH27: 1.77 | AI27: 18.5 | AJ27: 8 | AK27: 15.2 | AL27: 11.6 | AM27: 10.5 | AN27: 57 | AO27: 60 | AP27: 32.5 | AQ27: 103.3 | AR27: 16.7 | AS27: 1841 | AT27: =H27/D27 -> 24.6 | AU27: =U27/D27 -> 5.3 | AV27: =T27/D27 -> 7.2 | AW27: =R27/D27 -> 2.5 | AX27: =S27/D27 -> 4.7 | AY27: =W27/D27 -> 1.2 | AZ27: =X27/D27 -> 0.9 | BA27: =V27/D27 -> 3 | BB27: =IF(G27>0,AT27/G27,"") -> 0.86013986 | BC27: =IF(BA27>0,AU27/BA27,"") -> 1.7666667 | BD27: =IF(G27>0,AY27/G27,"") -> 0.041958042 | BE27: =IF(G27>0,AZ27/G27,"") -> 0.031468531 | BF27: =IF(G27>0,AW27/G27,"") -> 0.087412587 | BG27: =IF(G27>0,AX27/G27,"") -> 0.16433566 | BH27: =IF(G27<10,"<10 min",IF(G27<20,"10–19 min",IF(G27<30,"20–29 min",IF(G27<40,"30–39 min","40+ min")))) -> 20–29 min | BI27: =IF(C27<23,"18–22",IF(C27<28,"23–27",IF(C27<33,"28–32","33+"))) -> 23–27 | BJ27: =AN27/100 -> 0.57 | BK27: =AO27/100 -> 0.6 | BL27: =J27/(MAX($J$11:$J$579)) -> 0.30597465 | BM27: =IF(AND(G27>=30,J27>=500),"Conserver","Écarter") -> Écarter | BN27: =AT27/(MAX($AT$11:$AT$579)) -> 0.75235412 | BO27: =G27*D27 -> 858 | BP27: =IF(BO27>0,U27/BO27,"") -> 0.18531469 | BQ27: =IF(V27>0,U27/V27,0) -> 1.7666667 | BR27: =IF(G27>0,AV27/G27,"") -> 0.25174825 | BS27: =AVERAGE(Tableau1[[#This Row],[STL_pg/Min]],Tableau1[[#This Row],[BLK_pg/Min]],Tableau1[[#This Row],[REB_pg/Min]]) -> 0.10839161 | BT27: =AVERAGE(Tableau1[FG%]) -> 44.610896 | BU27: =AVERAGE(Tableau1[3P%]) -> 29.90246 | BV27: =AVERAGE(Tableau1[FT%]) -> 72.024077
A28: Stephen Curry | B28: GSW | C28: 37 | D28: 70 | E28: 41 | F28: 29 | G28: 32.2 | H28: 1715 | I28: 567 | J28: 1260 | K28: 44.8 | L28: 308 | M28: 784 | N28: 39.7 | O28: Données | P28: 301 | Q28: 93.3 | R28: 42 | S28: 273 | T28: 308 | U28: 420 | V28: 203 | W28: 77 | X28: 28 | Y28: 98 | Z28: 2849 | AA28: 9 | AB28: 0 | AC28: 4.3 | AD28: 118.4 | AE28: 112.7 | AF28: 5.7 | AG28: 28.4 | AH28: 2.11 | AI28: 21.1 | AJ28: 1.7 | AK28: 11.8 | AL28: 6.6 | AM28: 10 | AN28: 57.2 | AO28: 61.8 | AP28: 28.6 | AQ28: 101.72 | AR28: 14.5 | AS28: 4785 | AT28: =H28/D28 -> 24.5 | AU28: =U28/D28 -> 6 | AV28: =T28/D28 -> 4.4 | AW28: =R28/D28 -> 0.6 | AX28: =S28/D28 -> 3.9 | AY28: =W28/D28 -> 1.1 | AZ28: =X28/D28 -> 0.4 | BA28: =V28/D28 -> 2.9 | BB28: =IF(G28>0,AT28/G28,"") -> 0.76086957 | BC28: =IF(BA28>0,AU28/BA28,"") -> 2.0689655 | BD28: =IF(G28>0,AY28/G28,"") -> 0.034161491 | BE28: =IF(G28>0,AZ28/G28,"") -> 0.01242236 | BF28: =IF(G28>0,AW28/G28,"") -> 0.01863354 | BG28: =IF(G28>0,AX28/G28,"") -> 0.12111801 | BH28: =IF(G28<10,"<10 min",IF(G28<20,"10–19 min",IF(G28<30,"20–29 min",IF(G28<40,"30–39 min","40+ min")))) -> 30–39 min | BI28: =IF(C28<23,"18–22",IF(C28<28,"23–27",IF(C28<33,"28–32","33+"))) -> 33+ | BJ28: =AN28/100 -> 0.572 | BK28: =AO28/100 -> 0.618 | BL28: =J28/(MAX($J$11:$J$579)) -> 0.76041038 | BM28: =IF(AND(G28>=30,J28>=500),"Conserver","Écarter") -> Conserver | BN28: =AT28/(MAX($AT$11:$AT$579)) -> 0.74929577 | BO28: =G28*D28 -> 2254 | BP28: =IF(BO28>0,U28/BO28,"") -> 0.1863354 | BQ28: =IF(V28>0,U28/V28,0) -> 2.0689655 | BR28: =IF(G28>0,AV28/G28,"") -> 0.13664596 | BS28: =AVERAGE(Tableau1[[#This Row],[STL_pg/Min]],Tableau1[[#This Row],[BLK_pg/Min]],Tableau1[[#This Row],[REB_pg/Min]]) -> 0.061076605 | BT28: =AVERAGE(Tableau1[FG%]) -> 44.610896 | BU28: =AVERAGE(Tableau1[3P%]) -> 29.90246 | BV28: =AVERAGE(Tableau1[FT%]) -> 72.024077
A29: Karl-Anthony Towns | B29: NYK | C29: 29 | D29: 72 | E29: 46 | F29: 26 | G29: 35 | H29: 1757 | I29: 641 | J29: 1217 | K29: 52.6 | L29: 144 | M29: 338 | N29: 42 | O29: 338 | P29: 410 | Q29: 82.9 | R29: 209 | S29: 706 | T29: 922 | U29: 223 | V29: 194 | W29: 72 | X29: 50 | Y29: 252 | Z29: 3370 | AA29: 58 | AB29: 1 | AC29: 5.3 | AD29: 119.4 | AE29: 112.7 | AF29: 6.8 | AG29: 13 | AH29: 1.16 | AI29: 12.4 | AJ29: 8.7 | AK29: 28.4 | AL29: 18.7 | AM29: 10.7 | AN29: 58.4 | AO29: 63 | AP29: 26.5 | AQ29: 99.25 | AR29: 16.1 | AS29: 5215 | AT29: =H29/D29 -> 24.402778 | AU29: =U29/D29 -> 3.0972222 | AV29: =T29/D29 -> 12.805556 | AW29: =R29/D29 -> 2.9027778 | AX29: =S29/D29 -> 9.8055556 | AY29: =W29/D29 -> 1 | AZ29: =X29/D29 -> 0.69444444 | BA29: =V29/D29 -> 2.6944444 | BB29: =IF(G29>0,AT29/G29,"") -> 0.69722222 | BC29: =IF(BA29>0,AU29/BA29,"") -> 1.1494845 | BD29: =IF(G29>0,AY29/G29,"") -> 0.028571429 | BE29: =IF(G29>0,AZ29/G29,"") -> 0.01984127 | BF29: =IF(G29>0,AW29/G29,"") -> 0.082936508 | BG29: =IF(G29>0,AX29/G29,"") -> 0.28015873 | BH29: =IF(G29<10,"<10 min",IF(G29<20,"10–19 min",IF(G29<30,"20–29 min",IF(G29<40,"30–39 min","40+ min")))) -> 30–39 min | BI29: =IF(C29<23,"18–22",IF(C29<28,"23–27",IF(C29<33,"28–32","33+"))) -> 28–32 | BJ29: =AN29/100 -> 0.584 | BK29: =AO29/100 -> 0.63 | BL29: =J29/(MAX($J$11:$J$579)) -> 0.73445987 | BM29: =IF(AND(G29>=30,J29>=500),"Conserver","Écarter") -> Conserver | BN29: =AT29/(MAX($AT$11:$AT$579)) -> 0.74632238 | BO29: =G29*D29 -> 2520 | BP29: =IF(BO29>0,U29/BO29,"") -> 0.088492063 | BQ29: =IF(V29>0,U29/V29,0) -> 1.1494845 | BR29: =IF(G29>0,AV29/G29,"") -> 0.36587302 | BS29: =AVERAGE(Tableau1[[#This Row],[STL_pg/Min]],Tableau1[[#This Row],[BLK_pg/Min]],Tableau1[[#This Row],[REB_pg/Min]]) -> 0.13809524 | BT29: =AVERAGE(Tableau1[FG%]) -> 44.610896 | BU29: =AVERAGE(Tableau1[3P%]) -> 29.90246 | BV29: =AVERAGE(Tableau1[FT%]) -> 72.024077
A30: LeBron James | B30: LAL | C30: 40 | D30: 70 | E30: 44 | F30: 26 | G30: 34.9 | H30: 1708 | I30: 651 | J30: 1267 | K30: 51.3 | L30: 147 | M30: 399 | N30: 37.6 | O30: 259 | P30: 329 | Q30: 78.2 | R30: 70 | S30: 476 | T30: 546 | U30: 574 | V30: 259 | W30: 70 | X30: 42 | Y30: 98 | Z30: 3297 | AA30: 32 | AB30: 10 | AC30: -0.8 | AD30: 112.7 | AE30: 114 | AF30: -1.3 | AG30: 39.5 | AH30: 2.21 | AI30: 25.6 | AJ30: 3.1 | AK30: 18.7 | AL30: 11.2 | AM30: 11.6 | AN30: 57.1 | AO30: 60.4 | AP30: 29.1 | AQ30: 100.62 | AR30: 16.9 | AS30: 5129 | AT30: =H30/D30 -> 24.4 | AU30: =U30/D30 -> 8.2 | AV30: =T30/D30 -> 7.8 | AW30: =R30/D30 -> 1 | AX30: =S30/D30 -> 6.8 | AY30: =W30/D30 -> 1 | AZ30: =X30/D30 -> 0.6 | BA30: =V30/D30 -> 3.7 | BB30: =IF(G30>0,AT30/G30,"") -> 0.6991404 | BC30: =IF(BA30>0,AU30/BA30,"") -> 2.2162162 | BD30: =IF(G30>0,AY30/G30,"") -> 0.028653295 | BE30: =IF(G30>0,AZ30/G30,"") -> 0.017191977 | BF30: =IF(G30>0,AW30/G30,"") -> 0.028653295 | BG30: =IF(G30>0,AX30/G30,"") -> 0.19484241 | BH30: =IF(G30<10,"<10 min",IF(G30<20,"10–19 min",IF(G30<30,"20–29 min",IF(G30<40,"30–39 min","40+ min")))) -> 30–39 min | BI30: =IF(C30<23,"18–22",IF(C30<28,"23–27",IF(C30<33,"28–32","33+"))) -> 33+ | BJ30: =AN30/100 -> 0.571 | BK30: =AO30/100 -> 0.604 | BL30: =J30/(MAX($J$11:$J$579)) -> 0.76463488 | BM30: =IF(AND(G30>=30,J30>=500),"Conserver","Écarter") -> Conserver | BN30: =AT30/(MAX($AT$11:$AT$579)) -> 0.74623742 | BO30: =G30*D30 -> 2443 | BP30: =IF(BO30>0,U30/BO30,"") -> 0.23495702 | BQ30: =IF(V30>0,U30/V30,0) -> 2.2162162 | BR30: =IF(G30>0,AV30/G30,"") -> 0.2234957 | BS30: =AVERAGE(Tableau1[[#This Row],[STL_pg/Min]],Tableau1[[#This Row],[BLK_pg/Min]],Tableau1[[#This Row],[REB_pg/Min]]) -> 0.089780325 | BT30: =AVERAGE(Tableau1[FG%]) -> 44.610896 | BU30: =AVERAGE(Tableau1[3P%]) -> 29.90246 | BV30: =AVERAGE(Tableau1[FT%]) -> 72.024077
A31: Victor Wembanyama | B31: SAS | C31: 21 | D31: 46 | E31: 21 | F31: 25 | G31: 33.2 | H31: 1118 | I31: 409 | J31: 856 | K31: 47.6 | L31: 143 | M31: 405 | N31: 35.2 | O31: 156 | P31: 189 | Q31: 83.6 | R31: 83 | S31: 423 | T31: 506 | U31: 170 | V31: 147 | W31: 51 | X31: 175 | Y31: 106 | Z31: 2512 | AA31: 28 | AB31: 1 | AC31: 2.2 | AD31: 112.5 | AE31: 110 | AF31: 2.5 | AG31: 18.4 | AH31: 1.13 | AI31: 13.4 | AJ31: 5.4 | AK31: 25.5 | AL31: 15.9 | AM31: 11.9 | AN31: 55.9 | AO31: 59.4 | AP31: 30 | AQ31: 101 | AR31: 16.8 | AS31: 3223 | AT31: =H31/D31 -> 24.304348 | AU31: =U31/D31 -> 3.6956522 | AV31: =T31/D31 -> 11 | AW31: =R31/D31 -> 1.8043478 | AX31: =S31/D31 -> 9.1956522 | AY31: =W31/D31 -> 1.1086957 | AZ31: =X31/D31 -> 3.8043478 | BA31: =V31/D31 -> 3.1956522 | BB31: =IF(G31>0,AT31/G31,"") -> 0.73205867 | BC31: =IF(BA31>0,AU31/BA31,"") -> 1.1564626 | BD31: =IF(G31>0,AY31/G31,"") -> 0.033394447 | BE31: =IF(G31>0,AZ31/G31,"") -> 0.11458879 | BF31: =IF(G31>0,AW31/G31,"") -> 0.054347826 | BG31: =IF(G31>0,AX31/G31,"") -> 0.27697748 | BH31: =IF(G31<10,"<10 min",IF(G31<20,"10–19 min",IF(G31<30,"20–29 min",IF(G31<40,"30–39 min","40+ min")))) -> 30–39 min | BI31: =IF(C31<23,"18–22",IF(C31<28,"23–27",IF(C31<33,"28–32","33+"))) -> 18–22 | BJ31: =AN31/100 -> 0.559 | BK31: =AO31/100 -> 0.594 | BL31: =J31/(MAX($J$11:$J$579)) -> 0.51659626 | BM31: =IF(AND(G31>=30,J31>=500),"Conserver","Écarter") -> Conserver | BN31: =AT31/(MAX($AT$11:$AT$579)) -> 0.74331205 | BO31: =G31*D31 -> 1527.2 | BP31: =IF(BO31>0,U31/BO31,"") -> 0.11131482 | BQ31: =IF(V31>0,U31/V31,0) -> 1.1564626 | BR31: =IF(G31>0,AV31/G31,"") -> 0.3313253 | BS31: =AVERAGE(Tableau1[[#This Row],[STL_pg/Min]],Tableau1[[#This Row],[BLK_pg/Min]],Tableau1[[#This Row],[REB_pg/Min]]) -> 0.15976951 | BT31: =AVERAGE(Tableau1[FG%]) -> 44.610896 | BU31: =AVERAGE(Tableau1[3P%]) -> 29.90246 | BV31: =AVERAGE(Tableau1[FT%]) -> 72.024077
A32: Franz Wagner | B32: ORL | C32: 23 | D32: 60 | E32: 33 | F32: 27 | G32: 33.7 | H32: 1452 | I32: 540 | J32: 1164 | K32: 46.3 | L32: 102 | M32: 354 | N32: 29.5 | O32: 270 | P32: 312 | Q32: 87.1 | R32: 54 | S32: 288 | T32: 342 | U32: 282 | V32: 138 | W32: 78 | X32: 24 | Y32: 150 | Z32: 2436 | AA32: 3 | AB32: 0 | AC32: 4.1 | AD32: 111.8 | AE32: 105.8 | AF32: 6 | AG32: 24.7 | AH32: 2.06 | AI32: 16.5 | AJ32: 2.7 | AK32: 14.6 | AL32: 8.5 | AM32: 8 | AN32: 50.7 | AO32: 55.8 | AP32: 30.6 | AQ32: 97.65 | AR32: 15.3 | AS32: 4116 | AT32: =H32/D32 -> 24.2 | AU32: =U32/D32 -> 4.7 | AV32: =T32/D32 -> 5.7 | AW32: =R32/D32 -> 0.9 | AX32: =S32/D32 -> 4.8 | AY32: =W32/D32 -> 1.3 | AZ32: =X32/D32 -> 0.4 | BA32: =V32/D32 -> 2.3 | BB32: =IF(G32>0,AT32/G32,"") -> 0.71810089 | BC32: =IF(BA32>0,AU32/BA32,"") -> 2.0434783 | BD32: =IF(G32>0,AY32/G32,"") -> 0.038575668 | BE32: =IF(G32>0,AZ32/G32,"") -> 0.011869436 | BF32: =IF(G32>0,AW32/G32,"") -> 0.026706231 | BG32: =IF(G32>0,AX32/G32,"") -> 0.14243323 | BH32: =IF(G32<10,"<10 min",IF(G32<20,"10–19 min",IF(G32<30,"20–29 min",IF(G32<40,"30–39 min","40+ min")))) -> 30–39 min | BI32: =IF(C32<23,"18–22",IF(C32<28,"23–27",IF(C32<33,"28–32","33+"))) -> 23–27 | BJ32: =AN32/100 -> 0.507 | BK32: =AO32/100 -> 0.558 | BL32: =J32/(MAX($J$11:$J$579)) -> 0.70247435 | BM32: =IF(AND(G32>=30,J32>=500),"Conserver","Écarter") -> Conserver | BN32: =AT32/(MAX($AT$11:$AT$579)) -> 0.74012072 | BO32: =G32*D32 -> 2022 | BP32: =IF(BO32>0,U32/BO32,"") -> 0.13946588 | BQ32: =IF(V32>0,U32/V32,0) -> 2.0434783 | BR32: =IF(G32>0,AV32/G32,"") -> 0.16913947 | BS32: =AVERAGE(Tableau1[[#This Row],[STL_pg/Min]],Tableau1[[#This Row],[BLK_pg/Min]],Tableau1[[#This Row],[REB_pg/Min]]) -> 0.073194857 | BT32: =AVERAGE(Tableau1[FG%]) -> 44.610896 | BU32: =AVERAGE(Tableau1[3P%]) -> 29.90246 | BV32: =AVERAGE(Tableau1[FT%]) -> 72.024077
A33: Trae Young | B33: ATL | C33: 26 | D33: 76 | E33: 36 | F33: 40 | G33: 36 | H33: 1839 | I33: 562 | J33: 1376 | K33: 41.1 | L33: 220 | M33: 638 | N33: 34 | O33: 494 | P33: 562 | Q33: 87.5 | R33: 38 | S33: 198 | T33: 236 | U33: 882 | V33: 357 | W33: 91 | X33: 15 | Y33: 144 | Z33: 3397 | AA33: 51 | AB33: 0 | AC33: 0.4 | AD33: 115.2 | AE33: 114.6 | AF33: 0.6 | AG33: 45.2 | AH33: 2.48 | AI33: 30.9 | AJ33: 1.2 | AK33: 7.2 | AL33: 4.2 | AM33: 12.5 | AN33: 49.1 | AO33: 56.7 | AP33: 28.5 | AQ33: 105.51 | AR33: 12.9 | AS33: 6020 | AT33: =H33/D33 -> 24.197368 | AU33: =U33/D33 -> 11.605263 | AV33: =T33/D33 -> 3.1052632 | AW33: =R33/D33 -> 0.5 | AX33: =S33/D33 -> 2.6052632 | AY33: =W33/D33 -> 1.1973684 | AZ33: =X33/D33 -> 0.19736842 | BA33: =V33/D33 -> 4.6973684 | BB33: =IF(G33>0,AT33/G33,"") -> 0.67214912 | BC33: =IF(BA33>0,AU33/BA33,"") -> 2.4705882 | BD33: =IF(G33>0,AY33/G33,"") -> 0.033260234 | BE33: =IF(G33>0,AZ33/G33,"") -> 0.0054824561 | BF33: =IF(G33>0,AW33/G33,"") -> 0.013888889 | BG33: =IF(G33>0,AX33/G33,"") -> 0.072368421 | BH33: =IF(G33<10,"<10 min",IF(G33<20,"10–19 min",IF(G33<30,"20–29 min",IF(G33<40,"30–39 min","40+ min")))) -> 30–39 min | BI33: =IF(C33<23,"18–22",IF(C33<28,"23–27",IF(C33<33,"28–32","33+"))) -> 23–27 | BJ33: =AN33/100 -> 0.491 | BK33: =AO33/100 -> 0.567 | BL33: =J33/(MAX($J$11:$J$579)) -> 0.83041642 | BM33: =IF(AND(G33>=30,J33>=500),"Conserver","Écarter") -> Conserver | BN33: =AT33/(MAX($AT$11:$AT$579)) -> 0.74004024 | BO33: =G33*D33 -> 2736 | BP33: =IF(BO33>0,U33/BO33,"") -> 0.32236842 | BQ33: =IF(V33>0,U33/V33,0) -> 2.4705882 | BR33: =IF(G33>0,AV33/G33,"") -> 0.08625731 | BS33: =AVERAGE(Tableau1[[#This Row],[STL_pg/Min]],Tableau1[[#This Row],[BLK_pg/Min]],Tableau1[[#This Row],[REB_pg/Min]]) -> 0.041666667 | BT33: =AVERAGE(Tableau1[FG%]) -> 44.610896 | BU33: =AVERAGE(Tableau1[3P%]) -> 29.90246 | BV33: =AVERAGE(Tableau1[FT%]) -> 72.024077
A34: Donovan Mitchell | B34: CLE | C34: 28 | D34: 71 | E34: 55 | F34: 16 | G34: 31.4 | H34: 1704 | I34: 582 | J34: 1321 | K34: 44.3 | L34: 234 | M34: 632 | N34: 36.8 | O34: 298 | P34: 362 | Q34: 82.3 | R34: 57 | S34: 263 | T34: 320 | U34: 355 | V34: 149 | W34: 92 | X34: 14 | Y34: 142 | Z34: 2805 | AA34: 6 | AB34: 0 | AC34: 7.4 | AD34: 119.7 | AE34: 109.1 | AF34: 10.5 | AG34: 23.8 | AH34: 2.38 | AI34: 18 | AJ34: 2.5 | AK34: 11.2 | AL34: 6.9 | AM34: 7.6 | AN34: 53.1 | AO34: 57.5 | AP34: 29.8 | AQ34: 102.21 | AR34: 13.7 | AS34: 4762 | AT34: =H34/D34 -> 24 | AU34: =U34/D34 -> 5 | AV34: =T34/D34 -> 4.5070423 | AW34: =R34/D34 -> 0.8028169 | AX34: =S34/D34 -> 3.7042254 | AY34: =W34/D34 -> 1.2957746 | AZ34: =X34/D34 -> 0.1971831 | BA34: =V34/D34 -> 2.0985915 | BB34: =IF(G34>0,AT34/G34,"") -> 0.76433121 | BC34: =IF(BA34>0,AU34/BA34,"") -> 2.3825503 | BD34: =IF(G34>0,AY34/G34,"") -> 0.041266709 | BE34: =IF(G34>0,AZ34/G34,"") -> 0.0062797165 | BF34: =IF(G34>0,AW34/G34,"") -> 0.025567417 | BG34: =IF(G34>0,AX34/G34,"") -> 0.11796896 | BH34: =IF(G34<10,"<10 min",IF(G34<20,"10–19 min",IF(G34<30,"20–29 min",IF(G34<40,"30–39 min","40+ min")))) -> 30–39 min | BI34: =IF(C34<23,"18–22",IF(C34<28,"23–27",IF(C34<33,"28–32","33+"))) -> 28–32 | BJ34: =AN34/100 -> 0.531 | BK34: =AO34/100 -> 0.575 | BL34: =J34/(MAX($J$11:$J$579)) -> 0.7972239 | BM34: =IF(AND(G34>=30,J34>=500),"Conserver","Écarter") -> Conserver | BN34: =AT34/(MAX($AT$11:$AT$579)) -> 0.73400402 | BO34: =G34*D34 -> 2229.4 | BP34: =IF(BO34>0,U34/BO34,"") -> 0.15923567 | BQ34: =IF(V34>0,U34/V34,0) -> 2.3825503 | BR34: =IF(G34>0,AV34/G34,"") -> 0.14353638 | BS34: =AVERAGE(Tableau1[[#This Row],[STL_pg/Min]],Tableau1[[#This Row],[BLK_pg/Min]],Tableau1[[#This Row],[REB_pg/Min]]) -> 0.063694268 | BT34: =AVERAGE(Tableau1[FG%]) -> 44.610896 | BU34: =AVERAGE(Tableau1[3P%]) -> 29.90246 | BV34: =AVERAGE(Tableau1[FT%]) -> 72.024077
A35: Cam Thomas | B35: BKN | C35: 23 | D35: 25 | E35: 8 | F35: 17 | G35: 31.2 | H35: 600 | I35: 200 | J35: 455 | K35: 43.8 | L35: 68 | M35: 195 | N35: 34.9 | O35: 133 | P35: 150 | Q35: 88.1 | R35: 15 | S35: 68 | T35: 83 | U35: 95 | V35: 63 | W35: 15 | X35: 3 | Y35: 45 | Z35: 828 | AA35: 1 | AB35: 0 | AC35: -3.7 | AD35: 114.9 | AE35: 120.6 | AF35: -5.7 | AG35: 21.7 | AH35: 1.52 | AI35: 14 | AJ35: 2 | AK35: 8.9 | AL35: 5.4 | AM35: 9.2 | AN35: 51.3 | AO35: 57.5 | AP35: 32.8 | AQ35: 96.1 | AR35: 12.2 | AS35: 1563 | AT35: =H35/D35 -> 24 | AU35: =U35/D35 -> 3.8 | AV35: =T35/D35 -> 3.32 | AW35: =R35/D35 -> 0.6 | AX35: =S35/D35 -> 2.72 | AY35: =W35/D35 -> 0.6 | AZ35: =X35/D35 -> 0.12 | BA35: =V35/D35 -> 2.52 | BB35: =IF(G35>0,AT35/G35,"") -> 0.76923077 | BC35: =IF(BA35>0,AU35/BA35,"") -> 1.5079365 | BD35: =IF(G35>0,AY35/G35,"") -> 0.019230769 | BE35: =IF(G35>0,AZ35/G35,"") -> 0.0038461538 | BF35: =IF(G35>0,AW35/G35,"") -> 0.019230769 | BG35: =IF(G35>0,AX35/G35,"") -> 0.087179487 | BH35: =IF(G35<10,"<10 min",IF(G35<20,"10–19 min",IF(G35<30,"20–29 min",IF(G35<40,"30–39 min","40+ min")))) -> 30–39 min | BI35: =IF(C35<23,"18–22",IF(C35<28,"23–27",IF(C35<33,"28–32","33+"))) -> 23–27 | BJ35: =AN35/100 -> 0.513 | BK35: =AO35/100 -> 0.575 | BL35: =J35/(MAX($J$11:$J$579)) -> 0.27459264 | BM35: =IF(AND(G35>=30,J35>=500),"Conserver","Écarter") -> Écarter | BN35: =AT35/(MAX($AT$11:$AT$579)) -> 0.73400402 | BO35: =G35*D35 -> 780 | BP35: =IF(BO35>0,U35/BO35,"") -> 0.12179487 | BQ35: =IF(V35>0,U35/V35,0) -> 1.5079365 | BR35: =IF(G35>0,AV35/G35,"") -> 0.10641026 | BS35: =AVERAGE(Tableau1[[#This Row],[STL_pg/Min]],Tableau1[[#This Row],[BLK_pg/Min]],Tableau1[[#This Row],[REB_pg/Min]]) -> 0.043162393 | BT35: =AVERAGE(Tableau1[FG%]) -> 44.610896 | BU35: =AVERAGE(Tableau1[3P%]) -> 29.90246 | BV35: =AVERAGE(Tableau1[FT%]) -> 72.024077
A36: Tyler Herro | B36: MIA | C36: 25 | D36: 77 | E36: 37 | F36: 40 | G36: 35.4 | H36: 1840 | I36: 655 | J36: 1378 | K36: 47.2 | L36: 254 | M36: 670 | N36: 37.5 | O36: 285 | P36: 323 | Q36: 87.8 | R36: 39 | S36: 362 | T36: 400 | U36: 424 | V36: 200 | W36: 69 | X36: 15 | Y36: 85 | Z36: 3018 | AA36: 9 | AB36: 0 | AC36: 1.3 | AD36: 113.9 | AE36: 112.6 | AF36: 1.3 | AG36: 25.4 | AH36: 2.14 | AI36: 20 | AJ36: 1.3 | AK36: 13.2 | AL36: 7.3 | AM36: 9.3 | AN36: 56.3 | AO36: 60.5 | AP36: 27.1 | AQ36: 97.78 | AR36: 13.9 | AS36: 5564 | AT36: =H36/D36 -> 23.896104 | AU36: =U36/D36 -> 5.5064935 | AV36: =T36/D36 -> 5.1948052 | AW36: =R36/D36 -> 0.50649351 | AX36: =S36/D36 -> 4.7012987 | AY36: =W36/D36 -> 0.8961039 | AZ36: =X36/D36 -> 0.19480519 | BA36: =V36/D36 -> 2.5974026 | BB36: =IF(G36>0,AT36/G36,"") -> 0.67503118 | BC36: =IF(BA36>0,AU36/BA36,"") -> 2.12 | BD36: =IF(G36>0,AY36/G36,"") -> 0.025313669 | BE36: =IF(G36>0,AZ36/G36,"") -> 0.0055029716 | BF36: =IF(G36>0,AW36/G36,"") -> 0.014307726 | BG36: =IF(G36>0,AX36/G36,"") -> 0.13280505 | BH36: =IF(G36<10,"<10 min",IF(G36<20,"10–19 min",IF(G36<30,"20–29 min",IF(G36<40,"30–39 min","40+ min")))) -> 30–39 min | BI36: =IF(C36<23,"18–22",IF(C36<28,"23–27",IF(C36<33,"28–32","33+"))) -> 23–27 | BJ36: =AN36/100 -> 0.563 | BK36: =AO36/100 -> 0.605 | BL36: =J36/(MAX($J$11:$J$579)) -> 0.83162342 | BM36: =IF(AND(G36>=30,J36>=500),"Conserver","Écarter") -> Conserver | BN36: =AT36/(MAX($AT$11:$AT$579)) -> 0.73082652 | BO36: =G36*D36 -> 2725.8 | BP36: =IF(BO36>0,U36/BO36,"") -> 0.15555066 | BQ36: =IF(V36>0,U36/V36,0) -> 2.12 | BR36: =IF(G36>0,AV36/G36,"") -> 0.14674591 | BS36: =AVERAGE(Tableau1[[#This Row],[STL_pg/Min]],Tableau1[[#This Row],[BLK_pg/Min]],Tableau1[[#This Row],[REB_pg/Min]]) -> 0.059187517 | BT36: =AVERAGE(Tableau1[FG%]) -> 44.610896 | BU36: =AVERAGE(Tableau1[3P%]) -> 29.90246 | BV36: =AVERAGE(Tableau1[FT%]) -> 72.024077
A37: Joel Embiid | B37: PHI | C37: 31 | D37: 19 | E37: 8 | F37: 11 | G37: 30.2 | H37: 452 | I37: 141 | J37: 315 | K37: 44.4 | L37: 23 | M37: 78 | N37: 29.9 | O37: 148 | P37: 169 | Q37: 88.2 | R37: 36 | S37: 120 | T37: 156 | U37: 86 | V37: 63 | W37: 13 | X37: 17 | Y37: 42 | Z37: 800 | AA37: 7 | AB37: 1 | AC37: -3 | AD37: 104 | AE37: 109.5 | AF37: -5.5 | AG37: 28.6 | AH37: 1.37 | AI37: 15.8 | AJ37: 6.2 | AK37: 20.7 | AL37: 13.4 | AM37: 11.5 | AN37: 48.1 | AO37: 58 | AP37: 34.2 | AQ37: 99.95 | AR37: 16.9 | AS37: 1200 | AT37: =H37/D37 -> 23.789474 | AU37: =U37/D37 -> 4.5263158 | AV37: =T37/D37 -> 8.2105263 | AW37: =R37/D37 -> 1.8947368 | AX37: =S37/D37 -> 6.3157895 | AY37: =W37/D37 -> 0.68421053 | AZ37: =X37/D37 -> 0.89473684 | BA37: =V37/D37 -> 3.3157895 | BB37: =IF(G37>0,AT37/G37,"") -> 0.78773092 | BC37: =IF(BA37>0,AU37/BA37,"") -> 1.3650794 | BD37: =IF(G37>0,AY37/G37,"") -> 0.022655978 | BE37: =IF(G37>0,AZ37/G37,"") -> 0.029627048 | BF37: =IF(G37>0,AW37/G37,"") -> 0.062739631 | BG37: =IF(G37>0,AX37/G37,"") -> 0.2091321 | BH37: =IF(G37<10,"<10 min",IF(G37<20,"10–19 min",IF(G37<30,"20–29 min",IF(G37<40,"30–39 min","40+ min")))) -> 30–39 min | BI37: =IF(C37<23,"18–22",IF(C37<28,"23–27",IF(C37<33,"28–32","33+"))) -> 28–32 | BJ37: =AN37/100 -> 0.481 | BK37: =AO37/100 -> 0.58 | BL37: =J37/(MAX($J$11:$J$579)) -> 0.1901026 | BM37: =IF(AND(G37>=30,J37>=500),"Conserver","Écarter") -> Écarter | BN37: =AT37/(MAX($AT$11:$AT$579)) -> 0.72756539 | BO37: =G37*D37 -> 573.8 | BP37: =IF(BO37>0,U37/BO37,"") -> 0.14987801 | BQ37: =IF(V37>0,U37/V37,0) -> 1.3650794 | BR37: =IF(G37>0,AV37/G37,"") -> 0.27187173 | BS37: =AVERAGE(Tableau1[[#This Row],[STL_pg/Min]],Tableau1[[#This Row],[BLK_pg/Min]],Tableau1[[#This Row],[REB_pg/Min]]) -> 0.10805159 | BT37: =AVERAGE(Tableau1[FG%]) -> 44.610896 | BU37: =AVERAGE(Tableau1[3P%]) -> 29.90246 | BV37: =AVERAGE(Tableau1[FT%]) -> 72.024077
A38: De'Aaron Fox | B38: SAS | C38: 27 | D38: 62 | E38: 27 | F38: 35 | G38: 36.1 | H38: 1457 | I38: 539 | J38: 1166 | K38: 46.3 | L38: 118 | M38: 378 | N38: 31 | O38: 260 | P38: 316 | Q38: 82.7 | R38: 56 | S38: 242 | T38: 298 | U38: 391 | V38: 174 | W38: 93 | X38: 25 | Y38: 161 | Z38: 2579 | AA38: 9 | AB38: 0 | AC38: -1.1 | AD38: 113.7 | AE38: 114.9 | AF38: -1.2 | AG38: 26.2 | AH38: 2.25 | AI38: 21 | AJ38: 2.3 | AK38: 10.6 | AL38: 6.4 | AM38: 9.3 | AN38: 51.4 | AO38: 56 | AP38: 27.4 | AQ38: 102.22 | AR38: 11.9 | AS38: 4768 | AT38: =H38/D38 -> 23.5 | AU38: =U38/D38 -> 6.3064516 | AV38: =T38/D38 -> 4.8064516 | AW38: =R38/D38 -> 0.90322581 | AX38: =S38/D38 -> 3.9032258 | AY38: =W38/D38 -> 1.5 | AZ38: =X38/D38 -> 0.40322581 | BA38: =V38/D38 -> 2.8064516 | BB38: =IF(G38>0,AT38/G38,"") -> 0.65096953 | BC38: =IF(BA38>0,AU38/BA38,"") -> 2.2471264 | BD38: =IF(G38>0,AY38/G38,"") -> 0.041551247 | BE38: =IF(G38>0,AZ38/G38,"") -> 0.01116969 | BF38: =IF(G38>0,AW38/G38,"") -> 0.025020105 | BG38: =IF(G38>0,AX38/G38,"") -> 0.1081226 | BH38: =IF(G38<10,"<10 min",IF(G38<20,"10–19 min",IF(G38<30,"20–29 min",IF(G38<40,"30–39 min","40+ min")))) -> 30–39 min | BI38: =IF(C38<23,"18–22",IF(C38<28,"23–27",IF(C38<33,"28–32","33+"))) -> 23–27 | BJ38: =AN38/100 -> 0.514 | BK38: =AO38/100 -> 0.56 | BL38: =J38/(MAX($J$11:$J$579)) -> 0.70368135 | BM38: =IF(AND(G38>=30,J38>=500),"Conserver","Écarter") -> Conserver | BN38: =AT38/(MAX($AT$11:$AT$579)) -> 0.71871227 | BO38: =G38*D38 -> 2238.2 | BP38: =IF(BO38>0,U38/BO38,"") -> 0.17469395 | BQ38: =IF(V38>0,U38/V38,0) -> 2.2471264 | BR38: =IF(G38>0,AV38/G38,"") -> 0.1331427 | BS38: =AVERAGE(Tableau1[[#This Row],[STL_pg/Min]],Tableau1[[#This Row],[BLK_pg/Min]],Tableau1[[#This Row],[REB_pg/Min]]) -> 0.061954547 | BT38: =AVERAGE(Tableau1[FG%]) -> 44.610896 | BU38: =AVERAGE(Tableau1[3P%]) -> 29.90246 | BV38: =AVERAGE(Tableau1[FT%]) -> 72.024077
A39: Zach LaVine | B39: SAC | C39: 30 | D39: 74 | E39: 32 | F39: 42 | G39: 35.2 | H39: 1724 | I39: 622 | J39: 1221 | K39: 51.1 | L39: 237 | M39: 533 | N39: 44.6 | O39: 237 | P39: 289 | Q39: 82.5 | R39: 22 | S39: 296 | T39: 318 | U39: 311 | V39: 207 | W39: 59 | X39: 15 | Y39: 118 | Z39: 2568 | AA39: 6 | AB39: 0 | AC39: -0.9 | AD39: 115.4 | AE39: 116.8 | AF39: -1.4 | AG39: 17.8 | AH39: 1.49 | AI39: 16.7 | AJ39: 0.9 | AK39: 10.7 | AL39: 5.9 | AM39: 11.2 | AN39: 60.9 | AO39: 63.9 | AP39: 25.1 | AQ39: 101.28 | AR39: 11.5 | AS39: 5493 | AT39: =H39/D39 -> 23.297297 | AU39: =U39/D39 -> 4.2027027 | AV39: =T39/D39 -> 4.2972973 | AW39: =R39/D39 -> 0.2972973 | AX39: =S39/D39 -> 4 | AY39: =W39/D39 -> 0.7972973 | AZ39: =X39/D39 -> 0.2027027 | BA39: =V39/D39 -> 2.7972973 | BB39: =IF(G39>0,AT39/G39,"") -> 0.66185504 | BC39: =IF(BA39>0,AU39/BA39,"") -> 1.5024155 | BD39: =IF(G39>0,AY39/G39,"") -> 0.022650491 | BE39: =IF(G39>0,AZ39/G39,"") -> 0.0057585995 | BF39: =IF(G39>0,AW39/G39,"") -> 0.0084459459 | BG39: =IF(G39>0,AX39/G39,"") -> 0.11363636 | BH39: =IF(G39<10,"<10 min",IF(G39<20,"10–19 min",IF(G39<30,"20–29 min",IF(G39<40,"30–39 min","40+ min")))) -> 30–39 min | BI39: =IF(C39<23,"18–22",IF(C39<28,"23–27",IF(C39<33,"28–32","33+"))) -> 28–32 | BJ39: =AN39/100 -> 0.609 | BK39: =AO39/100 -> 0.639 | BL39: =J39/(MAX($J$11:$J$579)) -> 0.73687387 | BM39: =IF(AND(G39>=30,J39>=500),"Conserver","Écarter") -> Conserver | BN39: =AT39/(MAX($AT$11:$AT$579)) -> 0.71251292 | BO39: =G39*D39 -> 2604.8 | BP39: =IF(BO39>0,U39/BO39,"") -> 0.11939496 | BQ39: =IF(V39>0,U39/V39,0) -> 1.5024155 | BR39: =IF(G39>0,AV39/G39,"") -> 0.12208231 | BS39: =AVERAGE(Tableau1[[#This Row],[STL_pg/Min]],Tableau1[[#This Row],[BLK_pg/Min]],Tableau1[[#This Row],[REB_pg/Min]]) -> 0.0501638 | BT39: =AVERAGE(Tableau1[FG%]) -> 44.610896 | BU39: =AVERAGE(Tableau1[3P%]) -> 29.90246 | BV39: =AVERAGE(Tableau1[FT%]) -> 72.024077
A40: Ja Morant | B40: MEM | C40: 25 | D40: 50 | E40: 30 | F40: 20 | G40: 30.4 | H40: 1160 | I40: 405 | J40: 890 | K40: 45.4 | L40: 90 | M40: 285 | N40: 30.9 | O40: 265 | P40: 320 | Q40: 82.4 | R40: 35 | S40: 170 | T40: 205 | U40: 365 | V40: 185 | W40: 60 | X40: 10 | Y40: 115 | Z40: 1985 | AA40: 13 | AB40: 1 | AC40: 4.5 | AD40: 116.4 | AE40: 109.6 | AF40: 6.8 | AG40: 35.5 | AH40: 1.97 | AI40: 23.1 | AJ40: 2.1 | AK40: 10.1 | AL40: 6.2 | AM40: 11.8 | AN40: 50.4 | AO40: 56.3 | AP40: 31.2 | AQ40: 105.74 | AR40: 14.1 | AS40: 3346 | AT40: =H40/D40 -> 23.2 | AU40: =U40/D40 -> 7.3 | AV40: =T40/D40 -> 4.1 | AW40: =R40/D40 -> 0.7 | AX40: =S40/D40 -> 3.4 | AY40: =W40/D40 -> 1.2 | AZ40: =X40/D40 -> 0.2 | BA40: =V40/D40 -> 3.7 | BB40: =IF(G40>0,AT40/G40,"") -> 0.76315789 | BC40: =IF(BA40>0,AU40/BA40,"") -> 1.972973 | BD40: =IF(G40>0,AY40/G40,"") -> 0.039473684 | BE40: =IF(G40>0,AZ40/G40,"") -> 0.0065789474 | BF40: =IF(G40>0,AW40/G40,"") -> 0.023026316 | BG40: =IF(G40>0,AX40/G40,"") -> 0.11184211 | BH40: =IF(G40<10,"<10 min",IF(G40<20,"10–19 min",IF(G40<30,"20–29 min",IF(G40<40,"30–39 min","40+ min")))) -> 30–39 min | BI40: =IF(C40<23,"18–22",IF(C40<28,"23–27",IF(C40<33,"28–32","33+"))) -> 23–27 | BJ40: =AN40/100 -> 0.504 | BK40: =AO40/100 -> 0.563 | BL40: =J40/(MAX($J$11:$J$579)) -> 0.53711527 | BM40: =IF(AND(G40>=30,J40>=500),"Conserver","Écarter") -> Conserver | BN40: =AT40/(MAX($AT$11:$AT$579)) -> 0.70953722 | BO40: =G40*D40 -> 1520 | BP40: =IF(BO40>0,U40/BO40,"") -> 0.24013158 | BQ40: =IF(V40>0,U40/V40,0) -> 1.972973 | BR40: =IF(G40>0,AV40/G40,"") -> 0.13486842 | BS40: =AVERAGE(Tableau1[[#This Row],[STL_pg/Min]],Tableau1[[#This Row],[BLK_pg/Min]],Tableau1[[#This Row],[REB_pg/Min]]) -> 0.060307018 | BT40: =AVERAGE(Tableau1[FG%]) -> 44.610896 | BU40: =AVERAGE(Tableau1[3P%]) -> 29.90246 | BV40: =AVERAGE(Tableau1[FT%]) -> 72.024077
... A579: Jalen McDaniels | B579: WAS | C579: 27 | D579: 4 | E579: 2 | F579: 2 | G579: 1.8 | H579: 0 | I579: 0 | J579: 0 | K579: 0 | L579: 0 | M579: 0 | N579: 0 | O579: 0 | P579: 0 | Q579: 0 | R579: 0 | S579: 0 | T579: 0 | U579: 1 | V579: 0 | W579: 1 | X579: 0 | Y579: 0 | Z579: 4 | AA579: 0 | AB579: 0 | AC579: -0.3 | AD579: 81.3 | AE579: 77.8 | AF579: 3.5 | AG579: 25 | AH579: 0 | AI579: 100 | AJ579: 0 | AK579: 0 | AL579: 0 | AM579: 0 | AN579: 0 | AO579: 0 | AP579: 0 | AQ579: 111.25 | AR579: 11.4 | AS579: 16 | AT579: =H579/D579 -> 0 | AU579: =U579/D579 -> 0.25 | AV579: =T579/D579 -> 0 | AW579: =R579/D579 -> 0 | AX579: =S579/D579 -> 0 | AY579: =W579/D579 -> 0.25 | AZ579: =X579/D579 -> 0 | BA579: =V579/D579 -> 0 | BB579: =IF(G579>0,AT579/G579,"") -> 0 | BC579: =IF(BA579>0,AU579/BA579,"") | BD579: =IF(G579>0,AY579/G579,"") -> 0.13888889 | BE579: =IF(G579>0,AZ579/G579,"") -> 0 | BF579: =IF(G579>0,AW579/G579,"") -> 0 | BG579: =IF(G579>0,AX579/G579,"") -> 0 | BH579: =IF(G579<10,"<10 min",IF(G579<20,"10–19 min",IF(G579<30,"20–29 min",IF(G579<40,"30–39 min","40+ min")))) -> <10 min | BI579: =IF(C579<23,"18–22",IF(C579<28,"23–27",IF(C579<33,"28–32","33+"))) -> 23–27 | BJ579: =AN579/100 -> 0 | BK579: =AO579/100 -> 0 | BL579: =J579/(MAX($J$11:$J$579)) -> 0 | BM579: =IF(AND(G579>=30,J579>=500),"Conserver","Écarter") -> Écarter | BN579: =AT579/(MAX($AT$11:$AT$579)) -> 0 | BO579: =G579*D579 -> 7.2 | BP579: =IF(BO579>0,U579/BO579,"") -> 0.13888889 | BQ579: =IF(V579>0,U579/V579,0) -> 0 | BR579: =IF(G579>0,AV579/G579,"") -> 0 | BS579: =AVERAGE(Tableau1[[#This Row],[STL_pg/Min]],Tableau1[[#This Row],[BLK_pg/Min]],Tableau1[[#This Row],[REB_pg/Min]]) -> 0.046296296 | BT579: =AVERAGE(Tableau1[FG%]) -> 44.610896 | BU579: =AVERAGE(Tableau1[3P%]) -> 29.90246 | BV579: =AVERAGE(Tableau1[FT%]) -> 72.024077
A582: Filtre Tableau sur Tot_Min > 1000
A584: Player | B584: Team | C584: Age | D584: GP | E584: W | F584: L | G584: Min | H584: PTS | I584: FGM | J584: FGA | K584: FG% | L584: 15:00 | M584: 3PA | N584: 3P% | O584: FTM | P584: FTA | Q584: FT% | R584: OREB | S584: DREB | T584: REB | U584: AST | V584: TOV | W584: STL | X584: BLK | Y584: PF | Z584: FP | AA584: DD2 | AB584: TD3 | AC584: +/- | AD584: OFFRTG | AE584: DEFRTG | AF584: NETRTG | AG584: AST% | AH584: AST/TO | AI584: AST RATIO | AJ584: OREB% | AK584: DREB% | AL584: REB% | AM584: TO RATIO | AN584: EFG% | AO584: TS% | AP584: USG% | AQ584: PACE | AR584: PIE | AS584: POSS | AT584: PTS_pg | AU584: AST_pg | AV584: REB_pg | AW584: OREB_pg | AX584: DREB_pg | AY584: STL_pg | AZ584: BLK_pg | BA584: TOV_pg | BB584: PTS_pg/Min | BC584: AST_pg/TOV_pg | BD584: STL_pg/Min | BE584: BLK_pg/Min | BF584: OREB_pg/Min | BG584: DREB_pg/Min | BH584: Classe_Min | BI584: Classe_Age | BJ584: EFG%_corr | BK584: TS%_corr | BL584: FGA_norm | BM584: Filtre joueur | BN584: PTG_pg_Norm | BO584: Min_tot | BP584: AST/Min | BQ584: AST/TOV | BR584: REB_pg/Min
A585: Mikal Bridges | B585: NYK | C585: 28 | D585: 82 | E585: 51 | F585: 31 | G585: 37 | H585: 1443 | I585: 590 | J585: 1181 | K585: 50 | L585: 164 | M585: 459 | N585: 35.4 | O585: 98 | P585: 115 | Q585: 81.4 | R585: 74 | S585: 189 | T585: 262 | U585: 303 | V585: 131 | W585: 74 | X585: 41 | Y585: 123 | Z585: 2435 | AA585: 1 | AB585: 0 | AC585: 4.1 | AD585: 118.4 | AE585: 112.9 | AF585: 5.6 | AG585: 14.1 | AH585: 2.32 | AI585: 18.3 | AJ585: 2.4 | AK585: 6.3 | AL585: 4.3 | AM585: 7.9 | AN585: 57 | AO585: 58.5 | AP585: 19.2 | AQ585: 98.1 | AR585: 9 | AS585: 6200 | AT585: 17.597561 | AU585: 3.695122 | AV585: 3.195122 | AW585: 0.90243902 | AX585: 2.304878 | AY585: 0.90243902 | AZ585: 0.5 | BA585: 1.597561 | BB585: 0.47560976 | BC585: 2.3129771 | BD585: 0.024390244 | BE585: 0.013513514 | BF585: 0.024390244 | BG585: 0.062294001 | BH585: 30–39 min | BI585: 28–32 | BJ585: 0.57 | BK585: 0.585 | BL585: 0.71273386 | BM585: Conserver | BN585: 0.53819502 | BO585: 3034 | BP585: 0.099868161 | BQ585: 2.3129771 | BR585: 0.086354647
A586: Josh Hart | B586: NYK | C586: 30 | D586: 77 | E586: 48 | F586: 29 | G586: 37.6 | H586: 1047 | I586: 400 | J586: 770 | K586: 52.5 | L586: 85 | M586: 254 | N586: 33.3 | O586: 162 | P586: 208 | Q586: 77.6 | R586: 162 | S586: 578 | T586: 739 | U586: 454 | V586: 162 | W586: 116 | X586: 31 | Y586: 200 | Z586: 2895 | AA586: 34 | AB586: 9 | AC586: 2.6 | AD586: 117.9 | AE586: 114.3 | AF586: 3.6 | AG586: 20.6 | AH586: 2.87 | AI586: 30.8 | AJ586: 5.7 | AK586: 20.3 | AL586: 13 | AM586: 10.8 | AN586: 57.9 | AO586: 61.1 | AP586: 15.1 | AQ586: 97.79 | AR586: 11.9 | AS586: 5898 | AT586: 13.597403 | AU586: 5.8961039 | AV586: 9.5974026 | AW586: 2.1038961 | AX586: 7.5064935 | AY586: 1.5064935 | AZ586: 0.4025974 | BA586: 2.1038961 | BB586: 0.36163305 | BC586: 2.8024691 | BD586: 0.040066317 | BE586: 0.010707378 | BF586: 0.055954684 | BG586: 0.19964078 | BH586: 30–39 min | BI586: 28–32 | BJ586: 0.579 | BK586: 0.611 | BL586: 0.46469523 | BM586: Conserver | BN586: 0.41585618 | BO586: 2895.2 | BP586: 0.15681127 | BQ586: 2.8024691 | BR586: 0.25525007
A587: Anthony Edwards | B587: MIN | C587: 23 | D587: 79 | E587: 48 | F587: 31 | G587: 36.3 | H587: 2180 | I587: 719 | J587: 1612 | K587: 44.7 | L587: 324 | M587: 814 | N587: 39.5 | O587: 419 | P587: 498 | Q587: 83.7 | R587: 63 | S587: 387 | T587: 450 | U587: 356 | V587: 253 | W587: 95 | X587: 47 | Y587: 150 | Z587: 3429 | AA587: 7 | AB587: 0 | AC587: 3.7 | AD587: 116.2 | AE587: 111.4 | AF587: 4.8 | AG587: 20.9 | AH587: 1.44 | AI587: 14.8 | AJ587: 2.1 | AK587: 13.1 | AL587: 7.7 | AM587: 10.3 | AN587: 54.7 | AO587: 59.5 | AP587: 30.7 | AQ587: 98.27 | AR587: 14 | AS587: 5883 | AT587: 27.594937 | AU587: 4.5063291 | AV587: 5.6962025 | AW587: 0.79746835 | AX587: 4.8987342 | AY587: 1.2025316 | AZ587: 0.59493671 | BA587: 3.2025316 | BB587: 0.76019109 | BC587: 1.4071146 | BD587: 0.033127594 | BE587: 0.016389441 | BF587: 0.021968825 | BG587: 0.13495135 | BH587: 30–39 min | BI587: 23–27 | BJ587: 0.547 | BK587: 0.595 | BL587: 0.97284249 | BM587: Conserver | BN587: 0.84394977 | BO587: 2867.7 | BP587: 0.1241413 | BQ587: 1.4071146 | BR587: 0.15692018
A588: Devin Booker | B588: PHX | C588: 28 | D588: 75 | E588: 35 | F588: 40 | G588: 37.3 | H588: 1920 | I588: 653 | J588: 1418 | K588: 46.1 | L588: 180 | M588: 548 | N588: 33.2 | O588: 435 | P588: 480 | Q588: 89.4 | R588: 75 | S588: 233 | T588: 308 | U588: 533 | V588: 218 | W588: 68 | X588: 15 | Y588: 195 | Z588: 3113 | AA588: 16 | AB588: 0 | AC588: -2.4 | AD588: 115.3 | AE588: 118.5 | AF588: -3.2 | AG588: 30.1 | AH588: 2.4 | AI588: 22.4 | AJ588: 2.8 | AK588: 8 | AL588: 5.5 | AM588: 9.3 | AN588: 52.5 | AO588: 58.9 | AP588: 28.5 | AQ588: 98.72 | AR588: 12.2 | AS588: 5752 | AT588: 25.6 | AU588: 7.1066667 | AV588: 4.1066667 | AW588: 1 | AX588: 3.1066667 | AY588: 0.90666667 | AZ588: 0.2 | BA588: 2.9066667 | BB588: 0.68632708 | BC588: 2.4449541 | BD588: 0.024307417 | BE588: 0.0053619303 | BF588: 0.026809651 | BG588: 0.083288651 | BH588: 30–39 min | BI588: 28–32 | BJ588: 0.525 | BK588: 0.589 | BL588: 0.85576343 | BM588: Conserver | BN588: 0.78293763 | BO588: 2797.5 | BP588: 0.19052726 | BQ588: 2.4449541 | BR588: 0.1100983
A589: James Harden | B589: LAC | C589: 35 | D589: 79 | E589: 50 | F589: 29 | G589: 35.3 | H589: 1801 | I589: 529 | J589: 1296 | K589: 41 | L589: 237 | M589: 672 | N589: 35.2 | O589: 506 | P589: 577 | Q589: 87.4 | R589: 55 | S589: 403 | T589: 458 | U589: 687 | V589: 340 | W589: 119 | X589: 55 | Y589: 166 | Z589: 3555 | AA589: 38 | AB589: 3 | AC589: 4.4 | AD589: 115.4 | AE589: 109.2 | AF589: 6.2 | AG589: 36.5 | AH589: 2.01 | AI589: 26.9 | AJ589: 2 | AK589: 14.3 | AL589: 8.3 | AM589: 13.4 | AN589: 50.1 | AO589: 58.2 | AP589: 28.6 | AQ589: 98.82 | AR589: 14.5 | AS589: 5737 | AT589: 22.797468 | AU589: 8.6962025 | AV589: 5.7974684 | AW589: 0.69620253 | AX589: 5.1012658 | AY589: 1.5063291 | AZ589: 0.69620253 | BA589: 4.3037975 | BB589: 0.64582063 | BC589: 2.0205882 | BD589: 0.042672213 | BE589: 0.019722451 | BF589: 0.019722451 | BG589: 0.14451178 | BH589: 30–39 min | BI589: 33+ | BJ589: 0.501 | BK589: 0.582 | BL589: 0.78213639 | BM589: Conserver | BN589: 0.6972264 | BO589: 2788.7 | BP589: 0.24635135 | BQ589: 2.0205882 | BR589: 0.16423423
A590: DeMar DeRozan | B590: SAC | C590: 35 | D590: 77 | E590: 38 | F590: 39 | G590: 35.9 | H590: 1709 | I590: 624 | J590: 1309 | K590: 47.7 | L590: 85 | M590: 254 | N590: 32.8 | O590: 377 | P590: 439 | Q590: 85.7 | R590: 46 | S590: 246 | T590: 300 | U590: 339 | V590: 108 | W590: 62 | X590: 31 | Y590: 146 | Z590: 2757 | AA590: 3 | AB590: 0 | AC590: 1.4 | AD590: 116.8 | AE590: 115.3 | AF590: 1.5 | AG590: 18.2 | AH590: 3.26 | AI590: 17.7 | AJ590: 1.8 | AK590: 9 | AL590: 5.4 | AM590: 5.4 | AN590: 50.9 | AO590: 56.9 | AP590: 24.4 | AQ590: 99.35 | AR590: 11.2 | AS590: 5740 | AT590: 22.194805 | AU590: 4.4025974 | AV590: 3.8961039 | AW590: 0.5974026 | AX590: 3.1948052 | AY590: 0.80519481 | AZ590: 0.4025974 | BA590: 1.4025974 | BB590: 0.6182397 | BC590: 3.1388889 | BD590: 0.022428825 | BE590: 0.011214412 | BF590: 0.016640741 | BG590: 0.088991788 | BH590: 30–39 min | BI590: 33+ | BJ590: 0.509 | BK590: 0.569 | BL590: 0.78998189 | BM590: Conserver | BN590: 0.67879485 | BO590: 2764.3 | BP590: 0.12263503 | BQ590: 3.1388889 | BR590: 0.10852657
A591: Trae Young | B591: ATL | C591: 26 | D591: 76 | E591: 36 | F591: 40 | G591: 36 | H591: 1839 | I591: 562 | J591: 1376 | K591: 41.1 | L591: 220 | M591: 638 | N591: 34 | O591: 494 | P591: 562 | Q591: 87.5 | R591: 38 | S591: 198 | T591: 236 | U591: 882 | V591: 357 | W591: 91 | X591: 15 | Y591: 144 | Z591: 3397 | AA591: 51 | AB591: 0 | AC591: 0.4 | AD591: 115.2 | AE591: 114.6 | AF591: 0.6 | AG591: 45.2 | AH591: 2.48 | AI591: 30.9 | AJ591: 1.2 | AK591: 7.2 | AL591: 4.2 | AM591: 12.5 | AN591: 49.1 | AO591: 56.7 | AP591: 28.5 | AQ591: 105.51 | AR591: 12.9 | AS591: 6020 | AT591: 24.197368 | AU591: 11.605263 | AV591: 3.1052632 | AW591: 0.5 | AX591: 2.6052632 | AY591: 1.1973684 | AZ591: 0.19736842 | BA591: 4.6973684 | BB591: 0.67214912 | BC591: 2.4705882 | BD591: 0.033260234 | BE591: 0.0054824561 | BF591: 0.013888889 | BG591: 0.072368421 | BH591: 30–39 min | BI591: 23–27 | BJ591: 0.491 | BK591: 0.567 | BL591: 0.83041642 | BM591: Conserver | BN591: 0.74004024 | BO591: 2736 | BP591: 0.32236842 | BQ591: 2.4705882 | BR591: 0.08625731
A592: Tyler Herro | B592: MIA | C592: 25 | D592: 77 | E592: 37 | F592: 40 | G592: 35.4 | H592: 1840 | I592: 655 | J592: 1378 | K592: 47.2 | L592: 254 | M592: 670 | N592: 37.5 | O592: 285 | P592: 323 | Q592: 87.8 | R592: 39 | S592: 362 | T592: 400 | U592: 424 | V592: 200 | W592: 69 | X592: 15 | Y592: 85 | Z592: 3018 | AA592: 9 | AB592: 0 | AC592: 1.3 | AD592: 113.9 | AE592: 112.6 | AF592: 1.3 | AG592: 25.4 | AH592: 2.14 | AI592: 20 | AJ592: 1.3 | AK592: 13.2 | AL592: 7.3 | AM592: 9.3 | AN592: 56.3 | AO592: 60.5 | AP592: 27.1 | AQ592: 97.78 | AR592: 13.9 | AS592: 5564 | AT592: 23.896104 | AU592: 5.5064935 | AV592: 5.1948052 | AW592: 0.50649351 | AX592: 4.7012987 | AY592: 0.8961039 | AZ592: 0.19480519 | BA592: 2.5974026 | BB592: 0.67503118 | BC592: 2.12 | BD592: 0.025313669 | BE592: 0.0055029716 | BF592: 0.014307726 | BG592: 0.13280505 | BH592: 30–39 min | BI592: 23–27 | BJ592: 0.563 | BK592: 0.605 | BL592: 0.83162342 | BM592: Conserver | BN592: 0.73082652 | BO592: 2725.8 | BP592: 0.15555066 | BQ592: 2.12 | BR592: 0.14674591
A593: OG Anunoby | B593: NYK | C593: 27 | D593: 74 | E593: 45 | F593: 29 | G593: 36.6 | H593: 1332 | I593: 488 | J593: 1029 | K593: 47.6 | L593: 170 | M593: 459 | N593: 37.2 | O593: 185 | P593: 229 | Q593: 81 | R593: 96 | S593: 259 | T593: 355 | U593: 163 | V593: 104 | W593: 111 | X593: 67 | Y593: 170 | Z593: 2427 | AA593: 1 | AB593: 0 | AC593: 4.1 | AD593: 117.7 | AE593: 112.3 | AF593: 5.4 | AG593: 8.4 | AH593: 1.61 | AI593: 11.8 | AJ593: 3.7 | AK593: 9.8 | AL593: 6.7 | AM593: 7.3 | AN593: 55.9 | AO593: 59.1 | AP593: 19.5 | AQ593: 97.73 | AR593: 9.3 | AS593: 5511 | AT593: 18 | AU593: 2.2027027 | AV593: 4.7972973 | AW593: 1.2972973 | AX593: 3.5 | AY593: 1.5 | AZ593: 0.90540541 | BA593: 1.4054054 | BB593: 0.49180328 | BC593: 1.5673077 | BD593: 0.040983607 | BE593: 0.024737853 | BF593: 0.035445281 | BG593: 0.095628415 | BH593: 30–39 min | BI593: 23–27 | BJ593: 0.559 | BK593: 0.591 | BL593: 0.62100181 | BM593: Conserver | BN593: 0.55050302 | BO593: 2708.4 | BP593: 0.060183134 | BQ593: 1.5673077 | BR593: 0.1310737
A594: Jalen Green | B594: HOU | C594: 23 | D594: 82 | E594: 52 | F594: 30 | G594: 32.9 | H594: 1722 | I594: 607 | J594: 1435 | K594: 42.3 | L594: 238 | M594: 664 | N594: 35.4 | O594: 271 | P594: 336 | Q594: 81.3 | R594: 41 | S594: 328 | T594: 377 | U594: 279 | V594: 205 | W594: 74 | X594: 25 | Y594: 123 | Z594: 2690 | AA594: 4 | AB594: 0 | AC594: 2 | AD594: 113.8 | AE594: 111.1 | AF594: 2.8 | AG594: 15.9 | AH594: 1.39 | AI594: 13.7 | AJ594: 1.5 | AK594: 12 | AL594: 6.5 | AM594: 9.9 | AN594: 50.5 | AO594: 54.4 | AP594: 26.7 | AQ594: 99.75 | AR594: 11.1 | AS594: 5610 | AT594: 21 | AU594: 3.402439 | AV594: 4.597561 | AW594: 0.5 | AX594: 4 | AY594: 0.90243902 | AZ594: 0.30487805 | BA594: 2.5 | BB594: 0.63829787 | BC594: 1.3609756 | BD594: 0.027429758 | BE594: 0.00926681 | BF594: 0.015197568 | BG594: 0.12158055 | BH594: 30–39 min | BI594: 23–27 | BJ594: 0.505 | BK594: 0.544 | BL594: 0.86602293 | BM594: Conserver | BN594: 0.64225352 | BO594: 2697.8 | BP594: 0.1034176 | BQ594: 1.3609756 | BR594: 0.13974349
A595: Christian Braun | B595: DEN | C595: 24 | D595: 79 | E595: 48 | F595: 31 | G595: 33.9 | H595: 1217 | I595: 474 | J595: 822 | K595: 58 | L595: 87 | M595: 221 | N595: 39.7 | O595: 174 | P595: 213 | Q595: 82.7 | R595: 95 | S595: 308 | T595: 411 | U595: 205 | V595: 79 | W595: 87 | X595: 40 | Y595: 174 | Z595: 2299 | AA595: 6 | AB595: 0 | AC595: 6.1 | AD595: 122.7 | AE595: 114.5 | AF595: 8.2 | AG595: 9.6 | AH595: 2.53 | AI595: 17.1 | AJ595: 3.9 | AK595: 10.9 | AL595: 7.7 | AM595: 6.8 | AN595: 63.4 | AO595: 66.5 | AP595: 15.5 | AQ595: 101.04 | AR595: 9.6 | AS595: 5639 | AT595: 15.405063 | AU595: 2.5949367 | AV595: 5.2025316 | AW595: 1.2025316 | AX595: 3.8987342 | AY595: 1.1012658 | AZ595: 0.50632911 | BA595: 1 | BB595: 0.45442665 | BC595: 2.5949367 | BD595: 0.032485717 | BE595: 0.014935962 | BF595: 0.03547291 | BG595: 0.11500691 | BH595: 30–39 min | BI595: 23–27 | BJ595: 0.634 | BK595: 0.665 | BL595: 0.49607725 | BM595: Conserver | BN595: 0.47114077 | BO595: 2678.1 | BP595: 0.076546806 | BQ595: 2.5949367 | BR595: 0.15346701
A596: Bam Adebayo | B596: MIA | C596: 27 | D596: 78 | E596: 36 | F596: 42 | G596: 34.3 | H596: 1412 | I596: 538 | J596: 1115 | K596: 48.5 | L596: 78 | M596: 218 | N596: 35.7 | O596: 250 | P596: 328 | Q596: 76.5 | R596: 187 | S596: 562 | T596: 749 | U596: 335 | V596: 164 | W596: 101 | X596: 55 | Y596: 164 | Z596: 3104 | AA596: 38 | AB596: 1 | AC596: 0.3 | AD596: 110.9 | AE596: 110.8 | AF596: 0.1 | AG596: 20.4 | AH596: 2.09 | AI596: 19.2 | AJ596: 6.9 | AK596: 21.4 | AL596: 14.1 | AM596: 9.2 | AN596: 52.1 | AO596: 56.1 | AP596: 23.2 | AQ596: 97.02 | AR596: 13.7 | AS596: 5414 | AT596: 18.102564 | AU596: 4.2948718 | AV596: 9.6025641 | AW596: 2.3974359 | AX596: 7.2051282 | AY596: 1.2948718 | AZ596: 0.70512821 | BA596: 2.1025641 | BB596: 0.52777155 | BC596: 2.0426829 | BD596: 0.037751364 | BE596: 0.020557674 | BF596: 0.06989609 | BG596: 0.21006205 | BH596: 30–39 min | BI596: 23–27 | BJ596: 0.521 | BK596: 0.561 | BL596: 0.67290284 | BM596: Conserver | BN596: 0.55363979 | BO596: 2675.4 | BP596: 0.12521492 | BQ596: 2.0426829 | BR596: 0.27995814
... A633: Kevin Durant | B633: PHX | C633: 36 | D633: 62 | E633: 33 | F633: 29 | G633: 36.5 | H633: 1649 | I633: 589 | J633: 1122 | K633: 52.7 | L633: 161 | M633: 372 | N633: 43 | O633: 304 | P633: 360 | Q633: 83.9 | R633: 25 | S633: 353 | T633: 372 | U633: 260 | V633: 192 | W633: 50 | X633: 74 | Y633: 105 | Z633: 2678 | AA633: 5 | AB633: 0 | AC633: -0.6 | AD633: 116.5 | AE633: 117.4 | AF633: -1 | AG633: 18.8 | AH633: 1.38 | AI633: 15.2 | AJ633: 1.1 | AK633: 14.7 | AL633: 8.4 | AM633: 11 | AN633: 59.8 | AO633: 64.2 | AP633: 28.3 | AQ633: 99.49 | AR633: 14.2 | AS633: 4697 | AT633: 26.596774 | AU633: 4.1935484 | AV633: 6 | AW633: 0.40322581 | AX633: 5.6935484 | AY633: 0.80645161 | AZ633: 1.1935484 | BA633: 3.0967742 | BB633: 0.72867875 | BC633: 1.3541667 | BD633: 0.022094565 | BE633: 0.032699956 | BF633: 0.011047282 | BG633: 0.15598763 | BH633: 30–39 min | BI633: 33+ | BJ633: 0.598 | BK633: 0.642 | BL633: 0.67712734 | BM633: Conserver | BN633: 0.81342247 | BO633: 2263 | BP633: 0.11489174 | BQ633: 1.3541667 | BR633: 0.16438356
A634: Stephen Curry | B634: GSW | C634: 37 | D634: 70 | E634: 41 | F634: 29 | G634: 32.2 | H634: 1715 | I634: 567 | J634: 1260 | K634: 44.8 | L634: 308 | M634: 784 | N634: 39.7 | O634: Données | P634: 301 | Q634: 93.3 | R634: 42 | S634: 273 | T634: 308 | U634: 420 | V634: 203 | W634: 77 | X634: 28 | Y634: 98 | Z634: 2849 | AA634: 9 | AB634: 0 | AC634: 4.3 | AD634: 118.4 | AE634: 112.7 | AF634: 5.7 | AG634: 28.4 | AH634: 2.11 | AI634: 21.1 | AJ634: 1.7 | AK634: 11.8 | AL634: 6.6 | AM634: 10 | AN634: 57.2 | AO634: 61.8 | AP634: 28.6 | AQ634: 101.72 | AR634: 14.5 | AS634: 4785 | AT634: 24.5 | AU634: 6 | AV634: 4.4 | AW634: 0.6 | AX634: 3.9 | AY634: 1.1 | AZ634: 0.4 | BA634: 2.9 | BB634: 0.76086957 | BC634: 2.0689655 | BD634: 0.034161491 | BE634: 0.01242236 | BF634: 0.01863354 | BG634: 0.12111801 | BH634: 30–39 min | BI634: 33+ | BJ634: 0.572 | BK634: 0.618 | BL634: 0.76041038 | BM634: Conserver | BN634: 0.74929577 | BO634: 2254 | BP634: 0.1863354 | BQ634: 2.0689655 | BR634: 0.13664596
A635: Shaedon Sharpe | B635: POR | C635: 22 | D635: 72 | E635: 32 | F635: 40 | G635: 31.3 | H635: 1332 | I635: 497 | J635: 1102 | K635: 45.2 | L635: 144 | M635: 475 | N635: 31.1 | O635: 187 | P635: 245 | Q635: 78.5 | R635: 65 | S635: 259 | T635: 324 | U635: 202 | V635: 151 | W635: 65 | X635: 14 | Y635: 122 | Z635: 2102 | AA635: 3 | AB635: 0 | AC635: -1.9 | AD635: 111.4 | AE635: 114.4 | AF635: -3 | AG635: 13.8 | AH635: 1.32 | AI635: 12.7 | AJ635: 2.9 | AK635: 11.4 | AL635: 7 | AM635: 9.7 | AN635: 51.9 | AO635: 55.1 | AP635: 25 | AQ635: 99.88 | AR635: 10.2 | AS635: 4688 | AT635: 18.5 | AU635: 2.8055556 | AV635: 4.5 | AW635: 0.90277778 | AX635: 3.5972222 | AY635: 0.90277778 | AZ635: 0.19444444 | BA635: 2.0972222 | BB635: 0.59105431 | BC635: 1.3377483 | BD635: 0.028842741 | BE635: 0.0062122826 | BF635: 0.028842741 | BG635: 0.11492723 | BH635: 30–39 min | BI635: 18–22 | BJ635: 0.519 | BK635: 0.551 | BL635: 0.66505733 | BM635: Conserver | BN635: 0.56579477 | BO635: 2253.6 | BP635: 0.089634363 | BQ635: 1.3377483 | BR635: 0.14376997
A636: De'Aaron Fox | B636: SAS | C636: 27 | D636: 62 | E636: 27 | F636: 35 | G636: 36.1 | H636: 1457 | I636: 539 | J636: 1166 | K636: 46.3 | L636: 118 | M636: 378 | N636: 31 | O636: 260 | P636: 316 | Q636: 82.7 | R636: 56 | S636: 242 | T636: 298 | U636: 391 | V636: 174 | W636: 93 | X636: 25 | Y636: 161 | Z636: 2579 | AA636: 9 | AB636: 0 | AC636: -1.1 | AD636: 113.7 | AE636: 114.9 | AF636: -1.2 | AG636: 26.2 | AH636: 2.25 | AI636: 21 | AJ636: 2.3 | AK636: 10.6 | AL636: 6.4 | AM636: 9.3 | AN636: 51.4 | AO636: 56 | AP636: 27.4 | AQ636: 102.22 | AR636: 11.9 | AS636: 4768 | AT636: 23.5 | AU636: 6.3064516 | AV636: 4.8064516 | AW636: 0.90322581 | AX636: 3.9032258 | AY636: 1.5 | AZ636: 0.40322581 | BA636: 2.8064516 | BB636: 0.65096953 | BC636: 2.2471264 | BD636: 0.041551247 | BE636: 0.01116969 | BF636: 0.025020105 | BG636: 0.1081226 | BH636: 30–39 min | BI636: 23–27 | BJ636: 0.514 | BK636: 0.56 | BL636: 0.70368135 | BM636: Conserver | BN636: 0.71871227 | BO636: 2238.2 | BP636: 0.17469395 | BQ636: 2.2471264 | BR636: 0.1331427
A637: Jalen Williams | B637: OKC | C637: 24 | D637: 69 | E637: 55 | F637: 14 | G637: 32.4 | H637: 1490 | I637: 566 | J637: 1166 | K637: 48.4 | L637: 124 | M637: 338 | N637: 36.5 | O637: 235 | P637: 297 | Q637: 78.9 | R637: 62 | S637: 311 | T637: 366 | U637: 352 | V637: 152 | W637: 110 | X637: 48 | Y637: 159 | Z637: 2788 | AA637: 3 | AB637: 0 | AC637: 6.6 | AD637: 116.7 | AE637: 106.5 | AF637: 10.2 | AG637: 23.4 | AH637: 2.37 | AI637: 19.7 | AJ637: 2.6 | AK637: 13.1 | AL637: 7.9 | AM637: 8.3 | AN637: 53.7 | AO637: 57.3 | AP637: 27 | AQ637: 102.44 | AR637: 13.8 | AS637: 4760 | AT637: 21.594203 | AU637: 5.1014493 | AV637: 5.3043478 | AW637: 0.89855072 | AX637: 4.5072464 | AY637: 1.5942029 | AZ637: 0.69565217 | BA637: 2.2028986 | BB637: 0.66648774 | BC637: 2.3157895 | BD637: 0.049203793 | BE637: 0.021470746 | BF637: 0.027733047 | BG637: 0.13911254 | BH637: 30–39 min | BI637: 23–27 | BJ637: 0.537 | BK637: 0.573 | BL637: 0.70368135 | BM637: Conserver | BN637: 0.66042633 | BO637: 2235.6 | BP637: 0.15745214 | BQ637: 2.3157895 | BR637: 0.16371444
A638: Harrison Barnes | B638: SAS | C638: 33 | D638: 82 | E638: 34 | F638: 48 | G638: 27.2 | H638: 1009 | I638: 344 | J638: 681 | K638: 50.8 | L638: 156 | M638: 361 | N638: 43.3 | O638: 164 | P638: 197 | Q638: 80.9 | R638: 98 | S638: 213 | T638: 312 | U638: 139 | V638: 49 | W638: 41 | X638: 16 | Y638: 74 | Z638: 1697 | AA638: 1 | AB638: 0 | AC638: -0.3 | AD638: 114.5 | AE638: 115.6 | AF638: -1.2 | AG638: 8.5 | AH638: 2.72 | AI638: 14.2 | AJ638: 4.2 | AK638: 9.1 | AL638: 6.7 | AM638: 5.2 | AN638: 62.2 | AO638: 65.6 | AP638: 15.7 | AQ638: 100.08 | AR638: 9.2 | AS638: 4662 | AT638: 12.304878 | AU638: 1.695122 | AV638: 3.804878 | AW638: 1.195122 | AX638: 2.597561 | AY638: 0.5 | AZ638: 0.19512195 | BA638: 0.59756098 | BB638: 0.45238522 | BC638: 2.8367347 | BD638: 0.018382353 | BE638: 0.0071736011 | BF638: 0.043938307 | BG638: 0.095498565 | BH638: 20–29 min | BI638: 33+ | BJ638: 0.622 | BK638: 0.656 | BL638: 0.41098371 | BM638: Écarter | BN638: 0.37632625 | BO638: 2230.4 | BP638: 0.06232066 | BQ638: 2.8367347 | BR638: 0.13988522
A639: Donovan Mitchell | B639: CLE | C639: 28 | D639: 71 | E639: 55 | F639: 16 | G639: 31.4 | H639: 1704 | I639: 582 | J639: 1321 | K639: 44.3 | L639: 234 | M639: 632 | N639: 36.8 | O639: 298 | P639: 362 | Q639: 82.3 | R639: 57 | S639: 263 | T639: 320 | U639: 355 | V639: 149 | W639: 92 | X639: 14 | Y639: 142 | Z639: 2805 | AA639: 6 | AB639: 0 | AC639: 7.4 | AD639: 119.7 | AE639: 109.1 | AF639: 10.5 | AG639: 23.8 | AH639: 2.38 | AI639: 18 | AJ639: 2.5 | AK639: 11.2 | AL639: 6.9 | AM639: 7.6 | AN639: 53.1 | AO639: 57.5 | AP639: 29.8 | AQ639: 102.21 | AR639: 13.7 | AS639: 4762 | AT639: 24 | AU639: 5 | AV639: 4.5070423 | AW639: 0.8028169 | AX639: 3.7042254 | AY639: 1.2957746 | AZ639: 0.1971831 | BA639: 2.0985915 | BB639: 0.76433121 | BC639: 2.3825503 | BD639: 0.041266709 | BE639: 0.0062797165 | BF639: 0.025567417 | BG639: 0.11796896 | BH639: 30–39 min | BI639: 28–32 | BJ639: 0.531 | BK639: 0.575 | BL639: 0.7972239 | BM639: Conserver | BN639: 0.73400402 | BO639: 2229.4 | BP639: 0.15923567 | BQ639: 2.3825503 | BR639: 0.14353638
A640: Julius Randle | B640: MIN | C640: 30 | D640: 69 | E640: 44 | F640: 25 | G640: 32.3 | H640: 1290 | I640: 455 | J640: 938 | K640: 48.5 | L640: 110 | M640: 317 | N640: 34.4 | O640: 269 | P640: 338 | Q640: 80.6 | R640: 145 | S640: 345 | T640: 490 | U640: 324 | V640: 193 | W640: 48 | X640: 14 | Y640: 173 | Z640: 2353 | AA640: 14 | AB640: 0 | AC640: 2.4 | AD640: 115 | AE640: 111.6 | AF640: 3.4 | AG640: 22.8 | AH640: 1.65 | AI640: 20.1 | AJ640: 6.5 | AK640: 14.9 | AL640: 10.8 | AM640: 12.2 | AN640: 54.2 | AO640: 59.3 | AP640: 24.6 | AQ640: 98.45 | AR640: 12.4 | AS640: 4569 | AT640: 18.695652 | AU640: 4.6956522 | AV640: 7.1014493 | AW640: 2.1014493 | AX640: 5 | AY640: 0.69565217 | AZ640: 0.20289855 | BA640: 2.7971014 | BB640: 0.57881276 | BC640: 1.6787565 | BD640: 0.021537219 | BE640: 0.0062816889 | BF640: 0.065060349 | BG640: 0.15479876 | BH640: 30–39 min | BI640: 28–32 | BJ640: 0.542 | BK640: 0.593 | BL640: 0.56608328 | BM640: Conserver | BN640: 0.5717785 | BO640: 2228.7 | BP640: 0.14537623 | BQ640: 1.6787565 | BR640: 0.21985911
A641: Amen Thompson | B641: HOU | C641: 22 | D641: 69 | E641: 43 | F641: 26 | G641: 32.3 | H641: 973 | I641: 386 | J641: 697 | K641: 55.7 | L641: 28 | M641: 90 | N641: 27.5 | O641: 166 | P641: 248 | Q641: 68.4 | R641: 193 | S641: 373 | T641: 566 | U641: 262 | V641: 138 | W641: 97 | X641: 90 | Y641: 166 | Z641: 2463 | AA641: 21 | AB641: 3 | AC641: 3.9 | AD641: 114.2 | AE641: 107.9 | AF641: 6.3 | AG641: 16.7 | AH641: 1.92 | AI641: 21.9 | AJ641: 7.8 | AK641: 15.9 | AL641: 11.8 | AM641: 11.4 | AN641: 57.5 | AO641: 60.2 | AP641: 17.2 | AQ641: 100 | AR641: 12.9 | AS641: 4626 | AT641: 14.101449 | AU641: 3.7971014 | AV641: 8.2028986 | AW641: 2.7971014 | AX641: 5.4057971 | AY641: 1.4057971 | AZ641: 1.3043478 | BA641: 2 | BB641: 0.43657738 | BC641: 1.8985507 | BD641: 0.04352313 | BE641: 0.040382286 | BF641: 0.086597568 | BG641: 0.16736214 | BH641: 30–39 min | BI641: 18–22 | BJ641: 0.575 | BK641: 0.602 | BL641: 0.42063971 | BM641: Conserver | BN641: 0.43127169 | BO641: 2228.7 | BP641: 0.11755732 | BQ641: 1.8985507 | BR641: 0.25395971
A642: Desmond Bane | B642: MEM | C642: 26 | D642: 69 | E642: 38 | F642: 31 | G642: 32 | H642: 1325 | I642: 490 | J642: 1021 | K642: 48.4 | L642: 166 | M642: 421 | N642: 39.2 | O642: 179 | P642: 200 | Q642: 89.4 | R642: 62 | S642: 359 | T642: 421 | U642: 366 | V642: 166 | W642: 83 | X642: 28 | Y642: 166 | Z642: 2539 | AA642: 10 | AB642: 1 | AC642: 2.1 | AD642: 116.1 | AE642: 113.3 | AF642: 2.8 | AG642: 23.5 | AH642: 2.18 | AI642: 22.7 | AJ642: 2.6 | AK642: 15 | AL642: 8.8 | AM642: 10.4 | AN642: 56.5 | AO642: 60 | AP642: 22.7 | AQ642: 104.58 | AR642: 13.1 | AS642: 4809 | AT642: 19.202899 | AU642: 5.3043478 | AV642: 6.1014493 | AW642: 0.89855072 | AX642: 5.2028986 | AY642: 1.2028986 | AZ642: 0.4057971 | BA642: 2.4057971 | BB642: 0.60009058 | BC642: 2.2048193 | BD642: 0.03759058 | BE642: 0.012681159 | BF642: 0.02807971 | BG642: 0.16259058 | BH642: 30–39 min | BI642: 23–27 | BJ642: 0.565 | BK642: 0.6 | BL642: 0.61617381 | BM642: Conserver | BN642: 0.58729187 | BO642: 2208 | BP642: 0.16576087 | BQ642: 2.2048193 | BR642: 0.19067029
A643: Jaren Jackson Jr, | B643: MEM | C643: 25 | D643: 74 | E643: 42 | F643: 32 | G643: 29.8 | H643: 1643 | I643: 592 | J643: 1214 | K643: 48.8 | L643: 148 | M643: 392 | N643: 37.5 | O643: 311 | P643: 400 | Q643: 78.1 | R643: 89 | S643: 326 | T643: 414 | U643: 148 | V643: 155 | W643: 89 | X643: 111 | Y643: 259 | Z643: 2827 | AA643: 6 | AB643: 0 | AC643: 4.5 | AD643: 115.2 | AE643: 108.8 | AF643: 6.4 | AG643: 10.2 | AH643: 0.97 | AI643: 8.8 | AJ643: 3.8 | AK643: 13.4 | AL643: 8.7 | AM643: 9.1 | AN643: 54.8 | AO643: 59.1 | AP643: 27.4 | AQ643: 105.56 | AR643: 12.4 | AS643: 4863 | AT643: 22.202703 | AU643: 2 | AV643: 5.5945946 | AW643: 1.2027027 | AX643: 4.4054054 | AY643: 1.2027027 | AZ643: 1.5 | BA643: 2.0945946 | BB643: 0.74505714 | BC643: 0.95483871 | BD643: 0.040359151 | BE643: 0.05033557 | BF643: 0.040359151 | BG643: 0.1478324 | BH643: 20–29 min | BI643: 23–27 | BJ643: 0.548 | BK643: 0.591 | BL643: 0.73264937 | BM643: Écarter | BN643: 0.67903638 | BO643: 2205.2 | BP643: 0.067114094 | BQ643: 0.95483871 | BR643: 0.18773807
A644: Naz Reid | B644: MIN | C644: 25 | D644: 80 | E644: 47 | F644: 33 | G644: 27.5 | H644: 1136 | I644: 424 | J644: 920 | K644: 46.2 | L644: 176 | M644: 464 | N644: 37.9 | O644: 112 | P644: 144 | Q644: 77.6 | R644: 96 | S644: 392 | T644: 480 | U644: 184 | V644: 112 | W644: 56 | X644: 72 | Y644: 192 | Z644: 2264 | AA644: 10 | AB644: 0 | AC644: 4.3 | AD644: 116.2 | AE644: 108.8 | AF644: 7.4 | AG644: 12.3 | AH644: 1.68 | AI644: 14.2 | AJ644: 4.1 | AK644: 17.1 | AL644: 10.6 | AM644: 8.5 | AN644: 55.6 | AO644: 57.7 | AP644: 21 | AQ644: 99.34 | AR644: 11 | AS644: 4554 | AT644: 14.2 | AU644: 2.3 | AV644: 6 | AW644: 1.2 | AX644: 4.9 | AY644: 0.7 | AZ644: 0.9 | BA644: 1.4 | BB644: 0.51636364 | BC644: 1.6428571 | BD644: 0.025454545 | BE644: 0.032727273 | BF644: 0.043636364 | BG644: 0.17818182 | BH644: 20–29 min | BI644: 23–27 | BJ644: 0.556 | BK644: 0.577 | BL644: 0.55522028 | BM644: Écarter | BN644: 0.43428571 | BO644: 2200 | BP644: 0.083636364 | BQ644: 1.6428571 | BR644: 0.21818182
A645: Myles Turner | B645: IND | C645: 29 | D645: 72 | E645: 44 | F645: 28 | G645: 30.2 | H645: 1123 | I645: 389 | J645: 814 | K645: 48.1 | L645: 158 | M645: 396 | N645: 39.6 | O645: 187 | P645: 238 | Q645: 77.3 | R645: 94 | S645: 382 | T645: 468 | U645: 108 | V645: 122 | W645: 58 | X645: 144 | Y645: 180 | Z645: 2326 | AA645: 13 | AB645: 0 | AC645: 2.8 | AD645: 116.1 | AE645: 111.5 | AF645: 4.7 | AG645: 7.2 | AH645: 0.9 | AI645: 9.7 | AJ645: 4.3 | AK645: 16.9 | AL645: 10.9 | AM645: 10.7 | AN645: 57.7 | AO645: 61.2 | AP645: 20.7 | AQ645: 100.19 | AR645: 10.3 | AS645: 4533 | AT645: 15.597222 | AU645: 1.5 | AV645: 6.5 | AW645: 1.3055556 | AX645: 5.3055556 | AY645: 0.80555556 | AZ645: 2 | BA645: 1.6944444 | BB645: 0.51646431 | BC645: 0.8852459 | BD645: 0.026674025 | BE645: 0.066225166 | BF645: 0.043230316 | BG645: 0.17568065 | BH645: 30–39 min | BI645: 28–32 | BJ645: 0.577 | BK645: 0.612 | BL645: 0.49124925 | BM645: Conserver | BN645: 0.47701766 | BO645: 2174.4 | BP645: 0.049668874 | BQ645: 0.8852459 | BR645: 0.21523179
A646: Tyus Jones | B646: PHX | C646: 29 | D646: 81 | E646: 36 | F646: 45 | G646: 26.8 | H646: 826 | I646: 308 | J646: 680 | K646: 44.8 | L646: 162 | M646: 405 | N646: 41.4 | O646: 49 | P646: 57 | Q646: 89.5 | R646: 41 | S646: 154 | T646: 194 | U646: 429 | V646: 89 | W646: 73 | X646: 8 | Y646: 65 | Z646: 1847 | AA646: 6 | AB646: 0 | AC646: -1.1 | AD646: 113.6 | AE646: 116.1 | AF646: -2.5 | AG646: 27.6 | AH646: 4.71 | AI646: 34.9 | AJ646: 1.9 | AK646: 6.9 | AL646: 4.5 | AM646: 7.4 | AN646: 57 | AO646: 58.5 | AP646: 16 | AQ646: 99.19 | AR646: 9.9 | AS646: 4500 | AT646: 10.197531 | AU646: 5.2962963 | AV646: 2.3950617 | AW646: 0.50617284 | AX646: 1.9012346 | AY646: 0.90123457 | AZ646: 0.098765432 | BA646: 1.0987654 | BB646: 0.38050488 | BC646: 4.8202247 | BD646: 0.033628156 | BE646: 0.0036852773 | BF646: 0.018887046 | BG646: 0.070941588 | BH646: 20–29 min | BI646: 28–32 | BJ646: 0.57 | BK646: 0.585 | BL646: 0.41038021 | BM646: Écarter | BN646: 0.3118762 | BO646: 2170.8 | BP646: 0.197623 | BQ646: 4.8202247 | BR646: 0.089367975
... A854: Kyle Anderson | B854: MIA | C854: 31 | D854: 61 | E854: 30 | F854: 31 | G854: 16.4 | H854: 360 | I854: 140 | J854: 305 | K854: 46.9 | L854: 24 | M854: 67 | N854: 35.7 | O854: 49 | P854: 67 | Q854: 73.8 | R854: 55 | S854: 153 | T854: 207 | U854: 146 | V854: 37 | W854: 43 | X854: 31 | Y854: 79 | Z854: 1007 | AA854: 2 | AB854: 0 | AC854: -0.4 | AD854: 106.1 | AE854: 107.6 | AF854: -1.5 | AG854: 21.1 | AH854: 3.92 | AI854: 28.3 | AJ854: 4.9 | AK854: 14.8 | AL854: 9.7 | AM854: 7.2 | AN854: 51 | AO854: 53.8 | AP854: 15.2 | AQ854: 100.06 | AR854: 10.8 | AS854: 2093 | AT854: 5.9016393 | AU854: 2.3934426 | AV854: 3.3934426 | AW854: 0.90163934 | AX854: 2.5081967 | AY854: 0.70491803 | AZ854: 0.50819672 | BA854: 0.60655738 | BB854: 0.35985606 | BC854: 3.9459459 | BD854: 0.042982807 | BE854: 0.030987605 | BF854: 0.054978009 | BG854: 0.15293882 | BH854: 10–19 min | BI854: 28–32 | BJ854: 0.51 | BK854: 0.538 | BL854: 0.18406759 | BM854: Écarter | BN854: 0.18049279 | BO854: 1000.4 | BP854: 0.14594162 | BQ854: 3.9459459 | BR854: 0.20691723
A857: Ajout Colonne Indice de performance défensive synthétique (Def Impact Score) avec tri sur Tot_Min > 1000
A859: Player | B859: Team | C859: Age | D859: GP | E859: W | F859: L | G859: Min | H859: PTS | I859: FGM | J859: FGA | K859: FG% | L859: 15:00 | M859: 3PA | N859: 3P% | O859: FTM | P859: FTA | Q859: FT% | R859: OREB | S859: DREB | T859: REB | U859: AST | V859: TOV | W859: STL | X859: BLK | Y859: PF | Z859: FP | AA859: DD2 | AB859: TD3 | AC859: +/- | AD859: OFFRTG | AE859: DEFRTG | AF859: NETRTG | AG859: AST% | AH859: AST/TO | AI859: AST RATIO | AJ859: OREB% | AK859: DREB% | AL859: REB% | AM859: TO RATIO | AN859: EFG% | AO859: TS% | AP859: USG% | AQ859: PACE | AR859: PIE | AS859: POSS | AT859: PTS_pg | AU859: AST_pg | AV859: REB_pg | AW859: OREB_pg | AX859: DREB_pg | AY859: STL_pg | AZ859: BLK_pg | BA859: TOV_pg | BB859: PTS_pg/Min | BC859: AST_pg/TOV_pg | BD859: STL_pg/Min | BE859: BLK_pg/Min | BF859: OREB_pg/Min | BG859: DREB_pg/Min | BH859: Classe_Min | BI859: Classe_Age | BJ859: EFG%_corr | BK859: TS%_corr | BL859: FGA_norm | BM859: Filtre joueur | BN859: PTG_pg_Norm | BO859: Min_tot | BP859: AST/Min | BQ859: AST/TOV | BR859: REB_pg/Min | BS859: Def Impact Score
A860: Shai Gilgeous-Alexander | B860: OKC | C860: 26 | D860: 76 | E860: 63 | F860: 13 | G860: 34.2 | H860: 2485 | I860: 859 | J860: 1657 | K860: 51.9 | L860: 160 | M860: 433 | N860: 37.5 | O860: 600 | P860: 669 | Q860: 89.8 | R860: 68 | S860: 312 | T860: 380 | U860: 486 | V860: 182 | W860: 129 | X860: 76 | Y860: 167 | Z860: 4112 | AA860: 6 | AB860: 0 | AC860: 12.1 | AD860: 122.4 | AE860: 105.7 | AF860: 16.7 | AG860: 29.9 | AH860: 2.66 | AI860: 18.7 | AJ860: 2.5 | AK860: 11.2 | AL860: 6.9 | AM860: 7 | AN860: 56.9 | AO860: 63.7 | AP860: 33.6 | AQ860: 101.91 | AR860: 19.9 | AS860: 5514 | AT860: 32.697368 | AU860: 6.3947368 | AV860: 5 | AW860: 0.89473684 | AX860: 4.1052632 | AY860: 1.6973684 | AZ860: 1 | BA860: 2.3947368 | BB860: 0.9560634 | BC860: 2.6703297 | BD860: 0.049630656 | BE860: 0.029239766 | BF860: 0.026161896 | BG860: 0.12003693 | BH860: 30–39 min | BI860: 23–27 | BJ860: 0.569 | BK860: 0.637 | BL860: 1 | BM860: Conserver | BN860: 1 | BO860: 2599.2 | BP860: 0.18698061 | BQ860: 2.6703297 | BR860: 0.14619883 | BS860: 0.075023084
A861: Anthony Edwards | B861: MIN | C861: 23 | D861: 79 | E861: 48 | F861: 31 | G861: 36.3 | H861: 2180 | I861: 719 | J861: 1612 | K861: 44.7 | L861: 324 | M861: 814 | N861: 39.5 | O861: 419 | P861: 498 | Q861: 83.7 | R861: 63 | S861: 387 | T861: 450 | U861: 356 | V861: 253 | W861: 95 | X861: 47 | Y861: 150 | Z861: 3429 | AA861: 7 | AB861: 0 | AC861: 3.7 | AD861: 116.2 | AE861: 111.4 | AF861: 4.8 | AG861: 20.9 | AH861: 1.44 | AI861: 14.8 | AJ861: 2.1 | AK861: 13.1 | AL861: 7.7 | AM861: 10.3 | AN861: 54.7 | AO861: 59.5 | AP861: 30.7 | AQ861: 98.27 | AR861: 14 | AS861: 5883 | AT861: 27.594937 | AU861: 4.5063291 | AV861: 5.6962025 | AW861: 0.79746835 | AX861: 4.8987342 | AY861: 1.2025316 | AZ861: 0.59493671 | BA861: 3.2025316 | BB861: 0.76019109 | BC861: 1.4071146 | BD861: 0.033127594 | BE861: 0.016389441 | BF861: 0.021968825 | BG861: 0.13495135 | BH861: 30–39 min | BI861: 23–27 | BJ861: 0.547 | BK861: 0.595 | BL861: 0.97284249 | BM861: Conserver | BN861: 0.84394977 | BO861: 2867.7 | BP861: 0.1241413 | BQ861: 1.4071146 | BR861: 0.15692018 | BS861: 0.068812405
A862: Nikola Jokić | B862: DEN | C862: 30 | D862: 70 | E862: 46 | F862: 24 | G862: 36.7 | H862: 2072 | I862: 784 | J862: 1365 | K862: 57.6 | L862: 140 | M862: 329 | N862: 41.7 | O862: 364 | P862: 448 | Q862: 80 | R862: 203 | S862: 693 | T862: 889 | U862: 714 | V862: 231 | W862: 126 | X862: 42 | Y862: 161 | Z862: 4501 | AA862: 59 | AB862: 34 | AC862: 8.5 | AD862: 125.6 | AE862: 115.1 | AF862: 10.5 | AG862: 39.8 | AH862: 3.11 | AI862: 28.7 | AJ862: 8.3 | AK862: 25.2 | AL862: 17.3 | AM862: 9.2 | AN862: 62.7 | AO862: 66.3 | AP862: 28.5 | AQ862: 101.99 | AR862: 20.6 | AS862: 5471 | AT862: 29.6 | AU862: 10.2 | AV862: 12.7 | AW862: 2.9 | AX862: 9.9 | AY862: 1.8 | AZ862: 0.6 | BA862: 3.3 | BB862: 0.80653951 | BC862: 3.0909091 | BD862: 0.049046322 | BE862: 0.016348774 | BF862: 0.079019074 | BG862: 0.26975477 | BH862: 30–39 min | BI862: 28–32 | BJ862: 0.627 | BK862: 0.663 | BL862: 0.82377791 | BM862: Conserver | BN862: 0.90527163 | BO862: 2569 | BP862: 0.27792916 | BQ862: 3.0909091 | BR862: 0.34604905 | BS862: 0.13714805
A863: Giannis Antetokounmpo | B863: MIL | C863: 30 | D863: 67 | E863: 40 | F863: 27 | G863: 34.2 | H863: 2037 | I863: 791 | J863: 1320 | K863: 60.1 | L863: 13 | M863: 60 | N863: 22.2 | O863: 436 | P863: 710 | Q863: 61.7 | R863: 147 | S863: 650 | T863: 797 | U863: 436 | V863: 208 | W863: 60 | X863: 80 | Y863: 154 | Z863: 3846 | AA863: 55 | AB863: 11 | AC863: 5 | AD863: 118.9 | AE863: 111.7 | AF863: 7.2 | AG863: 33.9 | AH863: 2.1 | AI863: 19.2 | AJ863: 6.7 | AK863: 26.6 | AL863: 17.2 | AM863: 9.1 | AN863: 60.7 | AO863: 62.5 | AP863: 34.6 | AQ863: 100.18 | AR863: 21 | AS863: 4772 | AT863: 30.402985 | AU863: 6.5074627 | AV863: 11.895522 | AW863: 2.1940299 | AX863: 9.7014925 | AY863: 0.89552239 | AZ863: 1.1940299 | BA863: 3.1044776 | BB863: 0.88897617 | BC863: 2.0961538 | BD863: 0.026184865 | BE863: 0.034913154 | BF863: 0.06415292 | BG863: 0.28366937 | BH863: 30–39 min | BI863: 28–32 | BJ863: 0.607 | BK863: 0.625 | BL863: 0.7966204 | BM863: Conserver | BN863: 0.92982972 | BO863: 2291.4 | BP863: 0.19027669 | BQ863: 2.0961538 | BR863: 0.34782229 | BS863: 0.13630677
A864: Jayson Tatum | B864: BOS | C864: 27 | D864: 72 | E864: 53 | F864: 19 | G864: 36.4 | H864: 1930 | I864: 662 | J864: 1462 | K864: 45.2 | L864: 252 | M864: 727 | N864: 34.3 | O864: 360 | P864: 439 | Q864: 81.4 | R864: 50 | S864: 576 | T864: 626 | U864: 432 | V864: 209 | W864: 79 | X864: 36 | Y864: 158 | Z864: 3456 | AA864: 31 | AB864: 2 | AC864: 7.4 | AD864: 119.6 | AE864: 109.8 | AF864: 9.8 | AG864: 26.6 | AH864: 2.6 | AI864: 18.9 | AJ864: 1.7 | AK864: 20.6 | AL864: 11.2 | AM864: 9.2 | AN864: 53.7 | AO864: 58.2 | AP864: 30.1 | AQ864: 98.14 | AR864: 15.8 | AS864: 5368 | AT864: 26.805556 | AU864: 6 | AV864: 8.6944444 | AW864: 0.69444444 | AX864: 8 | AY864: 1.0972222 | AZ864: 0.5 | BA864: 2.9027778 | BB864: 0.73641636 | BC864: 2.0669856 | BD864: 0.030143468 | BE864: 0.013736264 | BF864: 0.019078144 | BG864: 0.21978022 | BH864: 30–39 min | BI864: 23–27 | BJ864: 0.537 | BK864: 0.582 | BL864: 0.88231744 | BM864: Conserver | BN864: 0.81980774 | BO864: 2620.8 | BP864: 0.16483516 | BQ864: 2.0669856 | BR864: 0.23885836 | BS864: 0.094246032
A865: Devin Booker | B865: PHX | C865: 28 | D865: 75 | E865: 35 | F865: 40 | G865: 37.3 | H865: 1920 | I865: 653 | J865: 1418 | K865: 46.1 | L865: 180 | M865: 548 | N865: 33.2 | O865: 435 | P865: 480 | Q865: 89.4 | R865: 75 | S865: 233 | T865: 308 | U865: 533 | V865: 218 | W865: 68 | X865: 15 | Y865: 195 | Z865: 3113 | AA865: 16 | AB865: 0 | AC865: -2.4 | AD865: 115.3 | AE865: 118.5 | AF865: -3.2 | AG865: 30.1 | AH865: 2.4 | AI865: 22.4 | AJ865: 2.8 | AK865: 8 | AL865: 5.5 | AM865: 9.3 | AN865: 52.5 | AO865: 58.9 | AP865: 28.5 | AQ865: 98.72 | AR865: 12.2 | AS865: 5752 | AT865: 25.6 | AU865: 7.1066667 | AV865: 4.1066667 | AW865: 1 | AX865: 3.1066667 | AY865: 0.90666667 | AZ865: 0.2 | BA865: 2.9066667 | BB865: 0.68632708 | BC865: 2.4449541 | BD865: 0.024307417 | BE865: 0.0053619303 | BF865: 0.026809651 | BG865: 0.083288651 | BH865: 30–39 min | BI865: 28–32 | BJ865: 0.525 | BK865: 0.589 | BL865: 0.85576343 | BM865: Conserver | BN865: 0.78293763 | BO865: 2797.5 | BP865: 0.19052726 | BQ865: 2.4449541 | BR865: 0.1100983 | BS865: 0.046589217
A866: Tyler Herro | B866: MIA | C866: 25 | D866: 77 | E866: 37 | F866: 40 | G866: 35.4 | H866: 1840 | I866: 655 | J866: 1378 | K866: 47.2 | L866: 254 | M866: 670 | N866: 37.5 | O866: 285 | P866: 323 | Q866: 87.8 | R866: 39 | S866: 362 | T866: 400 | U866: 424 | V866: 200 | W866: 69 | X866: 15 | Y866: 85 | Z866: 3018 | AA866: 9 | AB866: 0 | AC866: 1.3 | AD866: 113.9 | AE866: 112.6 | AF866: 1.3 | AG866: 25.4 | AH866: 2.14 | AI866: 20 | AJ866: 1.3 | AK866: 13.2 | AL866: 7.3 | AM866: 9.3 | AN866: 56.3 | AO866: 60.5 | AP866: 27.1 | AQ866: 97.78 | AR866: 13.9 | AS866: 5564 | AT866: 23.896104 | AU866: 5.5064935 | AV866: 5.1948052 | AW866: 0.50649351 | AX866: 4.7012987 | AY866: 0.8961039 | AZ866: 0.19480519 | BA866: 2.5974026 | BB866: 0.67503118 | BC866: 2.12 | BD866: 0.025313669 | BE866: 0.0055029716 | BF866: 0.014307726 | BG866: 0.13280505 | BH866: 30–39 min | BI866: 23–27 | BJ866: 0.563 | BK866: 0.605 | BL866: 0.83162342 | BM866: Conserver | BN866: 0.73082652 | BO866: 2725.8 | BP866: 0.15555066 | BQ866: 2.12 | BR866: 0.14674591 | BS866: 0.059187517
A867: Trae Young | B867: ATL | C867: 26 | D867: 76 | E867: 36 | F867: 40 | G867: 36 | H867: 1839 | I867: 562 | J867: 1376 | K867: 41.1 | L867: 220 | M867: 638 | N867: 34 | O867: 494 | P867: 562 | Q867: 87.5 | R867: 38 | S867: 198 | T867: 236 | U867: 882 | V867: 357 | W867: 91 | X867: 15 | Y867: 144 | Z867: 3397 | AA867: 51 | AB867: 0 | AC867: 0.4 | AD867: 115.2 | AE867: 114.6 | AF867: 0.6 | AG867: 45.2 | AH867: 2.48 | AI867: 30.9 | AJ867: 1.2 | AK867: 7.2 | AL867: 4.2 | AM867: 12.5 | AN867: 49.1 | AO867: 56.7 | AP867: 28.5 | AQ867: 105.51 | AR867: 12.9 | AS867: 6020 | AT867: 24.197368 | AU867: 11.605263 | AV867: 3.1052632 | AW867: 0.5 | AX867: 2.6052632 | AY867: 1.1973684 | AZ867: 0.19736842 | BA867: 4.6973684 | BB867: 0.67214912 | BC867: 2.4705882 | BD867: 0.033260234 | BE867: 0.0054824561 | BF867: 0.013888889 | BG867: 0.072368421 | BH867: 30–39 min | BI867: 23–27 | BJ867: 0.491 | BK867: 0.567 | BL867: 0.83041642 | BM867: Conserver | BN867: 0.74004024 | BO867: 2736 | BP867: 0.32236842 | BQ867: 2.4705882 | BR867: 0.08625731 | BS867: 0.041666667
A868: Cade Cunningham | B868: DET | C868: 23 | D868: 70 | E868: 38 | F868: 32 | G868: 35 | H868: 1827 | I868: 686 | J868: 1456 | K868: 46.9 | L868: 147 | M868: 420 | N868: 35.6 | O868: 315 | P868: 371 | Q868: 84.6 | R868: 56 | S868: 371 | T868: 427 | U868: 637 | V868: 308 | W868: 70 | X868: 56 | Y868: 196 | Z868: 3360 | AA868: 31 | AB868: 9 | AC868: 2.5 | AD868: 115 | AE868: 112.2 | AF868: 2.8 | AG868: 40.9 | AH868: 2.06 | AI868: 25 | AJ868: 2.3 | AK868: 14.7 | AL868: 8.6 | AM868: 12.1 | AN868: 52.1 | AO868: 56.5 | AP868: 32.3 | AQ868: 101.57 | AR868: 15.2 | AS868: 5201 | AT868: 26.1 | AU868: 9.1 | AV868: 6.1 | AW868: 0.8 | AX868: 5.3 | AY868: 1 | AZ868: 0.8 | BA868: 4.4 | BB868: 0.74571429 | BC868: 2.0681818 | BD868: 0.028571429 | BE868: 0.022857143 | BF868: 0.022857143 | BG868: 0.15142857 | BH868: 30–39 min | BI868: 23–27 | BJ868: 0.521 | BK868: 0.565 | BL868: 0.87869644 | BM868: Conserver | BN868: 0.79822938 | BO868: 2450 | BP868: 0.26 | BQ868: 2.0681818 | BR868: 0.17428571 | BS868: 0.075238095
A869: James Harden | B869: LAC | C869: 35 | D869: 79 | E869: 50 | F869: 29 | G869: 35.3 | H869: 1801 | I869: 529 | J869: 1296 | K869: 41 | L869: 237 | M869: 672 | N869: 35.2 | O869: 506 | P869: 577 | Q869: 87.4 | R869: 55 | S869: 403 | T869: 458 | U869: 687 | V869: 340 | W869: 119 | X869: 55 | Y869: 166 | Z869: 3555 | AA869: 38 | AB869: 3 | AC869: 4.4 | AD869: 115.4 | AE869: 109.2 | AF869: 6.2 | AG869: 36.5 | AH869: 2.01 | AI869: 26.9 | AJ869: 2 | AK869: 14.3 | AL869: 8.3 | AM869: 13.4 | AN869: 50.1 | AO869: 58.2 | AP869: 28.6 | AQ869: 98.82 | AR869: 14.5 | AS869: 5737 | AT869: 22.797468 | AU869: 8.6962025 | AV869: 5.7974684 | AW869: 0.69620253 | AX869: 5.1012658 | AY869: 1.5063291 | AZ869: 0.69620253 | BA869: 4.3037975 | BB869: 0.64582063 | BC869: 2.0205882 | BD869: 0.042672213 | BE869: 0.019722451 | BF869: 0.019722451 | BG869: 0.14451178 | BH869: 30–39 min | BI869: 33+ | BJ869: 0.501 | BK869: 0.582 | BL869: 0.78213639 | BM869: Conserver | BN869: 0.6972264 | BO869: 2788.7 | BP869: 0.24635135 | BQ869: 2.0205882 | BR869: 0.16423423 | BS869: 0.075542965
A870: Karl-Anthony Towns | B870: NYK | C870: 29 | D870: 72 | E870: 46 | F870: 26 | G870: 35 | H870: 1757 | I870: 641 | J870: 1217 | K870: 52.6 | L870: 144 | M870: 338 | N870: 42 | O870: 338 | P870: 410 | Q870: 82.9 | R870: 209 | S870: 706 | T870: 922 | U870: 223 | V870: 194 | W870: 72 | X870: 50 | Y870: 252 | Z870: 3370 | AA870: 58 | AB870: 1 | AC870: 5.3 | AD870: 119.4 | AE870: 112.7 | AF870: 6.8 | AG870: 13 | AH870: 1.16 | AI870: 12.4 | AJ870: 8.7 | AK870: 28.4 | AL870: 18.7 | AM870: 10.7 | AN870: 58.4 | AO870: 63 | AP870: 26.5 | AQ870: 99.25 | AR870: 16.1 | AS870: 5215 | AT870: 24.402778 | AU870: 3.0972222 | AV870: 12.805556 | AW870: 2.9027778 | AX870: 9.8055556 | AY870: 1 | AZ870: 0.69444444 | BA870: 2.6944444 | BB870: 0.69722222 | BC870: 1.1494845 | BD870: 0.028571429 | BE870: 0.01984127 | BF870: 0.082936508 | BG870: 0.28015873 | BH870: 30–39 min | BI870: 28–32 | BJ870: 0.584 | BK870: 0.63 | BL870: 0.73445987 | BM870: Conserver | BN870: 0.74632238 | BO870: 2520 | BP870: 0.088492063 | BQ870: 1.1494845 | BR870: 0.36587302 | BS870: 0.13809524
A871: Zach LaVine | B871: SAC | C871: 30 | D871: 74 | E871: 32 | F871: 42 | G871: 35.2 | H871: 1724 | I871: 622 | J871: 1221 | K871: 51.1 | L871: 237 | M871: 533 | N871: 44.6 | O871: 237 | P871: 289 | Q871: 82.5 | R871: 22 | S871: 296 | T871: 318 | U871: 311 | V871: 207 | W871: 59 | X871: 15 | Y871: 118 | Z871: 2568 | AA871: 6 | AB871: 0 | AC871: -0.9 | AD871: 115.4 | AE871: 116.8 | AF871: -1.4 | AG871: 17.8 | AH871: 1.49 | AI871: 16.7 | AJ871: 0.9 | AK871: 10.7 | AL871: 5.9 | AM871: 11.2 | AN871: 60.9 | AO871: 63.9 | AP871: 25.1 | AQ871: 101.28 | AR871: 11.5 | AS871: 5493 | AT871: 23.297297 | AU871: 4.2027027 | AV871: 4.2972973 | AW871: 0.2972973 | AX871: 4 | AY871: 0.7972973 | AZ871: 0.2027027 | BA871: 2.7972973 | BB871: 0.66185504 | BC871: 1.5024155 | BD871: 0.022650491 | BE871: 0.0057585995 | BF871: 0.0084459459 | BG871: 0.11363636 | BH871: 30–39 min | BI871: 28–32 | BJ871: 0.609 | BK871: 0.639 | BL871: 0.73687387 | BM871: Conserver | BN871: 0.71251292 | BO871: 2604.8 | BP871: 0.11939496 | BQ871: 1.5024155 | BR871: 0.12208231 | BS871: 0.0501638
A872: Jalen Green | B872: HOU | C872: 23 | D872: 82 | E872: 52 | F872: 30 | G872: 32.9 | H872: 1722 | I872: 607 | J872: 1435 | K872: 42.3 | L872: 238 | M872: 664 | N872: 35.4 | O872: 271 | P872: 336 | Q872: 81.3 | R872: 41 | S872: 328 | T872: 377 | U872: 279 | V872: 205 | W872: 74 | X872: 25 | Y872: 123 | Z872: 2690 | AA872: 4 | AB872: 0 | AC872: 2 | AD872: 113.8 | AE872: 111.1 | AF872: 2.8 | AG872: 15.9 | AH872: 1.39 | AI872: 13.7 | AJ872: 1.5 | AK872: 12 | AL872: 6.5 | AM872: 9.9 | AN872: 50.5 | AO872: 54.4 | AP872: 26.7 | AQ872: 99.75 | AR872: 11.1 | AS872: 5610 | AT872: 21 | AU872: 3.402439 | AV872: 4.597561 | AW872: 0.5 | AX872: 4 | AY872: 0.90243902 | AZ872: 0.30487805 | BA872: 2.5 | BB872: 0.63829787 | BC872: 1.3609756 | BD872: 0.027429758 | BE872: 0.00926681 | BF872: 0.015197568 | BG872: 0.12158055 | BH872: 30–39 min | BI872: 23–27 | BJ872: 0.505 | BK872: 0.544 | BL872: 0.86602293 | BM872: Conserver | BN872: 0.64225352 | BO872: 2697.8 | BP872: 0.1034176 | BQ872: 1.3609756 | BR872: 0.13974349 | BS872: 0.058813354
A873: Stephen Curry | B873: GSW | C873: 37 | D873: 70 | E873: 41 | F873: 29 | G873: 32.2 | H873: 1715 | I873: 567 | J873: 1260 | K873: 44.8 | L873: 308 | M873: 784 | N873: 39.7 | O873: Données | P873: 301 | Q873: 93.3 | R873: 42 | S873: 273 | T873: 308 | U873: 420 | V873: 203 | W873: 77 | X873: 28 | Y873: 98 | Z873: 2849 | AA873: 9 | AB873: 0 | AC873: 4.3 | AD873: 118.4 | AE873: 112.7 | AF873: 5.7 | AG873: 28.4 | AH873: 2.11 | AI873: 21.1 | AJ873: 1.7 | AK873: 11.8 | AL873: 6.6 | AM873: 10 | AN873: 57.2 | AO873: 61.8 | AP873: 28.6 | AQ873: 101.72 | AR873: 14.5 | AS873: 4785 | AT873: 24.5 | AU873: 6 | AV873: 4.4 | AW873: 0.6 | AX873: 3.9 | AY873: 1.1 | AZ873: 0.4 | BA873: 2.9 | BB873: 0.76086957 | BC873: 2.0689655 | BD873: 0.034161491 | BE873: 0.01242236 | BF873: 0.01863354 | BG873: 0.12111801 | BH873: 30–39 min | BI873: 33+ | BJ873: 0.572 | BK873: 0.618 | BL873: 0.76041038 | BM873: Conserver | BN873: 0.74929577 | BO873: 2254 | BP873: 0.1863354 | BQ873: 2.0689655 | BR873: 0.13664596 | BS873: 0.061076605
A874: DeMar DeRozan | B874: SAC | C874: 35 | D874: 77 | E874: 38 | F874: 39 | G874: 35.9 | H874: 1709 | I874: 624 | J874: 1309 | K874: 47.7 | L874: 85 | M874: 254 | N874: 32.8 | O874: 377 | P874: 439 | Q874: 85.7 | R874: 46 | S874: 246 | T874: 300 | U874: 339 | V874: 108 | W874: 62 | X874: 31 | Y874: 146 | Z874: 2757 | AA874: 3 | AB874: 0 | AC874: 1.4 | AD874: 116.8 | AE874: 115.3 | AF874: 1.5 | AG874: 18.2 | AH874: 3.26 | AI874: 17.7 | AJ874: 1.8 | AK874: 9 | AL874: 5.4 | AM874: 5.4 | AN874: 50.9 | AO874: 56.9 | AP874: 24.4 | AQ874: 99.35 | AR874: 11.2 | AS874: 5740 | AT874: 22.194805 | AU874: 4.4025974 | AV874: 3.8961039 | AW874: 0.5974026 | AX874: 3.1948052 | AY874: 0.80519481 | AZ874: 0.4025974 | BA874: 1.4025974 | BB874: 0.6182397 | BC874: 3.1388889 | BD874: 0.022428825 | BE874: 0.011214412 | BF874: 0.016640741 | BG874: 0.088991788 | BH874: 30–39 min | BI874: 33+ | BJ874: 0.509 | BK874: 0.569 | BL874: 0.78998189 | BM874: Conserver | BN874: 0.67879485 | BO874: 2764.3 | BP874: 0.12263503 | BQ874: 3.1388889 | BR874: 0.10852657 | BS874: 0.047389936
A875: LeBron James | B875: LAL | C875: 40 | D875: 70 | E875: 44 | F875: 26 | G875: 34.9 | H875: 1708 | I875: 651 | J875: 1267 | K875: 51.3 | L875: 147 | M875: 399 | N875: 37.6 | O875: 259 | P875: 329 | Q875: 78.2 | R875: 70 | S875: 476 | T875: 546 | U875: 574 | V875: 259 | W875: 70 | X875: 42 | Y875: 98 | Z875: 3297 | AA875: 32 | AB875: 10 | AC875: -0.8 | AD875: 112.7 | AE875: 114 | AF875: -1.3 | AG875: 39.5 | AH875: 2.21 | AI875: 25.6 | AJ875: 3.1 | AK875: 18.7 | AL875: 11.2 | AM875: 11.6 | AN875: 57.1 | AO875: 60.4 | AP875: 29.1 | AQ875: 100.62 | AR875: 16.9 | AS875: 5129 | AT875: 24.4 | AU875: 8.2 | AV875: 7.8 | AW875: 1 | AX875: 6.8 | AY875: 1 | AZ875: 0.6 | BA875: 3.7 | BB875: 0.6991404 | BC875: 2.2162162 | BD875: 0.028653295 | BE875: 0.017191977 | BF875: 0.028653295 | BG875: 0.19484241 | BH875: 30–39 min | BI875: 33+ | BJ875: 0.571 | BK875: 0.604 | BL875: 0.76463488 | BM875: Conserver | BN875: 0.74623742 | BO875: 2443 | BP875: 0.23495702 | BQ875: 2.2162162 | BR875: 0.2234957 | BS875: 0.089780325
A876: Donovan Mitchell | B876: CLE | C876: 28 | D876: 71 | E876: 55 | F876: 16 | G876: 31.4 | H876: 1704 | I876: 582 | J876: 1321 | K876: 44.3 | L876: 234 | M876: 632 | N876: 36.8 | O876: 298 | P876: 362 | Q876: 82.3 | R876: 57 | S876: 263 | T876: 320 | U876: 355 | V876: 149 | W876: 92 | X876: 14 | Y876: 142 | Z876: 2805 | AA876: 6 | AB876: 0 | AC876: 7.4 | AD876: 119.7 | AE876: 109.1 | AF876: 10.5 | AG876: 23.8 | AH876: 2.38 | AI876: 18 | AJ876: 2.5 | AK876: 11.2 | AL876: 6.9 | AM876: 7.6 | AN876: 53.1 | AO876: 57.5 | AP876: 29.8 | AQ876: 102.21 | AR876: 13.7 | AS876: 4762 | AT876: 24 | AU876: 5 | AV876: 4.5070423 | AW876: 0.8028169 | AX876: 3.7042254 | AY876: 1.2957746 | AZ876: 0.1971831 | BA876: 2.0985915 | BB876: 0.76433121 | BC876: 2.3825503 | BD876: 0.041266709 | BE876: 0.0062797165 | BF876: 0.025567417 | BG876: 0.11796896 | BH876: 30–39 min | BI876: 28–32 | BJ876: 0.531 | BK876: 0.575 | BL876: 0.7972239 | BM876: Conserver | BN876: 0.73400402 | BO876: 2229.4 | BP876: 0.15923567 | BQ876: 2.3825503 | BR876: 0.14353638 | BS876: 0.063694268
A877: Jalen Brunson | B877: NYK | C877: 28 | D877: 65 | E877: 40 | F877: 25 | G877: 35.4 | H877: 1690 | I877: 585 | J877: 1203 | K877: 48.8 | L877: 150 | M877: 397 | N877: 38.3 | O877: 371 | P877: 449 | Q877: 82.1 | R877: 26 | S877: 163 | T877: 189 | U877: 475 | V877: 163 | W877: 59 | X877: 7 | Y877: 137 | Z877: 2665 | AA877: 14 | AB877: 0 | AC877: 2.2 | AD877: 118.3 | AE877: 115.7 | AF877: 2.6 | AG877: 31.8 | AH877: 2.9 | AI877: 23.5 | AJ877: 1.2 | AK877: 7.2 | AL877: 4.2 | AM877: 8.1 | AN877: 55.1 | AO877: 60.5 | AP877: 28.9 | AQ877: 97.79 | AR877: 13.8 | AS877: 4697 | AT877: 26 | AU877: 7.3076923 | AV877: 2.9076923 | AW877: 0.4 | AX877: 2.5076923 | AY877: 0.90769231 | AZ877: 0.10769231 | BA877: 2.5076923 | BB877: 0.73446328 | BC877: 2.9141104 | BD877: 0.025641026 | BE877: 0.0030421556 | BF877: 0.011299435 | BG877: 0.070838766 | BH877: 30–39 min | BI877: 28–32 | BJ877: 0.551 | BK877: 0.605 | BL877: 0.72601086 | BM877: Conserver | BN877: 0.79517103 | BO877: 2301 | BP877: 0.20643199 | BQ877: 2.9141104 | BR877: 0.082138201 | BS877: 0.036940461
A878: Kevin Durant | B878: PHX | C878: 36 | D878: 62 | E878: 33 | F878: 29 | G878: 36.5 | H878: 1649 | I878: 589 | J878: 1122 | K878: 52.7 | L878: 161 | M878: 372 | N878: 43 | O878: 304 | P878: 360 | Q878: 83.9 | R878: 25 | S878: 353 | T878: 372 | U878: 260 | V878: 192 | W878: 50 | X878: 74 | Y878: 105 | Z878: 2678 | AA878: 5 | AB878: 0 | AC878: -0.6 | AD878: 116.5 | AE878: 117.4 | AF878: -1 | AG878: 18.8 | AH878: 1.38 | AI878: 15.2 | AJ878: 1.1 | AK878: 14.7 | AL878: 8.4 | AM878: 11 | AN878: 59.8 | AO878: 64.2 | AP878: 28.3 | AQ878: 99.49 | AR878: 14.2 | AS878: 4697 | AT878: 26.596774 | AU878: 4.1935484 | AV878: 6 | AW878: 0.40322581 | AX878: 5.6935484 | AY878: 0.80645161 | AZ878: 1.1935484 | BA878: 3.0967742 | BB878: 0.72867875 | BC878: 1.3541667 | BD878: 0.022094565 | BE878: 0.032699956 | BF878: 0.011047282 | BG878: 0.15598763 | BH878: 30–39 min | BI878: 33+ | BJ878: 0.598 | BK878: 0.642 | BL878: 0.67712734 | BM878: Conserver | BN878: 0.81342247 | BO878: 2263 | BP878: 0.11489174 | BQ878: 1.3541667 | BR878: 0.16438356 | BS878: 0.073059361
A879: Jaren Jackson Jr, | B879: MEM | C879: 25 | D879: 74 | E879: 42 | F879: 32 | G879: 29.8 | H879: 1643 | I879: 592 | J879: 1214 | K879: 48.8 | L879: 148 | M879: 392 | N879: 37.5 | O879: 311 | P879: 400 | Q879: 78.1 | R879: 89 | S879: 326 | T879: 414 | U879: 148 | V879: 155 | W879: 89 | X879: 111 | Y879: 259 | Z879: 2827 | AA879: 6 | AB879: 0 | AC879: 4.5 | AD879: 115.2 | AE879: 108.8 | AF879: 6.4 | AG879: 10.2 | AH879: 0.97 | AI879: 8.8 | AJ879: 3.8 | AK879: 13.4 | AL879: 8.7 | AM879: 9.1 | AN879: 54.8 | AO879: 59.1 | AP879: 27.4 | AQ879: 105.56 | AR879: 12.4 | AS879: 4863 | AT879: 22.202703 | AU879: 2 | AV879: 5.5945946 | AW879: 1.2027027 | AX879: 4.4054054 | AY879: 1.2027027 | AZ879: 1.5 | BA879: 2.0945946 | BB879: 0.74505714 | BC879: 0.95483871 | BD879: 0.040359151 | BE879: 0.05033557 | BF879: 0.040359151 | BG879: 0.1478324 | BH879: 20–29 min | BI879: 23–27 | BJ879: 0.548 | BK879: 0.591 | BL879: 0.73264937 | BM879: Écarter | BN879: 0.67903638 | BO879: 2205.2 | BP879: 0.067114094 | BQ879: 0.95483871 | BR879: 0.18773807 | BS879: 0.092810932
A880: Pascal Siakam | B880: IND | C880: 31 | D880: 78 | E880: 47 | F880: 31 | G880: 32.7 | H880: 1576 | I880: 616 | J880: 1186 | K880: 51.9 | L880: 125 | M880: 328 | N880: 38.9 | O880: 226 | P880: 304 | Q880: 73.4 | R880: 133 | S880: 406 | T880: 538 | U880: 265 | V880: 109 | W880: 70 | X880: 39 | Y880: 187 | Z880: 2847 | AA880: 11 | AB880: 0 | AC880: 4 | AD880: 114.5 | AE880: 108.9 | AF880: 5.5 | AG880: 15.5 | AH880: 2.41 | AI880: 15.6 | AJ880: 5.3 | AK880: 15.4 | AL880: 10.4 | AM880: 6.5 | AN880: 57.2 | AO880: 59.9 | AP880: 23.7 | AQ880: 101.43 | AR880: 13 | AS880: 5390 | AT880: 20.205128 | AU880: 3.3974359 | AV880: 6.8974359 | AW880: 1.7051282 | AX880: 5.2051282 | AY880: 0.8974359 | AZ880: 0.5 | BA880: 1.3974359 | BB880: 0.61789383 | BC880: 2.4311927 | BD880: 0.027444523 | BE880: 0.01529052 | BF880: 0.052144593 | BG880: 0.15917823 | BH880: 30–39 min | BI880: 28–32 | BJ880: 0.572 | BK880: 0.599 | BL880: 0.71575136 | BM880: Conserver | BN880: 0.61794356 | BO880: 2550.6 | BP880: 0.10389712 | BQ880: 2.4311927 | BR880: 0.21093076 | BS880: 0.084555268
A881: Darius Garland | B881: CLE | C881: 25 | D881: 75 | E881: 60 | F881: 15 | G881: 30.7 | H881: 1545 | I881: 555 | J881: 1178 | K881: 47.2 | L881: 210 | M881: 533 | N881: 40.1 | O881: 225 | P881: 255 | Q881: 87.8 | R881: 45 | S881: 165 | T881: 218 | U881: 503 | V881: 188 | W881: 90 | X881: 8 | Y881: 143 | Z881: 2678 | AA881: 7 | AB881: 0 | AC881: 6.7 | AD881: 123.2 | AE881: 113.4 | AF881: 9.9 | AG881: 30.9 | AH881: 2.68 | AI881: 25.6 | AJ881: 2.1 | AK881: 6.8 | AL881: 4.5 | AM881: 9.6 | AN881: 56.2 | AO881: 60 | AP881: 26.5 | AQ881: 101.32 | AR881: 12.6 | AS881: 4865 | AT881: 20.6 | AU881: 6.7066667 | AV881: 2.9066667 | AW881: 0.6 | AX881: 2.2 | AY881: 1.2 | AZ881: 0.10666667 | BA881: 2.5066667 | BB881: 0.67100977 | BC881: 2.6755319 | BD881: 0.039087948 | BE881: 0.0034744843 | BF881: 0.019543974 | BG881: 0.071661238 | BH881: 30–39 min | BI881: 23–27 | BJ881: 0.562 | BK881: 0.6 | BL881: 0.71092336 | BM881: Conserver | BN881: 0.63002012 | BO881: 2302.5 | BP881: 0.2184582 | BQ881: 2.6755319 | BR881: 0.094679696 | BS881: 0.045747376
A882: Coby White | B882: CHI | C882: 25 | D882: 74 | E882: 35 | F882: 39 | G882: 33.1 | H882: 1510 | I882: 511 | J882: 1117 | K882: 45.3 | L882: 215 | M882: 585 | N882: 37 | O882: 274 | P882: 303 | Q882: 90.2 | R882: 22 | S882: 252 | T882: 274 | U882: 333 | V882: 178 | W882: 67 | X882: 15 | Y882: 155 | Z882: 2412 | AA882: 2 | AB882: 0 | AC882: -1.9 | AD882: 111.5 | AE882: 113.9 | AF882: -2.5 | AG882: 19.7 | AH882: 1.86 | AI882: 18.8 | AJ882: 1 | AK882: 9.5 | AL882: 5.3 | AM882: 10.1 | AN882: 55 | AO882: 60.1 | AP882: 23.7 | AQ882: 105.37 | AR882: 10.3 | AS882: 5375 | AT882: 20.405405 | AU882: 4.5 | AV882: 3.7027027 | AW882: 0.2972973 | AX882: 3.4054054 | AY882: 0.90540541 | AZ882: 0.2027027 | BA882: 2.4054054 | BB882: 0.6164775 | BC882: 1.8707865 | BD882: 0.027353638 | BE882: 0.0061239487 | BF882: 0.0089817915 | BG882: 0.10288234 | BH882: 30–39 min | BI882: 23–27 | BJ882: 0.55 | BK882: 0.601 | BL882: 0.67410984 | BM882: Conserver | BN882: 0.62406874 | BO882: 2449.4 | BP882: 0.13595166 | BQ882: 1.8707865 | BR882: 0.11186413 | BS882: 0.048447239
A883: Jalen Williams | B883: OKC | C883: 24 | D883: 69 | E883: 55 | F883: 14 | G883: 32.4 | H883: 1490 | I883: 566 | J883: 1166 | K883: 48.4 | L883: 124 | M883: 338 | N883: 36.5 | O883: 235 | P883: 297 | Q883: 78.9 | R883: 62 | S883: 311 | T883: 366 | U883: 352 | V883: 152 | W883: 110 | X883: 48 | Y883: 159 | Z883: 2788 | AA883: 3 | AB883: 0 | AC883: 6.6 | AD883: 116.7 | AE883: 106.5 | AF883: 10.2 | AG883: 23.4 | AH883: 2.37 | AI883: 19.7 | AJ883: 2.6 | AK883: 13.1 | AL883: 7.9 | AM883: 8.3 | AN883: 53.7 | AO883: 57.3 | AP883: 27 | AQ883: 102.44 | AR883: 13.8 | AS883: 4760 | AT883: 21.594203 | AU883: 5.1014493 | AV883: 5.3043478 | AW883: 0.89855072 | AX883: 4.5072464 | AY883: 1.5942029 | AZ883: 0.69565217 | BA883: 2.2028986 | BB883: 0.66648774 | BC883: 2.3157895 | BD883: 0.049203793 | BE883: 0.021470746 | BF883: 0.027733047 | BG883: 0.13911254 | BH883: 30–39 min | BI883: 23–27 | BJ883: 0.537 | BK883: 0.573 | BL883: 0.70368135 | BM883: Conserver | BN883: 0.66042633 | BO883: 2235.6 | BP883: 0.15745214 | BQ883: 2.3157895 | BR883: 0.16371444 | BS883: 0.078129659
A884: Austin Reaves | B884: LAL | C884: 27 | D884: 73 | E884: 46 | F884: 27 | G884: 34.9 | H884: 1475 | I884: 475 | J884: 1037 | K884: 46 | L884: 197 | M884: 533 | N884: 37.7 | O884: 321 | P884: 365 | Q884: 87.7 | R884: 58 | S884: 270 | T884: 329 | U884: 423 | V884: 175 | W884: 80 | X884: 22 | Y884: 153 | Z884: 2635 | AA884: 9 | AB884: 1 | AC884: 2.7 | AD884: 117.1 | AE884: 113.3 | AF884: 3.8 | AG884: 24.1 | AH884: 2.38 | AI884: 23.6 | AJ884: 2.5 | AK884: 10.1 | AL884: 6.5 | AM884: 9.9 | AN884: 55.6 | AO884: 61.6 | AP884: 23 | AQ884: 99.86 | AR884: 11.8 | AS884: 5303 | AT884: 20.205479 | AU884: 5.7945205 | AV884: 4.5068493 | AW884: 0.79452055 | AX884: 3.6986301 | AY884: 1.0958904 | AZ884: 0.30136986 | BA884: 2.3972603 | BB884: 0.57895357 | BC884: 2.4171429 | BD884: 0.031400871 | BE884: 0.0086352396 | BF884: 0.022765632 | BG884: 0.10597794 | BH884: 30–39 min | BI884: 23–27 | BJ884: 0.556 | BK884: 0.616 | BL884: 0.62582981 | BM884: Conserver | BN884: 0.6179543 | BO884: 2547.7 | BP884: 0.16603211 | BQ884: 2.4171429 | BR884: 0.12913608 | BS884: 0.056390732
A885: De'Aaron Fox | B885: SAS | C885: 27 | D885: 62 | E885: 27 | F885: 35 | G885: 36.1 | H885: 1457 | I885: 539 | J885: 1166 | K885: 46.3 | L885: 118 | M885: 378 | N885: 31 | O885: 260 | P885: 316 | Q885: 82.7 | R885: 56 | S885: 242 | T885: 298 | U885: 391 | V885: 174 | W885: 93 | X885: 25 | Y885: 161 | Z885: 2579 | AA885: 9 | AB885: 0 | AC885: -1.1 | AD885: 113.7 | AE885: 114.9 | AF885: -1.2 | AG885: 26.2 | AH885: 2.25 | AI885: 21 | AJ885: 2.3 | AK885: 10.6 | AL885: 6.4 | AM885: 9.3 | AN885: 51.4 | AO885: 56 | AP885: 27.4 | AQ885: 102.22 | AR885: 11.9 | AS885: 4768 | AT885: 23.5 | AU885: 6.3064516 | AV885: 4.8064516 | AW885: 0.90322581 | AX885: 3.9032258 | AY885: 1.5 | AZ885: 0.40322581 | BA885: 2.8064516 | BB885: 0.65096953 | BC885: 2.2471264 | BD885: 0.041551247 | BE885: 0.01116969 | BF885: 0.025020105 | BG885: 0.1081226 | BH885: 30–39 min | BI885: 23–27 | BJ885: 0.514 | BK885: 0.56 | BL885: 0.70368135 | BM885: Conserver | BN885: 0.71871227 | BO885: 2238.2 | BP885: 0.17469395 | BQ885: 2.2471264 | BR885: 0.1331427 | BS885: 0.061954547
... A1129: Cody Williams | B1129: UTA | C1129: 20 | D1129: 50 | E1129: 9 | F1129: 41 | G1129: 21.2 | H1129: 230 | I1129: 85 | J1129: 255 | K1129: 32.3 | L1129: 35 | M1129: 135 | N1129: 25.9 | O1129: 30 | P1129: 40 | Q1129: 72.5 | R1129: 25 | S1129: 85 | T1129: 115 | U1129: 60 | V1129: 45 | W1129: 25 | X1129: 15 | Y1129: 95 | Z1129: 525 | AA1129: 0 | AB1129: 0 | AC1129: -6.8 | AD1129: 103 | AE1129: 118.5 | AF1129: -15.5 | AG1129: 7.8 | AH1129: 1.34 | AI1129: 15.6 | AJ1129: 2.4 | AK1129: 7.5 | AL1129: 4.9 | AM1129: 11.6 | AN1129: 39.1 | AO1129: 41.9 | AP1129: 12.2 | AQ1129: 103.19 | AR1129: 2.1 | AS1129: 2284 | AT1129: 4.6 | AU1129: 1.2 | AV1129: 2.3 | AW1129: 0.5 | AX1129: 1.7 | AY1129: 0.5 | AZ1129: 0.3 | BA1129: 0.9 | BB1129: 0.21698113 | BC1129: 1.3333333 | BD1129: 0.023584906 | BE1129: 0.014150943 | BF1129: 0.023584906 | BG1129: 0.080188679 | BH1129: 20–29 min | BI1129: 18–22 | BJ1129: 0.391 | BK1129: 0.419 | BL1129: 0.15389258 | BM1129: Écarter | BN1129: 0.1406841 | BO1129: 1060 | BP1129: 0.056603774 | BQ1129: 1.3333333 | BR1129: 0.10849057 | BS1129: 0.048742138
A1132: Filtre Top 15 Players par PTG_pg
A1134: Player | B1134: Team | C1134: Age | D1134: GP | E1134: W | F1134: L | G1134: Min | H1134: PTS | I1134: FGM | J1134: FGA | K1134: FG% | L1134: 15:00 | M1134: 3PA | N1134: 3P% | O1134: FTM | P1134: FTA | Q1134: FT% | R1134: OREB | S1134: DREB | T1134: REB | U1134: AST | V1134: TOV | W1134: STL | X1134: BLK | Y1134: PF | Z1134: FP | AA1134: DD2 | AB1134: TD3 | AC1134: +/- | AD1134: OFFRTG | AE1134: DEFRTG | AF1134: NETRTG | AG1134: AST% | AH1134: AST/TO | AI1134: AST RATIO | AJ1134: OREB% | AK1134: DREB% | AL1134: REB% | AM1134: TO RATIO | AN1134: EFG% | AO1134: TS% | AP1134: USG% | AQ1134: PACE | AR1134: PIE | AS1134: POSS | AT1134: PTS_pg | AU1134: AST_pg | AV1134: REB_pg | AW1134: OREB_pg | AX1134: DREB_pg | AY1134: STL_pg | AZ1134: BLK_pg | BA1134: TOV_pg | BB1134: PTS_pg/Min | BC1134: AST_pg/TOV_pg | BD1134: STL_pg/Min | BE1134: BLK_pg/Min | BF1134: OREB_pg/Min | BG1134: DREB_pg/Min | BH1134: Classe_Min | BI1134: Classe_Age | BJ1134: EFG%_corr | BK1134: TS%_corr | BL1134: FGA_norm | BM1134: Filtre joueur | BN1134: PTG_pg_Norm | BO1134: Min_tot | BP1134: AST/Min | BQ1134: AST/TOV | BR1134: REB_pg/Min | BS1134: Def Impact Score | BT1134: Moy. Gén. Réussite Tirs | BU1134: Moy. Gén. Réussite 3 Points | BV1134: Moy. Gén. Réussite Lancers Francs
...

Sheet Equipe
A1: Code | B1: Nom complet de l'équipe
A2: ATL | B2: Atlanta Hawks
A3: BKN | B3: Brooklyn Nets
A4: BOS | B4: Boston Celtics
A5: CHA | B5: Charlotte Hornets
A6: CHI | B6: Chicago Bulls
A7: CLE | B7: Cleveland Cavaliers
A8: DAL | B8: Dallas Mavericks
A9: DEN | B9: Denver Nuggets
A10: DET | B10: Detroit Pistons
A11: GSW | B11: Golden State Warriors
A12: HOU | B12: Houston Rockets
... A31: WAS | B31: Washington Wizards

Sheet Dictionnaire de donnée enrichi
A1: Dictionnaire du jeu de données initial
A2: Player | B2: Nom du joueur | C2: REB% | D2: Pourcentage de rebonds totaux parmi ceux disponibles
A3: Team | B3: Équipe du joueur (code à 3 lettres) | C3: TO RATIO | D3: Turnover Ratio – pertes de balle par 100 possessions
A4: Age | B4: Âge du joueur | C4: EFG% | D4: Effective Field Goal % (pondère les 3 points)
A5: GP | B5: Nombre de matchs joués (Games Played) | C5: TS% | D5: True Shooting % (inclut FG et FT dans l'efficacité)
A6: W | B6: Nombre de victoires de l'équipe lors des matchs joués | C6: USG% | D6: Usage Rate – % des actions utilisées par le joueur
A7: L | B7: Nombre de défaites | C7: PACE | D7: Rythme de jeu (possessions par 48 minutes)
A8: Min | B8: Minutes moyennes jouées par joueur par match | C8: PIE | D8: Player Impact Estimate – évaluation globale de l’impact
A9: PTS | B9: Points marqués par saison | C9: POSS | D9: Nombre total de possessions jouées
A10: FGM | B10: Tirs réussis par match (Field Goals Made)
A11: FGA | B11: Tirs tentés par match (Field Goals Attempted)
A12: FG% | B12: Pourcentage de réussite aux tirs
A13: 0.625 | B13: Minutes jouées après 15:00 de jeu
A14: 3PA | B14: Tirs à 3 points tentés par match
A15: 3P% | B15: Pourcentage de réussite à 3 points
A16: FTM | B16: Lancers francs réussis (Free Throws Made) | C16: Dictionnaire des données ajoutées
A17: FTA | B17: Lancers francs tentés | C17: Min_tot | D17: Minutes jouées par joueur par saison
A18: FT% | B18: Pourcentage de réussite aux lancers francs | C18: PTS_pg | D18: Points marquées en moyenne par match
A19: OREB | B19: Rebonds offensifs par saison | C19: PTS_pg/Min | D19: Points marquées en moyenne par minute
A20: DREB | B20: Rebonds défensifs par saison | C20: PTS_pg_Norm | D20: Normalisation de PTS_pg (entre 0 et 1)
A21: REB | B21: Rebonds totaux par saison | C21: FGA_norm | D21: Normalisation de FGA (entre 0 et 1)
A22: AST | B22: Passes décisives (Assists) par saison | C22: OREB_pg | D22: Rebonds offensifs en moyenne par match
A23: TOV | B23: Balles perdues (Turnovers) par saison | C23: DREB_pg | D23: Rebonds défensifs en moyenne par match
A24: STL | B24: Interceptions (Steals) par saison | C24: REB_pg | D24: Rebonds totaux en moyenne par match
A25: BLK | B25: Contres (Blocks) par saison | C25: OREB_pg/Min | D25: Rebonds offensifs en moyenne par minute
A26: PF | B26: Fautes personnelles | C26: DREB_pg/Min | D26: Rebonds défensifs en moyenne par minute
A27: FP | B27: Fantasy Points | C27: REB_pg/Min | D27: Rebonds totaux en moyenne par minute
A28: DD2 | B28: Double-doubles (≥10 dans deux catégories principales) | C28: AST_pg | D28: Passes décisives (Assists) en moyenne par match
A29: TD3 | B29: Triple-doubles (≥10 dans trois catégories principales) | C29: AST/Min | D29: Passes décisives par minute
A30: ="+ / -" -> + / - | B30: Plus-Minus (écart de score lorsque le joueur est sur le terrain) | C30: TOV_pg | D30: Balles perdues (Turnovers) en moyenne par match
A31: OFFRTG | B31: Offensive Rating (points marqués par 100 possessions) | C31: AST_pg/TOV_pg | D31: Ratio Passes / Pertes
A32: DEFRTG | B32: Defensive Rating (points encaissés par 100 possessions) | C32: STL_pg | D32: Interceptions (Steals) en moyenne par match
A33: NETRTG | B33: Net Rating = OFFRTG - DEFRTG | C33: STL_pg/Min | D33: Interceptions en moyenne par minute
A34: AST% | B34: Pourcentage d'assists – implication dans les passes décisives | C34: BLK_pg | D34: Contres (Blocks) en moyenne par match
A35: AST/TO | B35: Ratio passes / pertes de balle | C35: BLK_pg/Min | D35: Contres en moyenne par minute
A36: AST RATIO | B36: Ratio d’assists pour 100 possessions | C36: Def Impact Score | D36: Indicateur combiné STL_BLK_REB
A37: OREB% | B37: Pourcentage de rebonds offensifs parmi ceux disponibles | C37: EFG%_corr | D37: Normalisation de EFG% (entre 0 et 1)
A38: DREB% | B38: Idem en défensif | C38: TS%_corr | D38: Normalisation de TS% (entre 0 et 1)

Sheet Stats
A2: Statistiques _ Indicateurs de performance
A4: Statistique simple | B4: Age | C4: GP | D4: W | E4: L | F4: Min | G4: PTS | H4: FG% | I4: 3P% | J4: FT% | K4: REB | L4: AST | M4: TOV | N4: STL | O4: BLK | P4: AST% | Q4: AST/TO | R4: OREB% | S4: DREB% | T4: REB% | U4: EFG% | V4: TS% | W4: PTS_pg | X4: AST_pg | Y4: REB_pg | Z4: OREB_pg | AA4: DREB_pg | AB4: STL_pg | AC4: BLK_pg | AD4: TOV_pg | AE4: PTS_pg/Min | AF4: STL_pg/Min | AG4: BLK_pg/Min | AH4: OREB_pg/Min | AI4: DREB_pg/Min | AJ4: AST/Min | AK4: REB_pg/Min
A5: Moyenne | B5: 26.1529 | C5: 46.231986 | D5: 23.235501 | E5: 22.996485 | F5: 19.429174 | G5: 492.11775 | H5: 44.610896 | I5: 29.90246 | J5: 72.024077 | K5: 190.79086 | L5: 114.8348 | M5: 58.418278 | N5: 35.553603 | O5: 21.205624 | P5: 14.551318 | Q5: 1.873638 | R5: 4.8203866 | S5: 13.125308 | T5: 8.9442882 | U5: 51.719156 | V5: 54.554833 | W5: 8.8877017 | X5: 2.0856741 | Y5: 3.5966342 | Z5: 0.93807776 | AA5: 2.6631632 | AB5: 0.66894025 | AC5: 0.40483115 | AD5: 1.0906491 | AE5: 0.41782487 | AF5: 0.034718943 | AG5: 0.020908175 | AH5: 0.051304084 | AI5: 0.13620467 | AJ5: 0.1004946 | AK5: 0.18704194
A6: Max | B6: 40 | C6: 82 | D6: 64 | E6: 64 | F6: 37.7 | G6: 2485 | H6: 100 | I6: 100 | J6: 100 | K6: 1008 | L6: 882 | M6: 357 | N6: 228 | O6: 175 | P6: 55.6 | Q6: 11 | R6: 25 | S6: 44.4 | T6: 22.1 | U6: 125 | V6: 125 | W6: 32.697368 | X6: 11.605263 | Y6: 13.9 | Z6: 4.6034483 | AA6: 10.1 | AB6: 3 | AC6: 3.8043478 | AD6: 4.6973684 | AE6: 1.3513514 | AF6: 0.18518519 | AG6: 0.11458879 | AH6: 0.23529412 | AI6: 0.35087719 | AJ6: 0.32472613 | AK6: 0.47880691
A7: Min | B7: 19 | C7: 1 | D7: 0 | E7: 0 | F7: 0.9 | G7: 0 | H7: 0 | I7: 0 | J7: 0 | K7: 0 | L7: 0 | M7: 0 | N7: 0 | O7: 0 | P7: 0 | Q7: 0 | R7: 0 | S7: 0 | T7: 0 | U7: 0 | V7: 0 | W7: 0 | X7: 0 | Y7: 0 | Z7: 0 | AA7: 0 | AB7: 0 | AC7: 0 | AD7: 0 | AE7: 0 | AF7: 0 | AG7: 0 | AH7: 0 | AI7: 0 | AJ7: 0 | AK7: 0

Sheet Vue d'ensemble
A1: VUE D'ENSEMBLE DU JEU DE DONNEES
A3: 1️⃣ Structure descriptive
A5: Élément | B5: Valeur | C5: Objectif
A6: Nombre total de joueurs | B6: =COUNTA(_xlfn.UNIQUE('Données NBA enrichies'!A2:A570)) -> 569 | C6: Taille de l’échantillon
A7: Nombre d’équipes | B7: =COUNTA(_xlfn.UNIQUE('Données NBA enrichies'!B2:B570)) -> 30 | C7: Couverture du championnat
A8: Nombre moyen de matchs joués (GP) | B8: =AVERAGE('Données NBA enrichies'!D2:D570) -> 46.231986 | C8: Représentativité saisonnière
A9: Minutes moyennes par match | B9: =AVERAGE('Données NBA enrichies'!G2:G570) -> 19.429174 | C9: Charge de jeu moyenne
A10: Âge moyen des joueurs | B10: =AVERAGE('Données NBA enrichies'!C2:C570) -> 26.1529 | C10: Profil démographique
A11: Total de points marqués (PTS) | B11: =SUM('Données NBA enrichies'!H2:H570) -> 280015 | C11: Volume offensif global
A12: Total passes (AST) | B12: =SUM('Données NBA enrichies'!U2:U570) -> 65341 | C12: Création de jeu globale
A13: Total rebonds (REB) | B13: =SUM('Données NBA enrichies'!T2:T570) -> 108560 | C13: Activité au rebond
A14: Total interceptions (STL) | B14: =SUM('Données NBA enrichies'!W2:W570) -> 20230 | C14: Activité défensive
A15: Total contres (BLK) | B15: =SUM('Données NBA enrichies'!X2:X570) -> 12066 | C15: Protection du cercle
A17: 2️⃣ Répartition et variabilité
A19: Répartition du temps de jeu
A21: Tranche de minutes | B21: Nombre de Player
A22: <10 min | B22: 111
A23: 10–19 min | B23: 187
A24: 20–29 min | B24: 169
A25: 30–39 min | B25: 102
A26: Total général | B26: 569
A38: Répartition du scoring
A76: Top 15 Players selon Points moyens par jeu
A77: Joueurs | B77: Points / Jeu | C77: % Réussite Tirs | D77: Moy. Gén. % Tirs | E77: Nbre de tirs tentés
A78: Shai Gilgeous-Alexander | B78: 32.697368 | C78: 51.9 | D78: 44.610896 | E78: 1657
A79: Giannis Antetokounmpo | B79: 30.402985 | C79: 60.1 | D79: 44.610896 | E79: 1320
A80: Nikola Jokić | B80: 29.6 | C80: 57.6 | D80: 44.610896 | E80: 1365
A81: Luka Dončić | B81: 28.2 | C81: 45 | D81: 44.610896 | E81: 1025
A82: Anthony Edwards | B82: 27.594937 | C82: 44.7 | D82: 44.610896 | E82: 1612
A83: Jayson Tatum | B83: 26.805556 | C83: 45.2 | D83: 44.610896 | E83: 1462
A84: Kevin Durant | B84: 26.596774 | C84: 52.7 | D84: 44.610896 | E84: 1122
A85: Tyrese Maxey | B85: 26.307692 | C85: 43.7 | D85: 44.610896 | E85: 1092
A86: Cade Cunningham | B86: 26.1 | C86: 46.9 | D86: 44.610896 | E86: 1456
A87: Jalen Brunson | B87: 26 | C87: 48.8 | D87: 44.610896 | E87: 1203
A88: Paolo Banchero | B88: 25.891304 | C88: 45.2 | D88: 44.610896 | E88: 911
A89: Devin Booker | B89: 25.6 | C89: 46.1 | D89: 44.610896 | E89: 1418
... A92: Anthony Davis | B92: 24.705882 | C92: 51.6 | D92: 44.610896 | E92: 908
A93: Moyenne Top 15 | B93: 27.106036 | C93: 48.32 | D93: 44.610896
A116: Top 15 Players selon Points moyens par jeu
A117: Joueurs | B117: % Réussite Tirs | C117: % Réussite 3 Pts | D117: % Lanc. Franc | E117: Moy. Gén. % Tirs | F117: Moy. Gén. % 3 Points | G117: Moy. Gén. % Lanc. Francs | H117: Nbre de tirs tentés
A118: Anthony Davis | B118: 51.6 | C118: 28.2 | D118: 77.5 | E118: 44.610896 | F118: 29.90246 | G118: 72.024077 | H118: 1657
A119: Anthony Edwards | B119: 44.7 | C119: 39.5 | D119: 83.7 | E119: 44.610896 | F119: 29.90246 | G119: 72.024077 | H119: 1320
A120: Cade Cunningham | B120: 46.9 | C120: 35.6 | D120: 84.6 | E120: 44.610896 | F120: 29.90246 | G120: 72.024077 | H120: 1365
A121: Damian Lillard | B121: 44.8 | C121: 37.6 | D121: 92.1 | E121: 44.610896 | F121: 29.90246 | G121: 72.024077 | H121: 1025
A122: Devin Booker | B122: 46.1 | C122: 33.2 | D122: 89.4 | E122: 44.610896 | F122: 29.90246 | G122: 72.024077 | H122: 1612
A123: Giannis Antetokounmpo | B123: 60.1 | C123: 22.2 | D123: 61.7 | E123: 44.610896 | F123: 29.90246 | G123: 72.024077 | H123: 1462
A124: Jalen Brunson | B124: 48.8 | C124: 38.3 | D124: 82.1 | E124: 44.610896 | F124: 29.90246 | G124: 72.024077 | H124: 1122
A125: Jayson Tatum | B125: 45.2 | C125: 34.3 | D125: 81.4 | E125: 44.610896 | F125: 29.90246 | G125: 72.024077 | H125: 1092
A126: Kevin Durant | B126: 52.7 | C126: 43 | D126: 83.9 | E126: 44.610896 | F126: 29.90246 | G126: 72.024077 | H126: 1456
A127: LaMelo Ball | B127: 40.5 | C127: 33.9 | D127: 84.3 | E127: 44.610896 | F127: 29.90246 | G127: 72.024077 | H127: 1203
A128: Luka Dončić | B128: 45 | C128: 36.8 | D128: 78.2 | E128: 44.610896 | F128: 29.90246 | G128: 72.024077 | H128: 911
A129: Nikola Jokić | B129: 57.6 | C129: 41.7 | D129: 80 | E129: 44.610896 | F129: 29.90246 | G129: 72.024077 | H129: 1418
... A132: Tyrese Maxey | B132: 43.7 | C132: 33.7 | D132: 87.9 | E132: 44.610896 | F132: 29.90246 | G132: 72.024077 | H132: 908
A133: Moyenne Top 15 | B133: 48.32 | C133: 35.166667 | D133: 81.953333 | E133: 44.610896 | F133: 29.90246 | G133: 72.024077
A155: Répartition par âge
A157: Tranche d'âge | B157: Nombre de Player
A158: 18–22 | B158: 107
A159: 23–27 | B159: 284
A160: 28–32 | B160: 125
A161: 33+ | B161: 53
A162: Total général | B162: 569
A173: 3️⃣ Indicateurs moyens et extrêmes (Key Metrics)
A175: Indicateur | B175: Valeurs | C175: Libellé / Interprétation
A176: PTS_pg moyen | B176: =AVERAGE('Données NBA enrichies'!AT2:AT570) -> 8.8877017 | C176: Moyenne de points / joueur / match
A177: Top scorer (max) | B177: =MAX('Données NBA enrichies'!AT2:AT570) -> 32.697368 | C177: Joueur le plus prolifique
A178: FG% moyen (%) | B178: =AVERAGE('Données NBA enrichies'!K2:K570) -> 44.610896 | C178: Efficacité globale au tir
A179: 3P% moyen (%) | B179: =AVERAGE('Données NBA enrichies'!N2:N570) -> 29.90246 | C179: Précision à 3 points
A180: FT% moyen (%) | B180: =AVERAGE('Données NBA enrichies'!Q2:Q570) -> 72.024077 | C180: Fiabilité aux lancers
A181: AST_pg moyen | B181: =AVERAGE('Données NBA enrichies'!AU2:AU570) -> 2.0856741 | C181: Création collective
A182: REB_pg moyen | B182: =AVERAGE('Données NBA enrichies'!AV2:AV570) -> 3.5966342 | C182: Domination aérienne
A183: TS% moyen (%) | B183: =AVERAGE('Données NBA enrichies'!AO2:AO570) -> 54.554833 | C183: Efficacité totale au tir
A184: AST/TOV moyen | B184: =AVERAGE('Données NBA enrichies'!BC2:BC570) -> 1.938483 | C184: Maîtrise du jeu collectif
A185: STL_pg moyen | B185: =AVERAGE('Données NBA enrichies'!AY2:AY570) -> 0.66894025 | C185: Activité défensive moyenne
A186: BLK_pg moyen | B186: =AVERAGE('Données NBA enrichies'!AZ2:AZ570) -> 0.40483115 | C186: Protection du cercle moyenne
A187: 💬 Lecture :
A188: Si TS% > 60 % → très bonne efficacité offensive.
A189: Si AST/TOV > 2 → jeu collectif fluide.
A190: Si STL_pg > 1,5 et BLK_pg > 1 → défense active.
A192: VUES DIVERSES
A194: Equipe | B194: Nombre de Player | C194: Mesurer la profonduer des rosters
A195: PHI | B195: 23
A196: CHA | B196: 22
A197: NOP | B197: 22
A198: TOR | B198: 21
A199: MIN | B199: 20
A200: BKN | B200: 20
A201: IND | B201: 20
A202: CHI | B202: 20
A203: LAL | B203: 20
A204: MIL | B204: 19
A205: POR | B205: 19
A206: WAS | B206: 19
... A225: Total général | B225: 569
A230: Profil d'expérience
A232: Age | B232: Nombre de Player
A233: 19 | B233: 6
A234: 20 | B234: 19
A235: 21 | B235: 31
A236: 22 | B236: 51
A237: 23 | B237: 53
...

Sheet Production_Profil de tir
A2: PRODUCTION ET PROFIL DE TIR PAR EQUIPE
A4: 1️⃣ Points par équipe
A6: Equipes | B6: Somme de PTS_pg
A7: PHI | B7: 231.51161
A8: NOP | B8: 219.07615
A9: CHA | B9: 210.56634
A10: TOR | B10: 199.87183
A11: BKN | B11: 193.54481
A12: DAL | B12: 189.00385
A13: UTA | B13: 180.62856
A14: DET | B14: 179.49492
A15: ATL | B15: 174.46914
A16: CLE | B16: 166.11355
A17: Total général | B17: 1944.2808
A24: 2️⃣ Profil de tir par équipe
A41: Equipe | B41: Moyenne de FG% | C41: Moyenne de 3P% | D41: Moyenne de FT% | E41: Moyenne de EFG% | F41: Moyenne de TS% | G41: Somme de PTS_pg
A42: PHI | B42: 43.204348 | C42: 29.930435 | D42: 76.765217 | E42: 50.452174 | F42: 53.721739 | G42: 231.51161
A43: NOP | B43: 45.531818 | C43: 28.840909 | D43: 75.213636 | E43: 51.409091 | F43: 54.45 | G43: 219.07615
A44: CHA | B44: 43.218182 | C44: 31.627273 | D44: 78.722727 | E44: 50.013636 | F44: 53.590909 | G44: 210.56634
A45: TOR | B45: 43.061905 | C45: 27.419048 | D45: 74.17619 | E45: 48.914286 | F45: 52.17619 | G45: 199.87183
A46: BKN | B46: 40.66 | C46: 30.79 | D46: 74.39 | E46: 48.49 | F46: 51.82 | G46: 193.54481
A47: DAL | B47: 52.3 | C47: 29.552632 | D47: 74.563158 | E47: 57.747368 | F47: 60.478947 | G47: 189.00385
A48: UTA | B48: 43.983333 | C48: 29.933333 | D48: 75.888889 | E48: 51.533333 | F48: 54.777778 | G48: 180.62856
A49: DET | B49: 49.163158 | C49: 31.1 | D49: 68.247368 | E49: 56.389474 | F49: 59 | G49: 179.49492
A50: ATL | B50: 47.816667 | C50: 34.327778 | D50: 70.877778 | E50: 56.238889 | F50: 58.605556 | G50: 174.46914
A51: CLE | B51: 45.538889 | C51: 30.783333 | D51: 70.911111 | E51: 53.988889 | F51: 56.255556 | G51: 166.11355
A52: Total général | B52: 45.318 | C52: 30.3675 | D52: 74.1465 | E52: 52.345 | F52: 55.341 | G52: 1944.2808
A54: Equipe | B54: Moyenne de FG% | C54: Moyenne de 3P% | D54: Moyenne de FT% | E54: Moyenne de EFG% | F54: Moyenne de TS%
A55: PHI | B55: 43.204348 | C55: 29.930435 | D55: 76.765217 | E55: 50.452174 | F55: 53.721739
A56: NOP | B56: 45.531818 | C56: 28.840909 | D56: 75.213636 | E56: 51.409091 | F56: 54.45
A57: CHA | B57: 43.218182 | C57: 31.627273 | D57: 78.722727 | E57: 50.013636 | F57: 53.590909
A58: TOR | B58: 43.061905 | C58: 27.419048 | D58: 74.17619 | E58: 48.914286 | F58: 52.17619
A59: BKN | B59: 40.66 | C59: 30.79 | D59: 74.39 | E59: 48.49 | F59: 51.82
A60: DAL | B60: 52.3 | C60: 29.552632 | D60: 74.563158 | E60: 57.747368 | F60: 60.478947
A61: UTA | B61: 43.983333 | C61: 29.933333 | D61: 75.888889 | E61: 51.533333 | F61: 54.777778
A62: DET | B62: 49.163158 | C62: 31.1 | D62: 68.247368 | E62: 56.389474 | F62: 59
A63: ATL | B63: 47.816667 | C63: 34.327778 | D63: 70.877778 | E63: 56.238889 | F63: 58.605556
A64: CLE | B64: 45.538889 | C64: 30.783333 | D64: 70.911111 | E64: 53.988889 | F64: 56.255556
A65: Total général | B65: 45.318 | C65: 30.3675 | D65: 74.1465 | E65: 52.345 | F65: 55.341
A99: FG% : Pourcentage de tirs réussis 2 points et 3 points. _ FGA : Tirs tentés 2 pts et 3 pts _ FGM : Tirs réussis 2pts et 3 pts. FG% = FGM / FGA.
A100: 3P% : Pourcentage de tirs 3 points réussis. _ 3PA : Tirs 3 points tentés. _ 3PM : Tirs 3 points réussis. _ 3P% = 3PM / 3PA.
A101: FT% : Pourcentage de Lancers Francs réussis. _ FTA : Lancers francs tentés. _ FTM : Lancers francs réussis. _ FT% = FTM / FTA.
A102: EFG% : % de réussite aux tirs avec une pondération majorée des tirs 3 points. _ EFG% = [FGM + 0,5*(3P)] / FGA
A103: TS% : Efficacité globale au tire intégrant les 2 pts, les 3 pts et les lancers francs. _ TS% = PTS / [2×(FGA + 0,44×FTA)]
A105: Guide de lecture
A107: Une équipe avec 3P% élevé mais FT% moyen → style orienté “tir extérieur” (ex. Golden State).
A108: Une équipe avec FT% haut et FGA dans la raquette → style plus “intérieur / physique”.
A109: TS% et EFG% donnent la mesure finale d’efficacité globale : au-delà de 58 %, le rendement offensif est excellent.
A113: Production et profil de tir par équipe – Synthèse et enseignements
A115: L’analyse du profil de tir des équipes NBA 2024/2025 met en évidence une corrélation forte entre volume
A116: offensif et efficacité au tir.
... A124: 👉 Pour Les Pionniers, trois axes d’amélioration :
B126: privilégier la qualité de tir (eFG% > 52 %) plutôt que le volume ;
B127: maintenir un équilibre intérieur/extérieur dans les phases offensives ;
B128: développer la discipline sur la ligne des lancers francs pour capitaliser sur les fautes adverses.

Sheet Scoring_Efficacité_Individuelle
A2: Scoring et efficacité individuelle
A4: Joueurs | B4: Moyenne de PTS_pg
A5: Alexander | B5: 32.697368
A6: OKC | B6: 32.697368
A7: Antetokounmpo | B7: 30.402985
A8: MIL | B8: 30.402985
A9: Jokić | B9: 29.6
A10: DEN | B10: 29.6
A11: Dončić | B11: 28.2
A12: LAL | B12: 28.2
A13: Edwards | B13: 27.594937
A14: MIN | B14: 27.594937
A15: Tatum | B15: 26.805556
A16: BOS | B16: 26.805556
... A35: Total général | B35: 27.106036
A76: Productivité vs Efficacité
A78: Joueurs | B78: Points par match | C78: Moyenne de EFG% | D78: Moyenne de TS%
A79: Shai Gilgeous-Alexander | B79: 32.697368 | C79: 56.9 | D79: 63.7
A80: Giannis Antetokounmpo | B80: 30.402985 | C80: 60.7 | D80: 62.5
A81: Nikola Jokić | B81: 29.6 | C81: 62.7 | D81: 66.3
A82: Luka Dončić | B82: 28.2 | C82: 53.6 | D82: 58.7
A83: Anthony Edwards | B83: 27.594937 | C83: 54.7 | D83: 59.5
A84: Jayson Tatum | B84: 26.805556 | C84: 53.7 | D84: 58.2
A85: Kevin Durant | B85: 26.596774 | C85: 59.8 | D85: 64.2
A86: Tyrese Maxey | B86: 26.307692 | C86: 51.1 | D86: 56.2
A87: Cade Cunningham | B87: 26.1 | C87: 52.1 | D87: 56.5
A88: Jalen Brunson | B88: 26 | C88: 55.1 | D88: 60.5
A89: Paolo Banchero | B89: 25.891304 | C89: 50 | D89: 55.1
A90: Devin Booker | B90: 25.6 | C90: 52.5 | D90: 58.9
... A94: Total général | B94: 27.106036 | C94: 54.706667 | D94: 59.653333
A113: Visualisation de la productivité_efficacité des 1er, 7ème et 15ème scorers
A115: Valeurs | B115: Shai Gilgeous-Alexander
A116: Productivité (PTS_norm) | B116: 1
A117: Efficacité tirs (EFG%) | B117: 0.569
A118: Efficacité globale (TS%) | B118: 0.637
A150: Valeurs | B150: Kevin Durant
A151: Productivité (PTS_norm) | B151: 0.81
A152: Efficacité tirs (EFG%) | B152: 0.6
A153: Efficacité globale (TS%) | B153: 0.64
A187: Profil de performance offensive comparée des 1er, 7ème et 15ème scorer
B189: Joueurs | C189: Moyenne PTS_Norm | D189: Moyenne de EFG% | E189: Moyenne de TS%
B190: Shai Gilgeous-Alexander | C190: 1 | D190: 0.569 | E190: 0.637
B191: Kevin Durant | C191: 0.81342247 | D191: 0.598 | E191: 0.642
B192: Anthony Davis | C192: 0.75559238 | D192: 0.536 | E192: 0.588
A225: Scoring et efficacité individuelle – Synthèse et enseignements
A228: L’analyse du scoring individuel révèle que les meilleurs joueurs NBA allient volume offensif et efficacité de tir.
A230: Le top 15 des scoreurs affiche 27 points par match en moyenne, mais seuls quelques-uns — comme Jokić,
A231: Durant ou Alexander — dépassent un TS% de 60 %, gage d’un rendement réellement optimal.
A233: Cette distinction souligne que la performance ne repose pas uniquement sur la quantité de tirs, mais sur la
A234: sélection et la qualité des tentatives.
A236: Les indicateurs EFG% (pondérant les tirs à 3 pts) et TS% (incluant les lancers francs) montrent que la
A237: réussite dépend de la diversité offensive et de la capacité à provoquer des fautes.
A239: 👉 Pour Les Pionniers : privilégier la qualité de tir (EFG% ≥ 55 %), encourager un jeu varié et travailler la
A240: prise de décision rapide pour maximiser le rendement par possession.

Sheet Création jeu_Maîtrise
A1: Création du jeu et maîtrise _ Identifier les joueurs les plus influents dans la construction offensive
A2: (Passes, pertes, continuité du jeu)
A4: 1️⃣ Création du jeu individuel
A6: Identifier les meilleurs créateurs : volume de passes élevé, atio AST/TOV supérieur à 2 (= joueur fiable), forte contribution par minute.
A8: Ratio AST/TOV : > 2,5 (Créateur d'élite _ peu de pertes) _ Entre 1,5 et 2,5 (Bon gestionnaire) _ < 1,5 (Risque élevé de pertes)
A10: Top 15 AST / TOV
A12: Étiquettes de lignes | B12: Moyenne de AST/TOV
A13: Mason Jones | B13: 11
A14: Bobi Klintman | B14: 7
A15: Cam Spencer | B15: 7
A16: Jahmir Young | B16: 6
A17: Tyrese Haliburton | B17: 5.7435897
A18: TyTy Washington Jr, | B18: 5.3333333
A19: Tre Jones | B19: 5.2162162
A20: PJ Dozier | B20: 5
A21: Chuma Okeke | B21: 5
A22: Yuki Kawamura | B22: 5
A23: Miles McBride | B23: 4.8947368
A24: Jeff Dowtin Jr, | B24: 4.875
... A28: Total général | B28: 5.7442498
A39: Création vs Maîtrise _ Top 15 joueurs
B41: Ratio passes / pertes | C41: Passes / Minute
A42: Joueurs | B42: (AST/TOV) | C42: (AST/Min)
A43: Mason Jones | B43: 11 | C43: 0.24444444
A44: Bobi Klintman | B44: 7 | C44: 0.16509434
A45: Cam Spencer | B45: 7 | C45: 0.13861386
A46: Jahmir Young | B46: 6 | C46: 0.20408163
A47: Tyrese Haliburton | B47: 5.7435897 | C47: 0.2739726
A48: TyTy Washington Jr, | B48: 5.3333333 | C48: 0.13513514
A49: Tre Jones | B49: 5.2162162 | C49: 0.21297727
A50: PJ Dozier | B50: 5 | C50: 0.14245014
A51: Chuma Okeke | B51: 5 | C51: 0.076103501
A52: Yuki Kawamura | B52: 5 | C52: 0.21645022
A53: Miles McBride | B53: 4.8947368 | C53: 0.11671687
A54: Jeff Dowtin Jr, | B54: 4.875 | C54: 0.12598934
... A58: Total général | B58: 5.7442498 | C58: 2.6850208
A114: 2️⃣ Maîtrise collective du jeu par équipe
A117: Equipe | B117: Passes / Minute (AST/Min) | C117: Ratio passes / pertes (AST/TOV)
A118: CHI | B118: 2.2996468 | C118: 2.5564149
A119: SAC | B119: 2.1642471 | C119: 2.3693541
A120: CLE | B120: 1.7520049 | C120: 2.3110187
A121: OKC | B121: 1.6987834 | C121: 2.285283
A122: MEM | B122: 1.8591754 | C122: 2.2523268
A123: PHX | B123: 1.8520807 | C123: 2.2180559
A124: BOS | B124: 1.4532702 | C124: 2.2141862
A125: GSW | B125: 1.9609811 | C125: 2.1857904
A126: DET | B126: 2.2026104 | C126: 2.1551941
A127: IND | B127: 2.2115993 | C127: 2.1423861
A128: ATL | B128: 1.8644355 | C128: 2.0941876
A129: SAS | B129: 1.8862139 | C129: 2.0859391
... A133: Total général | B133: 28.511574 | C133: 2.1893928
A137: 🎯 Lecture :
A139: Équipe haute sur les deux axes → circulation fluide et maîtrisée.
A140: Équipe forte en AST/Min mais faible en AST/TOV → jeu risqué ou désorganisé.
A189: Création du jeu et maîtrise – Synthèse et enseignements
A192: L’analyse de la création de jeu révèle une forte corrélation entre volume de passes et maîtrise collective.
A194: Les meilleurs créateurs (Jones, Klintman, Haliburton) affichent un AST/TOV supérieur à 5, signe d’un jeu sûr
A195: et fluide.
A197: Au niveau collectif, Chicago, Sacramento et Cleveland se distinguent par un ratio global supérieur à 2,3,
A198: garantissant une circulation efficace.
A200: 👉 Pour Les Pionniers : viser un AST/TOV ≥ 2,0, former les joueurs à la lecture du jeu, et privilégier les
A201: profils à fort rendement collectif plutôt que la seule créativité individuelle.

Sheet Rebond_Défense
A1: Top 15 des "rebondeurs"
A2: Hiérarchisation des joueurs les plus actifs au rebond.
A3: Joueur | B3: Rebonds (REB) /Min
A4: Oscar Tshiebwe | B4: 0.47880691
A5: DeAndre Jordan | B5: 0.41521487
A6: Andre Drummond | B6: 0.41489362
A7: Tristan Thompson | B7: 0.41463415
A8: N'Faly Dante | B8: 0.41338583
A9: Ron Harper Jr, | B9: 0.41176471
A10: Jonas Valančiūnas | B10: 0.40977147
A11: Steven Adams | B11: 0.40901082
A12: Kevon Looney | B12: 0.40701754
A13: Walker Kessler | B13: 0.40689655
A14: Tazé Moore | B14: 0.4040404
A15: Charles Bassey | B15: 0.40331197
... A19: Total général | B19: 0.41238067
A40: Spécialistes défensifs
A41: Jeu et agressivité défensive (Interceptions)
A42: Joueurs | B42: Interceptions (STL) / Min
A43: Dyson Daniels | B43: 0.088757396
A44: Alex Caruso | B44: 0.082517751
A45: Ausar Thompson | B45: 0.075329567
A46: Kris Dunn | B46: 0.070651564
A47: Tari Eason | B47: 0.06834355
A48: Cason Wallace | B48: 0.065004263
A49: T,J, McConnell | B49: 0.06152323
A50: Keon Ellis | B50: 0.06147541
A51: Dejounte Murray | B51: 0.061349693
A52: Scotty Pippen Jr, | B52: 0.061211149
A53: Jonathan Isaac | B53: 0.058533016
A54: Kevin Porter Jr, | B54: 0.055892256
... A58: Total général | B58: 0.065030266
A77: Jeu et agressivité défensive (Contres)
A78: Joueurs | B78: Contres (BLK) / Min
A79: Victor Wembanyama | B79: 0.11458879
A80: Daniel Gafford | B80: 0.084047328
A81: Donovan Clingan | B81: 0.080657319
A82: Walker Kessler | B82: 0.079885057
A83: Jonathan Isaac | B83: 0.071337114
A84: Isaiah Stewart | B84: 0.070491346
A85: Goga Bitadze | B85: 0.068627451
A86: Myles Turner | B86: 0.066225166
A87: Anthony Davis | B87: 0.065750851
A88: Zach Edey | B88: 0.060606061
A89: Brook Lopez | B89: 0.059748428
A90: Peyton Watson | B90: 0.057492133
... A94: Total général | B94: 0.069432676
A114: Indice de performance défensive synthétique [Def Impact Score = Moyenne(STL/Min;BLK/Min;REB/Min)]
A116: Étiquettes de lignes | B116: Moyenne de Def Impact Score
A117: Walker Kessler | B117: 0.16896552
A118: Donovan Clingan | B118: 0.16835017
A119: Kevon Looney | B119: 0.16023392
A120: Victor Wembanyama | B120: 0.15976951
A121: Clint Capela | B121: 0.15746248
A122: Zach Edey | B122: 0.15668311
A123: Jonas Valančiūnas | B123: 0.15629104
A124: Jalen Duren | B124: 0.15456659
A125: Mark Williams | B125: 0.15179995
A126: Isaiah Hartenstein | B126: 0.15070532
A127: Anthony Davis | B127: 0.1497006
A128: Jusuf Nurkić | B128: 0.14925842
... A132: Total général | B132: 0.15442879
A152: Rebonds et défense – Synthèse et enseignements
A155: L’étude défensive met en évidence des profils complets combinant rebond, interception et contre.
A157: Les leaders — Kessler, Clingan, Wembanyama et Capela — atteignent un Def Impact Score de 0,17, contre
A158: 0,15 en moyenne.
A160: Cet indicateur global mesure la présence défensive réelle plutôt que le volume brut.
A162: 👉 Pour Les Pionniers : viser un Def Impact Score ≥ 0,15, former les joueurs à la lecture du jeu défensif, et
A163: privilégier la polyvalence (capacité à protéger le cercle et relancer).

Sheet Synthèse générale
A2: Synthèse générale – Profils types et leviers clés
A5: L’analyse des données NBA 2024/2025 met en évidence trois profils de performance dont le club
A6: Les Pionniers peut s’inspirer pour structurer son développement sportif.
A8: 1. Le Shooter extérieur
A10: Spécialiste du tir longue distance (3PA/FGA > 0,4, TS% > 60 %), il optimise la sélection de tirs et contribue à
A11: espacer le jeu.
A12: ➡️ Levier : viser un eFG% ≥ 55 %, travailler la mécanique de shoot et la création d’espaces ouverts.
A14: 2. Le Créateur sûr
A16: Joueur intelligent et collectif (AST/TOV ≥ 2, AST/Min > 0,12), garant de la fluidité offensive et de la maîtrise du
A17: tempo.
A18: ➡️ Levier : instaurer un objectif collectif AST/TOV ≥ 2,0, renforcer la lecture du jeu et limiter les pertes de
A19: balle.
... A41: un jeu lucide, collectif et discipliné, garant de progression durable et de succès à moyen terme.
